Workbook

Sheet Top WS
J1: =$H$4+($H$4*J3) -> 3600 | K1: =$H$4+($H$4*K3) -> 3800
J2: 4000 | K2: 4000 | L2: =$H$4+($H$4*L3) -> 4000 | M2: =$H$4+($H$4*M3) -> 4120 | N2: =$H$4+($H$4*N3) -> 4320 | O2: =$H$4+($H$4*O3) -> 4400 | P2: =$H$4+($H$4*P3) -> 4600 | Q2: =$H$4+($H$4*Q3) -> 4800 | R2: =$H$4+($H$4*R3) -> 5200
D3: Incentive base | I3: Money | J3: -0.1 | K3: -0.05 | L3: 0 | M3: 0.03 | N3: 0.08 | O3: 0.1 | P3: 0.15 | Q3: 0.2 | R3: 0.3 | U3: Simulation
C4: Depot | D4: Now | E4: New | G4: Incentive $ | H4: 4000 | I4: GOAL | J4: 0.9 | K4: 0.95 | L4: 1 | M4: 1.03 | N4: 1.06 | O4: 1.1 | P4: 1.15 | Q4: 1.2 | R4: 1.3 | W4: 45566 | X4: 45597 | Y4: 45627 | Z4: Total
C5: Area Manger | D5: 5000 | E5: 5000 | U5: Real | V5: Sales (1-2-3-4) | W5: 5000 | X5: 5000 | Y5: 5000 | Z5: =SUM(W5:Y5) -> 15000
C6: Depocho | D6: 4000 | E6: 4000 | G6: G1(CORE) | H6: 0.05 | I6: AJINOMOTO | J6: =H6*$J$2 -> 200 | K6: =H6*$K$2 -> 200 | L6: =H6*$L$2 -> 200 | M6: =H6*$M$2 -> 206 | N6: =H6*$N$2 -> 216 | O6: =H6*$O$2 -> 220 | P6: =H6*$P$2 -> 230 | Q6: =H6*$Q$2 -> 240 | R6: =H6*$R$2 -> 260
C7: D.Depocho | D7: 4000 | E7: 4000 | H7: 0.1 | I7: ROSDEE | J7: =H7*$J$2 -> 400 | K7: =H7*$K$2 -> 400 | L7: =H7*$L$2 -> 400 | M7: =H7*$M$2 -> 412 | N7: =H7*$N$2 -> 432 | O7: =H7*$O$2 -> 440 | P7: =H7*$P$2 -> 460 | Q7: =H7*$Q$2 -> 480 | R7: =H7*$R$2 -> 520 | U7: New Metod | V7: Sales 1 | W7: 6000 | X7: 5000 | Y7: 4500 | Z7: =SUM(W7:Y7) -> 15500
C8: CV | D8: 2500 | E8: 2500 | H8: 0.2 | I8: BIRDY | J8: =H8*$J$2 -> 800 | K8: =H8*$K$2 -> 800 | L8: =H8*$L$2 -> 800 | M8: =H8*$M$2 -> 824 | N8: =H8*$N$2 -> 864 | O8: =H8*$O$2 -> 880 | P8: =H8*$P$2 -> 920 | Q8: =H8*$Q$2 -> 960 | R8: =H8*$R$2 -> 1040 | V8: Sales 2 | W8: =I39 -> 1244 | X8: 5200 | Y8: 5000 | Z8: =SUM(W8:Y8) -> 11444
C9: Driver | D9: 1200 | E9: 1200 | V9: Sales3 | W9: 5000 | X9: 4900 | Y9: 6500 | Z9: =SUM(W9:Y9) -> 16400 | AA9: =Z9/Z5 -> 1.0933333
C10: CVFV | E10: 2500 | G10: G2(GD) | H10: 0.05 | I10: AJI-PLUS | J10: =H10*$J$2 -> 200 | K10: =H10*$K$2 -> 200 | L10: =H10*$L$2 -> 200 | M10: =H10*$M$2 -> 206 | N10: =H10*$N$2 -> 216 | O10: =H10*$O$2 -> 220 | P10: =H10*$P$2 -> 230 | Q10: =H10*$Q$2 -> 240 | R10: =H10*$R$2 -> 260 | V10: Sales 4 | W10: 4800 | X10: 4000 | Y10: 5000 | Z10: =SUM(W10:Y10) -> 13800
C11: WSF | E11: 3500 | H11: 0.1 | I11: ROSDEE CUBE | J11: =H11*$J$2 -> 400 | K11: =H11*$K$2 -> 400 | L11: =H11*$L$2 -> 400 | M11: =H11*$M$2 -> 412 | N11: =H11*$N$2 -> 432 | O11: =H11*$O$2 -> 440 | P11: =H11*$P$2 -> 460 | Q11: =H11*$Q$2 -> 480 | R11: =H11*$R$2 -> 520 | Y11: Average | Z11: =MEDIAN(Z7:Z10) -> 14650 | AA11: =Z11/Z5-1 -> -0.023333333
C12: WH | E12: 3500 | H12: 0.05 | I12: ROSDEE MENU | J12: =H12*$J$2 -> 200 | K12: =H12*$K$2 -> 200 | L12: =H12*$L$2 -> 200 | M12: =H12*$M$2 -> 206 | N12: =H12*$N$2 -> 216 | O12: =H12*$O$2 -> 220 | P12: =H12*$P$2 -> 230 | Q12: =H12*$Q$2 -> 240 | R12: =H12*$R$2 -> 260
H13: 0.1 | I13: ROSDEE NOODLE | J13: =H13*$J$2 -> 400 | K13: =H13*$K$2 -> 400 | L13: =H13*$L$2 -> 400 | M13: =H13*$M$2 -> 412 | N13: =H13*$N$2 -> 432 | O13: =H13*$O$2 -> 440 | P13: =H13*$P$2 -> 460 | Q13: =H13*$Q$2 -> 480 | R13: =H13*$R$2 -> 520
J14: =H14*$J$2 -> 0 | K14: =H14*$K$2 -> 0 | L14: =H14*$L$2 -> 0 | M14: =H14*$M$2 -> 0 | N14: =H14*$N$2 -> 0 | O14: =H14*$O$2 -> 0 | P14: =H14*$P$2 -> 0 | Q14: =H14*$Q$2 -> 0 | R14: =H14*$R$2 -> 0
G16: G3(BB) | H16: 0.15 | I16: YUMYUM | J16: =H16*$J$2 -> 600 | K16: =H16*$K$2 -> 600 | L16: =H16*$L$2 -> 600 | M16: =H16*$M$2 -> 618 | N16: =H16*$N$2 -> 648 | O16: =H16*$O$2 -> 660 | P16: =H16*$P$2 -> 690 | Q16: =H16*$Q$2 -> 720 | R16: =H16*$R$2 -> 780 | U16: Cascade concept
H17: 0.1 | I17: POWDER COFFEE | J17: =H17*$J$2 -> 400 | K17: =H17*$K$2 -> 400 | L17: =H17*$L$2 -> 400 | M17: =H17*$M$2 -> 412 | N17: =H17*$N$2 -> 432 | O17: =H17*$O$2 -> 440 | P17: =H17*$P$2 -> 460 | Q17: =H17*$Q$2 -> 480 | R17: =H17*$R$2 -> 520
U18: Salesman | V18: Incentive
B19: AJINOMOTO | C19: ROSDEE | D19: BIRDY | E19: AJI Plus | G19: Others | H19: 0.05 | I19: Takumi-Aji | J19: =H19*$J$2 -> 200 | K19: =H19*$K$2 -> 200 | L19: =H19*$L$2 -> 200 | M19: =H19*$M$2 -> 206 | N19: =H19*$N$2 -> 216 | O19: =H19*$O$2 -> 220 | P19: =H19*$P$2 -> 230 | Q19: =H19*$Q$2 -> 240 | R19: =H19*$R$2 -> 260
A20: 0 | B20: =J10 -> 200 | C20: =J11 -> 400 | D20: =J12 -> 200 | E20: =J13 -> 400 | H20: 0.05 | I20: ROSDEE MENU KKR | J20: =H20*$J$2 -> 200 | K20: =H20*$K$2 -> 200 | L20: =H20*$L$2 -> 200 | M20: =H20*$M$2 -> 206 | N20: =H20*$N$2 -> 216 | O20: =H20*$O$2 -> 220 | P20: =H20*$P$2 -> 230 | Q20: =H20*$Q$2 -> 240 | R20: =H20*$R$2 -> 260 | U20: All Depot Salesman | V20: Depocho | W20: incentive
A21: 0.90001 | B21: =K10 -> 200 | C21: =K11 -> 400 | D21: =K12 -> 200 | E21: =K13 -> 400
A22: 0.95001 | B22: =L10 -> 200 | C22: =L11 -> 400 | D22: =L12 -> 200 | E22: =L13 -> 400 | U22: All Area depot result | V22: Area Manager | W22: Incentive
A23: 1.00001 | B23: =M10 -> 206 | C23: =M11 -> 412 | D23: =M12 -> 206 | E23: =M13 -> 412
A24: 1.03001 | B24: =N10 -> 216 | C24: =N11 -> 432 | D24: =N12 -> 216 | E24: =N13 -> 432 | U24: All Area manager Result | V24: Division manager | W24: Incetive
A25: =106.001% -> 1.06001 | B25: =O10 -> 220 | C25: =O11 -> 440 | D25: =O12 -> 220 | E25: =O13 -> 440
A26: =110.001% -> 1.10001 | B26: =P10 -> 230 | C26: =P11 -> 460 | D26: =P12 -> 230 | E26: =P13 -> 460
A27: =115.001% -> 1.15001 | B27: =Q10 -> 240 | C27: =Q11 -> 480 | D27: =Q12 -> 240 | E27: =Q13 -> 480
A28: =120.001% -> 1.20001 | B28: =R10 -> 260 | C28: =R11 -> 520 | D28: =R12 -> 260 | E28: =R13 -> 520
H30: =SUM(H6:H29) -> 1
I31: TOTAL | J31: =SUM(J6:J29) -> 4000 | K31: =SUM(K6:K29) -> 4000 | L31: =SUM(L6:L29) -> 4000 | M31: =SUM(M6:M29) -> 4120 | N31: =SUM(N6:N29) -> 4320 | O31: =SUM(O6:O29) -> 4400 | P31: =SUM(P6:P29) -> 4600 | Q31: =SUM(Q6:Q29) -> 4800 | R31: =SUM(R6:R29) -> 5200
G33: EXTRA | H33: Special KPI
H35: G1 | O35: =O6 -> 220
H36: G2 | J36: =J10 -> 200
H37: G3 | M37: =M16 -> 618
H38: Ot | M38: =M19 -> 206
H39: TOTAL | I39: =SUM(I35:R38) -> 1244
H41: Extreme | I41: <80% | J41: 80% to <90% | K41: 90% to <95% | L41: 95% to <100% | M41: 100% to <105% | N41: 105% to <110% | O41: 110% to <115% | P41: 115% to < 120% | Q41: 120% to <130% | R41: >130%
I42: 0 | J42: 1200 | K42: 1350 | L42: =1425 -> 1425 | M42: 1500 | N42: 1575 | O42: 1725 | P42: 1875 | Q42: 1950 | R42: 2100
H43: Money | J43: -0.2 | K43: -0.1 | L43: -0.05 | N43: 0.05 | O43: 0.15 | P43: 0.25 | Q43: 0.3 | R43: 0.4
H44: Option1 | I44: <80% | J44: 80% to <90% | K44: 90% to <95% | L44: 95% to <100% | M44: 1 | N44: >100% to <=105% | O44: >105% to <=110% | P44: >110% to <=115% | Q44: >115% to < =120% | R44: >120% to > 130%
H45: G1 | I45: =J6 -> 200 | J45: =J6 -> 200 | K45: =K6 -> 200 | L45: =L6 -> 200 | M45: =M6 -> 206 | N45: =N6 -> 216 | O45: =O6 -> 220 | P45: =P6 -> 230 | Q45: =Q6 -> 240 | R45: =R6 -> 260
H46: G2 | I46: =J10 -> 200 | J46: =J10 -> 200 | K46: =K10 -> 200 | L46: =L10 -> 200 | M46: =M10 -> 206 | N46: =N10 -> 216 | O46: =O10 -> 220 | P46: =P10 -> 230 | Q46: =Q10 -> 240 | R46: =R10 -> 260
H47: G3 | I47: =J16 -> 600 | J47: =J16 -> 600 | K47: =K16 -> 600 | L47: =L16 -> 600 | M47: =M16 -> 618 | N47: =N16 -> 648 | O47: =O16 -> 660 | P47: =P16 -> 690 | Q47: =Q16 -> 720 | R47: =R16 -> 780
H48: G4 | I48: =J19 -> 200 | J48: =J19 -> 200 | K48: =K19 -> 200 | L48: =L19 -> 200 | M48: =M19 -> 206 | N48: =N19 -> 216 | O48: =O19 -> 220 | P48: =P19 -> 230 | Q48: =Q19 -> 240 | R48: =R19 -> 260

Sheet  WS SF
J1: =$H$4+($H$4*J3) -> 3150 | K1: =$H$4+($H$4*K3) -> 3325
J2: 3500 | K2: 3500 | L2: =$H$4+($H$4*L3) -> 3500 | M2: =$H$4+($H$4*M3) -> 3605 | N2: =$H$4+($H$4*N3) -> 3780 | O2: =$H$4+($H$4*O3) -> 3850 | P2: =$H$4+($H$4*P3) -> 4025 | Q2: =$H$4+($H$4*Q3) -> 4200 | R2: =$H$4+($H$4*R3) -> 4550
D3: Incentive base | I3: Money | J3: -0.1 | K3: -0.05 | L3: 0 | M3: 0.03 | N3: 0.08 | O3: 0.1 | P3: 0.15 | Q3: 0.2 | R3: 0.3 | U3: Simulation
C4: Depot | D4: Now | E4: New | G4: Incentive $ | H4: 3500 | I4: GOAL | J4: 0.9 | K4: 0.95 | L4: 1 | M4: 1.03 | N4: 1.06 | O4: 1.1 | P4: 1.15 | Q4: 1.2 | R4: 1.3 | W4: 45566 | X4: 45597 | Y4: 45627 | Z4: Total
C5: Area Manger | D5: 5000 | E5: 5000 | U5: Real | V5: Sales (1-2-3-4) | W5: 5000 | X5: 5000 | Y5: 5000 | Z5: =SUM(W5:Y5) -> 15000
C6: Depocho | D6: 4000 | E6: 4000 | G6: G1(CORE) | H6: 0.05 | I6: AJINOMOTO | J6: =H6*$J$2 -> 175 | K6: =H6*$K$2 -> 175 | L6: =H6*$L$2 -> 175 | M6: =H6*$M$2 -> 180.25 | N6: =H6*$N$2 -> 189 | O6: =H6*$O$2 -> 192.5 | P6: =H6*$P$2 -> 201.25 | Q6: =H6*$Q$2 -> 210 | R6: =H6*$R$2 -> 227.5
C7: D.Depocho | D7: 4000 | E7: 4000 | H7: 0.1 | I7: ROSDEE | J7: =H7*$J$2 -> 350 | K7: =H7*$K$2 -> 350 | L7: =H7*$L$2 -> 350 | M7: =H7*$M$2 -> 360.5 | N7: =H7*$N$2 -> 378 | O7: =H7*$O$2 -> 385 | P7: =H7*$P$2 -> 402.5 | Q7: =H7*$Q$2 -> 420 | R7: =H7*$R$2 -> 455 | U7: New Metod | V7: Sales 1 | W7: 6000 | X7: 5000 | Y7: 4500 | Z7: =SUM(W7:Y7) -> 15500
C8: CV | D8: 2500 | E8: 2500 | H8: 0.1 | I8: BIRDY | J8: =H8*$J$2 -> 350 | K8: =H8*$K$2 -> 350 | L8: =H8*$L$2 -> 350 | M8: =H8*$M$2 -> 360.5 | N8: =H8*$N$2 -> 378 | O8: =H8*$O$2 -> 385 | P8: =H8*$P$2 -> 402.5 | Q8: =H8*$Q$2 -> 420 | R8: =H8*$R$2 -> 455 | V8: Sales 2 | W8: =I39 -> 1088.5 | X8: 5200 | Y8: 5000 | Z8: =SUM(W8:Y8) -> 11288.5
C9: Driver | D9: 1200 | E9: 1200 | V9: Sales3 | W9: 5000 | X9: 4900 | Y9: 6500 | Z9: =SUM(W9:Y9) -> 16400 | AA9: =Z9/Z5 -> 1.0933333
C10: CVFV | E10: 2500 | G10: G2(GD) | H10: 0.05 | I10: AJI-PLUS | J10: =H10*$J$2 -> 175 | K10: =H10*$K$2 -> 175 | L10: =H10*$L$2 -> 175 | M10: =H10*$M$2 -> 180.25 | N10: =H10*$N$2 -> 189 | O10: =H10*$O$2 -> 192.5 | P10: =H10*$P$2 -> 201.25 | Q10: =H10*$Q$2 -> 210 | R10: =H10*$R$2 -> 227.5 | V10: Sales 4 | W10: 4800 | X10: 4000 | Y10: 5000 | Z10: =SUM(W10:Y10) -> 13800
C11: WSF | E11: 3500 | H11: 0.1 | I11: ROSDEE CUBE | J11: =H11*$J$2 -> 350 | K11: =H11*$K$2 -> 350 | L11: =H11*$L$2 -> 350 | M11: =H11*$M$2 -> 360.5 | N11: =H11*$N$2 -> 378 | O11: =H11*$O$2 -> 385 | P11: =H11*$P$2 -> 402.5 | Q11: =H11*$Q$2 -> 420 | R11: =H11*$R$2 -> 455 | Y11: Average | Z11: =MEDIAN(Z7:Z10) -> 14650 | AA11: =Z11/Z5-1 -> -0.023333333
C12: WH | E12: 3500 | H12: 0.1 | I12: ROSDEE MENU | J12: =H12*$J$2 -> 350 | K12: =H12*$K$2 -> 350 | L12: =H12*$L$2 -> 350 | M12: =H12*$M$2 -> 360.5 | N12: =H12*$N$2 -> 378 | O12: =H12*$O$2 -> 385 | P12: =H12*$P$2 -> 402.5 | Q12: =H12*$Q$2 -> 420 | R12: =H12*$R$2 -> 455
H13: 0.1 | I13: ROSDEE NOODLE | J13: =H13*$J$2 -> 350 | K13: =H13*$K$2 -> 350 | L13: =H13*$L$2 -> 350 | M13: =H13*$M$2 -> 360.5 | N13: =H13*$N$2 -> 378 | O13: =H13*$O$2 -> 385 | P13: =H13*$P$2 -> 402.5 | Q13: =H13*$Q$2 -> 420 | R13: =H13*$R$2 -> 455
J14: =H14*$J$2 -> 0 | K14: =H14*$K$2 -> 0 | L14: =H14*$L$2 -> 0 | M14: =H14*$M$2 -> 0 | N14: =H14*$N$2 -> 0 | O14: =H14*$O$2 -> 0 | P14: =H14*$P$2 -> 0 | Q14: =H14*$Q$2 -> 0 | R14: =H14*$R$2 -> 0
G16: G3(BB) | H16: 0.15 | I16: YUMYUM | J16: =H16*$J$2 -> 525 | K16: =H16*$K$2 -> 525 | L16: =H16*$L$2 -> 525 | M16: =H16*$M$2 -> 540.75 | N16: =H16*$N$2 -> 567 | O16: =H16*$O$2 -> 577.5 | P16: =H16*$P$2 -> 603.75 | Q16: =H16*$Q$2 -> 630 | R16: =H16*$R$2 -> 682.5 | U16: Cascade concept
H17: 0.15 | I17: POWDER COFFEE | J17: =H17*$J$2 -> 525 | K17: =H17*$K$2 -> 525 | L17: =H17*$L$2 -> 525 | M17: =H17*$M$2 -> 540.75 | N17: =H17*$N$2 -> 567 | O17: =H17*$O$2 -> 577.5 | P17: =H17*$P$2 -> 603.75 | Q17: =H17*$Q$2 -> 630 | R17: =H17*$R$2 -> 682.5
U18: Salesman | V18: Incentive
B19: AJI Plus | C19: RDQ | D19: RDM | E19: RDNS | G19: Others | H19: 0.05 | I19: Takumi-Aji | J19: =H19*$J$2 -> 175 | K19: =H19*$K$2 -> 175 | L19: =H19*$L$2 -> 175 | M19: =H19*$M$2 -> 180.25 | N19: =H19*$N$2 -> 189 | O19: =H19*$O$2 -> 192.5 | P19: =H19*$P$2 -> 201.25 | Q19: =H19*$Q$2 -> 210 | R19: =H19*$R$2 -> 227.5
A20: 0 | B20: =J10 -> 175 | C20: =J11 -> 350 | D20: =J12 -> 350 | E20: =J13 -> 350 | H20: 0.05 | I20: ROSDEE MENU KKR | J20: =H20*$J$2 -> 175 | K20: =H20*$K$2 -> 175 | L20: =H20*$L$2 -> 175 | M20: =H20*$M$2 -> 180.25 | N20: =H20*$N$2 -> 189 | O20: =H20*$O$2 -> 192.5 | P20: =H20*$P$2 -> 201.25 | Q20: =H20*$Q$2 -> 210 | R20: =H20*$R$2 -> 227.5 | U20: All Depot Salesman | V20: Depocho | W20: incentive
A21: 0.90001 | B21: =K10 -> 175 | C21: =K11 -> 350 | D21: =K12 -> 350 | E21: =K13 -> 350
A22: 0.95001 | B22: =L10 -> 175 | C22: =L11 -> 350 | D22: =L12 -> 350 | E22: =L13 -> 350 | U22: All Area depot result | V22: Area Manager | W22: Incentive
A23: 1.00001 | B23: =M10 -> 180.25 | C23: =M11 -> 360.5 | D23: =M12 -> 360.5 | E23: =M13 -> 360.5
A24: 1.03001 | B24: =N10 -> 189 | C24: =N11 -> 378 | D24: =N12 -> 378 | E24: =N13 -> 378 | U24: All Area manager Result | V24: Division manager | W24: Incetive
A25: =106.001% -> 1.06001 | B25: =O10 -> 192.5 | C25: =O11 -> 385 | D25: =O12 -> 385 | E25: =O13 -> 385
A26: =110.001% -> 1.10001 | B26: =P10 -> 201.25 | C26: =P11 -> 402.5 | D26: =P12 -> 402.5 | E26: =P13 -> 402.5
A27: =115.001% -> 1.15001 | B27: =Q10 -> 210 | C27: =Q11 -> 420 | D27: =Q12 -> 420 | E27: =Q13 -> 420
A28: =120.001% -> 1.20001 | B28: =R10 -> 227.5 | C28: =R11 -> 455 | D28: =R12 -> 455 | E28: =R13 -> 455
H30: =SUM(H6:H29) -> 1
I31: TOTAL | J31: =SUM(J6:J29) -> 3500 | K31: =SUM(K6:K29) -> 3500 | L31: =SUM(L6:L29) -> 3500 | M31: =SUM(M6:M29) -> 3605 | N31: =SUM(N6:N29) -> 3780 | O31: =SUM(O6:O29) -> 3850 | P31: =SUM(P6:P29) -> 4025 | Q31: =SUM(Q6:Q29) -> 4200 | R31: =SUM(R6:R29) -> 4550
G33: EXTRA | H33: Special KPI
H35: G1 | O35: =O6 -> 192.5
H36: G2 | J36: =J10 -> 175
H37: G3 | M37: =M16 -> 540.75
H38: Ot | M38: =M19 -> 180.25
H39: TOTAL | I39: =SUM(I35:R38) -> 1088.5
H41: Extreme | I41: <80% | J41: 80% to <90% | K41: 90% to <95% | L41: 95% to <100% | M41: 100% to <105% | N41: 105% to <110% | O41: 110% to <115% | P41: 115% to < 120% | Q41: 120% to <130% | R41: >130%
I42: 0 | J42: 1200 | K42: 1350 | L42: =1425 -> 1425 | M42: 1500 | N42: 1575 | O42: 1725 | P42: 1875 | Q42: 1950 | R42: 2100
H43: Money | J43: -0.2 | K43: -0.1 | L43: -0.05 | N43: 0.05 | O43: 0.15 | P43: 0.25 | Q43: 0.3 | R43: 0.4
H44: Option1 | I44: <80% | J44: 80% to <90% | K44: 90% to <95% | L44: 95% to <100% | M44: 1 | N44: >100% to <=105% | O44: >105% to <=110% | P44: >110% to <=115% | Q44: >115% to < =120% | R44: >120% to > 130%
H45: G1 | I45: =J6 -> 175 | J45: =J6 -> 175 | K45: =K6 -> 175 | L45: =L6 -> 175 | M45: =M6 -> 180.25 | N45: =N6 -> 189 | O45: =O6 -> 192.5 | P45: =P6 -> 201.25 | Q45: =Q6 -> 210 | R45: =R6 -> 227.5
H46: G2 | I46: =J10 -> 175 | J46: =J10 -> 175 | K46: =K10 -> 175 | L46: =L10 -> 175 | M46: =M10 -> 180.25 | N46: =N10 -> 189 | O46: =O10 -> 192.5 | P46: =P10 -> 201.25 | Q46: =Q10 -> 210 | R46: =R10 -> 227.5
H47: G3 | I47: =J16 -> 525 | J47: =J16 -> 525 | K47: =K16 -> 525 | L47: =L16 -> 525 | M47: =M16 -> 540.75 | N47: =N16 -> 567 | O47: =O16 -> 577.5 | P47: =P16 -> 603.75 | Q47: =Q16 -> 630 | R47: =R16 -> 682.5
H48: G4 | I48: =J19 -> 175 | J48: =J19 -> 175 | K48: =K19 -> 175 | L48: =L19 -> 175 | M48: =M19 -> 180.25 | N48: =N19 -> 189 | O48: =O19 -> 192.5 | P48: =P19 -> 201.25 | Q48: =Q19 -> 210 | R48: =R19 -> 227.5

Sheet WS WH
J1: =$H$4+($H$4*J3) -> 3150 | K1: =$H$4+($H$4*K3) -> 3325
J2: 3500 | K2: 3500 | L2: =$H$4+($H$4*L3) -> 3500 | M2: =$H$4+($H$4*M3) -> 3605 | N2: =$H$4+($H$4*N3) -> 3780 | O2: =$H$4+($H$4*O3) -> 3850 | P2: =$H$4+($H$4*P3) -> 4025 | Q2: =$H$4+($H$4*Q3) -> 4200 | R2: =$H$4+($H$4*R3) -> 4550
D3: Incentive base | I3: Money | J3: -0.1 | K3: -0.05 | L3: 0 | M3: 0.03 | N3: 0.08 | O3: 0.1 | P3: 0.15 | Q3: 0.2 | R3: 0.3 | U3: Simulation
C4: Depot | D4: Now | E4: New | G4: Incentive $ | H4: 3500 | I4: GOAL | J4: 0.9 | K4: 0.95 | L4: 1 | M4: 1.03 | N4: 1.06 | O4: 1.1 | P4: 1.15 | Q4: 1.2 | R4: 1.3 | W4: 45566 | X4: 45597 | Y4: 45627 | Z4: Total
C5: Area Manger | D5: 5000 | E5: 5000 | U5: Real | V5: Sales (1-2-3-4) | W5: 5000 | X5: 5000 | Y5: 5000 | Z5: =SUM(W5:Y5) -> 15000
C6: Depocho | D6: 4000 | E6: 4000 | G6: G1(CORE) | H6: 0.1 | I6: AJINOMOTO | J6: =H6*$J$2 -> 350 | K6: =H6*$K$2 -> 350 | L6: =H6*$L$2 -> 350 | M6: =H6*$M$2 -> 360.5 | N6: =H6*$N$2 -> 378 | O6: =H6*$O$2 -> 385 | P6: =H6*$P$2 -> 402.5 | Q6: =H6*$Q$2 -> 420 | R6: =H6*$R$2 -> 455
C7: D.Depocho | D7: 4000 | E7: 4000 | H7: 0.15 | I7: ROSDEE | J7: =H7*$J$2 -> 525 | K7: =H7*$K$2 -> 525 | L7: =H7*$L$2 -> 525 | M7: =H7*$M$2 -> 540.75 | N7: =H7*$N$2 -> 567 | O7: =H7*$O$2 -> 577.5 | P7: =H7*$P$2 -> 603.75 | Q7: =H7*$Q$2 -> 630 | R7: =H7*$R$2 -> 682.5 | U7: New Metod | V7: Sales 1 | W7: 6000 | X7: 5000 | Y7: 4500 | Z7: =SUM(W7:Y7) -> 15500
C8: CV | D8: 2500 | E8: 2500 | H8: 0.25 | I8: BIRDY | J8: =H8*$J$2 -> 875 | K8: =H8*$K$2 -> 875 | L8: =H8*$L$2 -> 875 | M8: =H8*$M$2 -> 901.25 | N8: =H8*$N$2 -> 945 | O8: =H8*$O$2 -> 962.5 | P8: =H8*$P$2 -> 1006.25 | Q8: =H8*$Q$2 -> 1050 | R8: =H8*$R$2 -> 1137.5 | V8: Sales 2 | W8: =I39 -> 1100.75 | X8: 5200 | Y8: 5000 | Z8: =SUM(W8:Y8) -> 11300.75
C9: Driver | D9: 1200 | E9: 1200 | V9: Sales3 | W9: 5000 | X9: 4900 | Y9: 6500 | Z9: =SUM(W9:Y9) -> 16400 | AA9: =Z9/Z5 -> 1.0933333
C10: CVFV | E10: 2500 | G10: G2(GD) | H10: 0.05 | I10: AJI-PLUS | J10: =H10*$J$2 -> 175 | K10: =H10*$K$2 -> 175 | L10: =H10*$L$2 -> 175 | M10: =H10*$M$2 -> 180.25 | N10: =H10*$N$2 -> 189 | O10: =H10*$O$2 -> 192.5 | P10: =H10*$P$2 -> 201.25 | Q10: =H10*$Q$2 -> 210 | R10: =H10*$R$2 -> 227.5 | V10: Sales 4 | W10: 4800 | X10: 4000 | Y10: 5000 | Z10: =SUM(W10:Y10) -> 13800
C11: WSF | E11: 3500 | H11: 0.05 | I11: ROSDEE CUBE | J11: =H11*$J$2 -> 175 | K11: =H11*$K$2 -> 175 | L11: =H11*$L$2 -> 175 | M11: =H11*$M$2 -> 180.25 | N11: =H11*$N$2 -> 189 | O11: =H11*$O$2 -> 192.5 | P11: =H11*$P$2 -> 201.25 | Q11: =H11*$Q$2 -> 210 | R11: =H11*$R$2 -> 227.5 | Y11: Average | Z11: =MEDIAN(Z7:Z10) -> 14650 | AA11: =Z11/Z5-1 -> -0.023333333
C12: WH | E12: 3500 | H12: 0.05 | I12: ROSDEE MENU | J12: =H12*$J$2 -> 175 | K12: =H12*$K$2 -> 175 | L12: =H12*$L$2 -> 175 | M12: =H12*$M$2 -> 180.25 | N12: =H12*$N$2 -> 189 | O12: =H12*$O$2 -> 192.5 | P12: =H12*$P$2 -> 201.25 | Q12: =H12*$Q$2 -> 210 | R12: =H12*$R$2 -> 227.5
H13: 0.05 | I13: ROSDEE NOODLE | J13: =H13*$J$2 -> 175 | K13: =H13*$K$2 -> 175 | L13: =H13*$L$2 -> 175 | M13: =H13*$M$2 -> 180.25 | N13: =H13*$N$2 -> 189 | O13: =H13*$O$2 -> 192.5 | P13: =H13*$P$2 -> 201.25 | Q13: =H13*$Q$2 -> 210 | R13: =H13*$R$2 -> 227.5
J14: =H14*$J$2 -> 0 | K14: =H14*$K$2 -> 0 | L14: =H14*$L$2 -> 0 | M14: =H14*$M$2 -> 0 | N14: =H14*$N$2 -> 0 | O14: =H14*$O$2 -> 0 | P14: =H14*$P$2 -> 0 | Q14: =H14*$Q$2 -> 0 | R14: =H14*$R$2 -> 0
G16: G3(BB) | H16: 0.1 | I16: YUMYUM | J16: =H16*$J$2 -> 350 | K16: =H16*$K$2 -> 350 | L16: =H16*$L$2 -> 350 | M16: =H16*$M$2 -> 360.5 | N16: =H16*$N$2 -> 378 | O16: =H16*$O$2 -> 385 | P16: =H16*$P$2 -> 402.5 | Q16: =H16*$Q$2 -> 420 | R16: =H16*$R$2 -> 455 | U16: Cascade concept
H17: 0.1 | I17: POWDER COFFEE | J17: =H17*$J$2 -> 350 | K17: =H17*$K$2 -> 350 | L17: =H17*$L$2 -> 350 | M17: =H17*$M$2 -> 360.5 | N17: =H17*$N$2 -> 378 | O17: =H17*$O$2 -> 385 | P17: =H17*$P$2 -> 402.5 | Q17: =H17*$Q$2 -> 420 | R17: =H17*$R$2 -> 455
U18: Salesman | V18: Incentive
B19: AJI Plus | C19: RDQ | D19: RDM | E19: RDNS | G19: Others | H19: 0.05 | I19: Takumi-Aji | J19: =H19*$J$2 -> 175 | K19: =H19*$K$2 -> 175 | L19: =H19*$L$2 -> 175 | M19: =H19*$M$2 -> 180.25 | N19: =H19*$N$2 -> 189 | O19: =H19*$O$2 -> 192.5 | P19: =H19*$P$2 -> 201.25 | Q19: =H19*$Q$2 -> 210 | R19: =H19*$R$2 -> 227.5
A20: 0 | B20: =J10 -> 175 | C20: =J11 -> 175 | D20: =J12 -> 175 | E20: =J13 -> 175 | H20: 0.05 | I20: ROSDEE MENU KKR | J20: =H20*$J$2 -> 175 | K20: =H20*$K$2 -> 175 | L20: =H20*$L$2 -> 175 | M20: =H20*$M$2 -> 180.25 | N20: =H20*$N$2 -> 189 | O20: =H20*$O$2 -> 192.5 | P20: =H20*$P$2 -> 201.25 | Q20: =H20*$Q$2 -> 210 | R20: =H20*$R$2 -> 227.5 | U20: All Depot Salesman | V20: Depocho | W20: incentive
A21: 0.90001 | B21: =K10 -> 175 | C21: =K11 -> 175 | D21: =K12 -> 175 | E21: =K13 -> 175
A22: 0.95001 | B22: =L10 -> 175 | C22: =L11 -> 175 | D22: =L12 -> 175 | E22: =L13 -> 175 | U22: All Area depot result | V22: Area Manager | W22: Incentive
A23: 1.00001 | B23: =M10 -> 180.25 | C23: =M11 -> 180.25 | D23: =M12 -> 180.25 | E23: =M13 -> 180.25
A24: 1.03001 | B24: =N10 -> 189 | C24: =N11 -> 189 | D24: =N12 -> 189 | E24: =N13 -> 189 | U24: All Area manager Result | V24: Division manager | W24: Incetive
A25: =106.001% -> 1.06001 | B25: =O10 -> 192.5 | C25: =O11 -> 192.5 | D25: =O12 -> 192.5 | E25: =O13 -> 192.5
A26: =110.001% -> 1.10001 | B26: =P10 -> 201.25 | C26: =P11 -> 201.25 | D26: =P12 -> 201.25 | E26: =P13 -> 201.25
A27: =115.001% -> 1.15001 | B27: =Q10 -> 210 | C27: =Q11 -> 210 | D27: =Q12 -> 210 | E27: =Q13 -> 210
A28: =120.001% -> 1.20001 | B28: =R10 -> 227.5 | C28: =R11 -> 227.5 | D28: =R12 -> 227.5 | E28: =R13 -> 227.5
H30: =SUM(H6:H29) -> 1
I31: TOTAL | J31: =SUM(J6:J29) -> 3500 | K31: =SUM(K6:K29) -> 3500 | L31: =SUM(L6:L29) -> 3500 | M31: =SUM(M6:M29) -> 3605 | N31: =SUM(N6:N29) -> 3780 | O31: =SUM(O6:O29) -> 3850 | P31: =SUM(P6:P29) -> 4025 | Q31: =SUM(Q6:Q29) -> 4200 | R31: =SUM(R6:R29) -> 4550
G33: EXTRA | H33: Special KPI
H35: G1 | O35: =O6 -> 385
H36: G2 | J36: =J10 -> 175
H37: G3 | M37: =M16 -> 360.5
H38: Ot | M38: =M19 -> 180.25
H39: TOTAL | I39: =SUM(I35:R38) -> 1100.75
H41: Extreme | I41: <80% | J41: 80% to <90% | K41: 90% to <95% | L41: 95% to <100% | M41: 100% to <105% | N41: 105% to <110% | O41: 110% to <115% | P41: 115% to < 120% | Q41: 120% to <130% | R41: >130%
I42: 0 | J42: 1200 | K42: 1350 | L42: =1425 -> 1425 | M42: 1500 | N42: 1575 | O42: 1725 | P42: 1875 | Q42: 1950 | R42: 2100
H43: Money | J43: -0.2 | K43: -0.1 | L43: -0.05 | N43: 0.05 | O43: 0.15 | P43: 0.25 | Q43: 0.3 | R43: 0.4
H44: Option1 | I44: <80% | J44: 80% to <90% | K44: 90% to <95% | L44: 95% to <100% | M44: 1 | N44: >100% to <=105% | O44: >105% to <=110% | P44: >110% to <=115% | Q44: >115% to < =120% | R44: >120% to > 130%
H45: G1 | I45: =J6 -> 350 | J45: =J6 -> 350 | K45: =K6 -> 350 | L45: =L6 -> 350 | M45: =M6 -> 360.5 | N45: =N6 -> 378 | O45: =O6 -> 385 | P45: =P6 -> 402.5 | Q45: =Q6 -> 420 | R45: =R6 -> 455
H46: G2 | I46: =J10 -> 175 | J46: =J10 -> 175 | K46: =K10 -> 175 | L46: =L10 -> 175 | M46: =M10 -> 180.25 | N46: =N10 -> 189 | O46: =O10 -> 192.5 | P46: =P10 -> 201.25 | Q46: =Q10 -> 210 | R46: =R10 -> 227.5
H47: G3 | I47: =J16 -> 350 | J47: =J16 -> 350 | K47: =K16 -> 350 | L47: =L16 -> 350 | M47: =M16 -> 360.5 | N47: =N16 -> 378 | O47: =O16 -> 385 | P47: =P16 -> 402.5 | Q47: =Q16 -> 420 | R47: =R16 -> 455
H48: G4 | I48: =J19 -> 175 | J48: =J19 -> 175 | K48: =K19 -> 175 | L48: =L19 -> 175 | M48: =M19 -> 180.25 | N48: =N19 -> 189 | O48: =O19 -> 192.5 | P48: =P19 -> 201.25 | Q48: =Q19 -> 210 | R48: =R19 -> 227.5

Sheet Test
A1: Row Labels | E1: 1 | F1: 2 | G1: 3 | H1: 4 | I1: 5 | J1: 6 | K1: 7 | L1: 8 | M1: 9 | N1: 10 | O1: 11 | P1: 12 | Q1: 13 | R1: 14 | S1: 15 | T1: 16 | U1: 17 | V1: 18 | W1: 19
A2: 1190011201 | B2: 76001 | C2: MR.X | D2: =VLOOKUP(A2,'Actual_Aji Plus'!#REF!,2,0) -> #REF! | E2: 0.9 | F2: 0.9001 | G2: 0.95 | H2: 0.9501 | I2: 1 | J2: 1.0001 | K2: 1.03 | L2: 1.0301 | M2: 1.06 | N2: 1.0601 | O2: 1.1 | P2: 1.1001 | Q2: 1.15 | R2: 1.1501 | S2: 1.2 | T2: 1.2001 | U2: 1.7 | V2: 0.8 | W2: 0.55
E4: 1 | F4: 2 | G4: 3 | H4: 4 | I4: 5 | J4: 6 | K4: 7 | L4: 8 | M4: 9 | N4: 10 | O4: 11 | P4: 12 | Q4: 13 | R4: 14 | S4: 15 | T4: 16 | U4: 17 | V4: 18 | W4: 19
E5: =IFERROR(VLOOKUP(E2,'Top WS'!$A$19:$B$28,2),0) -> 200 | F5: =IFERROR(VLOOKUP(F2,'Top WS'!$A$19:$B$28,2),0) -> 200 | G5: =IFERROR(VLOOKUP(G2,'Top WS'!$A$19:$B$28,2),0) -> 200 | H5: =IFERROR(VLOOKUP(H2,'Top WS'!$A$19:$B$28,2),0) -> 200 | I5: =IFERROR(VLOOKUP(I2,'Top WS'!$A$19:$B$28,2),0) -> 200 | J5: =IFERROR(VLOOKUP(J2,'Top WS'!$A$19:$B$28,2),0) -> 206 | K5: =IFERROR(VLOOKUP(K2,'Top WS'!$A$19:$B$28,2),0) -> 206 | L5: =IFERROR(VLOOKUP(L2,'Top WS'!$A$19:$B$28,2),0) -> 216 | ... W5: =IFERROR(VLOOKUP(W2,'Top WS'!$A$19:$B$28,2),0) -> 200

Sheet SF WH
J1: =$H$4+($H$4*J3) -> 3150 | K1: =$H$4+($H$4*K3) -> 3325
J2: 3500 | K2: 3500 | L2: =$H$4+($H$4*L3) -> 3500 | M2: =$H$4+($H$4*M3) -> 3605 | N2: =$H$4+($H$4*N3) -> 3780 | O2: =$H$4+($H$4*O3) -> 3850 | P2: =$H$4+($H$4*P3) -> 4025 | Q2: =$H$4+($H$4*Q3) -> 4200 | R2: =$H$4+($H$4*R3) -> 4550
D3: Incentive base | I3: Money | J3: -0.1 | K3: -0.05 | L3: 0 | M3: 0.03 | N3: 0.08 | O3: 0.1 | P3: 0.15 | Q3: 0.2 | R3: 0.3 | U3: Simulation
C4: Depot | D4: Now | E4: New | G4: Incentive $ | H4: 3500 | I4: GOAL | J4: 0.9 | K4: 0.95 | L4: 1 | M4: 1.03 | N4: 1.06 | O4: 1.1 | P4: 1.15 | Q4: 1.2 | R4: 1.3 | W4: 45566 | X4: 45597 | Y4: 45627 | Z4: Total
C5: Area Manger | D5: 5000 | E5: 5000 | U5: Real | V5: Sales (1-2-3-4) | W5: 5000 | X5: 5000 | Y5: 5000 | Z5: =SUM(W5:Y5) -> 15000
C6: Depocho | D6: 4000 | E6: 4000 | G6: G1(CORE) | H6: 0.08 | I6: AJINOMOTO | J6: =H6*$J$2 -> 280 | K6: =H6*$K$2 -> 280 | L6: =H6*$L$2 -> 280 | M6: =H6*$M$2 -> 288.4 | N6: =H6*$N$2 -> 302.4 | O6: =H6*$O$2 -> 308 | P6: =H6*$P$2 -> 322 | Q6: =H6*$Q$2 -> 336 | R6: =H6*$R$2 -> 364
C7: D.Depocho | D7: 4000 | E7: 4000 | H7: 0.13 | I7: ROSDEE | J7: =H7*$J$2 -> 455 | K7: =H7*$K$2 -> 455 | L7: =H7*$L$2 -> 455 | M7: =H7*$M$2 -> 468.65 | N7: =H7*$N$2 -> 491.4 | O7: =H7*$O$2 -> 500.5 | P7: =H7*$P$2 -> 523.25 | Q7: =H7*$Q$2 -> 546 | R7: =H7*$R$2 -> 591.5 | U7: New Metod | V7: Sales 1 | W7: 6000 | X7: 5000 | Y7: 4500 | Z7: =SUM(W7:Y7) -> 15500
C8: CV | D8: 2500 | E8: 2500 | H8: 0.18 | I8: BIRDY | J8: =H8*$J$2 -> 630 | K8: =H8*$K$2 -> 630 | L8: =H8*$L$2 -> 630 | M8: =H8*$M$2 -> 648.9 | N8: =H8*$N$2 -> 680.4 | O8: =H8*$O$2 -> 693 | P8: =H8*$P$2 -> 724.5 | Q8: =H8*$Q$2 -> 756 | R8: =H8*$R$2 -> 819 | V8: Sales 2 | W8: =I39 -> 1131.9 | X8: 5200 | Y8: 5000 | Z8: =SUM(W8:Y8) -> 11331.9
C9: Driver | D9: 1200 | E9: 1200 | V9: Sales3 | W9: 5000 | X9: 4900 | Y9: 6500 | Z9: =SUM(W9:Y9) -> 16400 | AA9: =Z9/Z5 -> 1.0933333
C10: CVFV | E10: 2500 | G10: G2(GD) | H10: 0.05 | I10: AJI-PLUS | J10: =H10*$J$2 -> 175 | K10: =H10*$K$2 -> 175 | L10: =H10*$L$2 -> 175 | M10: =H10*$M$2 -> 180.25 | N10: =H10*$N$2 -> 189 | O10: =H10*$O$2 -> 192.5 | P10: =H10*$P$2 -> 201.25 | Q10: =H10*$Q$2 -> 210 | R10: =H10*$R$2 -> 227.5 | V10: Sales 4 | W10: 4800 | X10: 4000 | Y10: 5000 | Z10: =SUM(W10:Y10) -> 13800
C11: WSF | E11: 3500 | H11: 0.06 | I11: ROSDEE CUBE | J11: =H11*$J$2 -> 210 | K11: =H11*$K$2 -> 210 | L11: =H11*$L$2 -> 210 | M11: =H11*$M$2 -> 216.3 | N11: =H11*$N$2 -> 226.8 | O11: =H11*$O$2 -> 231 | P11: =H11*$P$2 -> 241.5 | Q11: =H11*$Q$2 -> 252 | R11: =H11*$R$2 -> 273 | Y11: Average | Z11: =MEDIAN(Z7:Z10) -> 14650 | AA11: =Z11/Z5-1 -> -0.023333333
C12: WH | E12: 3500 | H12: 0.07 | I12: ROSDEE MENU | J12: =H12*$J$2 -> 245 | K12: =H12*$K$2 -> 245 | L12: =H12*$L$2 -> 245 | M12: =H12*$M$2 -> 252.35 | N12: =H12*$N$2 -> 264.6 | O12: =H12*$O$2 -> 269.5 | P12: =H12*$P$2 -> 281.75 | Q12: =H12*$Q$2 -> 294 | R12: =H12*$R$2 -> 318.5
H13: 0.07 | I13: ROSDEE NOODLE | J13: =H13*$J$2 -> 245 | K13: =H13*$K$2 -> 245 | L13: =H13*$L$2 -> 245 | M13: =H13*$M$2 -> 252.35 | N13: =H13*$N$2 -> 264.6 | O13: =H13*$O$2 -> 269.5 | P13: =H13*$P$2 -> 281.75 | Q13: =H13*$Q$2 -> 294 | R13: =H13*$R$2 -> 318.5
J14: =H14*$J$2 -> 0 | K14: =H14*$K$2 -> 0 | L14: =H14*$L$2 -> 0 | M14: =H14*$M$2 -> 0 | N14: =H14*$N$2 -> 0 | O14: =H14*$O$2 -> 0 | P14: =H14*$P$2 -> 0 | Q14: =H14*$Q$2 -> 0 | R14: =H14*$R$2 -> 0
G16: G3(BB) | H16: 0.13 | I16: YUMYUM | J16: =H16*$J$2 -> 455 | K16: =H16*$K$2 -> 455 | L16: =H16*$L$2 -> 455 | M16: =H16*$M$2 -> 468.65 | N16: =H16*$N$2 -> 491.4 | O16: =H16*$O$2 -> 500.5 | P16: =H16*$P$2 -> 523.25 | Q16: =H16*$Q$2 -> 546 | R16: =H16*$R$2 -> 591.5 | U16: Cascade concept
H17: 0.13 | I17: POWDER COFFEE | J17: =H17*$J$2 -> 455 | K17: =H17*$K$2 -> 455 | L17: =H17*$L$2 -> 455 | M17: =H17*$M$2 -> 468.65 | N17: =H17*$N$2 -> 491.4 | O17: =H17*$O$2 -> 500.5 | P17: =H17*$P$2 -> 523.25 | Q17: =H17*$Q$2 -> 546 | R17: =H17*$R$2 -> 591.5
U18: Salesman | V18: Incentive
B19: AJI Plus | C19: RDQ | D19: RDM | E19: RDNS | G19: Others | H19: 0.05 | I19: Takumi-Aji | J19: =H19*$J$2 -> 175 | K19: =H19*$K$2 -> 175 | L19: =H19*$L$2 -> 175 | M19: =H19*$M$2 -> 180.25 | N19: =H19*$N$2 -> 189 | O19: =H19*$O$2 -> 192.5 | P19: =H19*$P$2 -> 201.25 | Q19: =H19*$Q$2 -> 210 | R19: =H19*$R$2 -> 227.5
A20: 0 | B20: =J10 -> 175 | C20: =J11 -> 210 | D20: =J12 -> 245 | E20: =J13 -> 245 | H20: 0.05 | I20: ROSDEE MENU KKR | J20: =H20*$J$2 -> 175 | K20: =H20*$K$2 -> 175 | L20: =H20*$L$2 -> 175 | M20: =H20*$M$2 -> 180.25 | N20: =H20*$N$2 -> 189 | O20: =H20*$O$2 -> 192.5 | P20: =H20*$P$2 -> 201.25 | Q20: =H20*$Q$2 -> 210 | R20: =H20*$R$2 -> 227.5 | U20: All Depot Salesman | V20: Depocho | W20: incentive
A21: 0.90001 | B21: =K10 -> 175 | C21: =K11 -> 210 | D21: =K12 -> 245 | E21: =K13 -> 245
A22: 0.95001 | B22: =L10 -> 175 | C22: =L11 -> 210 | D22: =L12 -> 245 | E22: =L13 -> 245 | U22: All Area depot result | V22: Area Manager | W22: Incentive
A23: 1.00001 | B23: =M10 -> 180.25 | C23: =M11 -> 216.3 | D23: =M12 -> 252.35 | E23: =M13 -> 252.35
A24: 1.03001 | B24: =N10 -> 189 | C24: =N11 -> 226.8 | D24: =N12 -> 264.6 | E24: =N13 -> 264.6 | U24: All Area manager Result | V24: Division manager | W24: Incetive
A25: =106.001% -> 1.06001 | B25: =O10 -> 192.5 | C25: =O11 -> 231 | D25: =O12 -> 269.5 | E25: =O13 -> 269.5
A26: =110.001% -> 1.10001 | B26: =P10 -> 201.25 | C26: =P11 -> 241.5 | D26: =P12 -> 281.75 | E26: =P13 -> 281.75
A27: =115.001% -> 1.15001 | B27: =Q10 -> 210 | C27: =Q11 -> 252 | D27: =Q12 -> 294 | E27: =Q13 -> 294
A28: =120.001% -> 1.20001 | B28: =R10 -> 227.5 | C28: =R11 -> 273 | D28: =R12 -> 318.5 | E28: =R13 -> 318.5
H30: =SUM(H6:H29) -> 1
I31: TOTAL | J31: =SUM(J6:J29) -> 3500 | K31: =SUM(K6:K29) -> 3500 | L31: =SUM(L6:L29) -> 3500 | M31: =SUM(M6:M29) -> 3605 | N31: =SUM(N6:N29) -> 3780 | O31: =SUM(O6:O29) -> 3850 | P31: =SUM(P6:P29) -> 4025 | Q31: =SUM(Q6:Q29) -> 4200 | R31: =SUM(R6:R29) -> 4550
G33: EXTRA | H33: Special KPI
H35: G1 | O35: =O6 -> 308
H36: G2 | J36: =J10 -> 175
H37: G3 | M37: =M16 -> 468.65
H38: Ot | M38: =M19 -> 180.25
H39: TOTAL | I39: =SUM(I35:R38) -> 1131.9
H41: Extreme | I41: <80% | J41: 80% to <90% | K41: 90% to <95% | L41: 95% to <100% | M41: 100% to <105% | N41: 105% to <110% | O41: 110% to <115% | P41: 115% to < 120% | Q41: 120% to <130% | R41: >130%
I42: 0 | J42: 1200 | K42: 1350 | L42: =1425 -> 1425 | M42: 1500 | N42: 1575 | O42: 1725 | P42: 1875 | Q42: 1950 | R42: 2100
H43: Money | J43: -0.2 | K43: -0.1 | L43: -0.05 | N43: 0.05 | O43: 0.15 | P43: 0.25 | Q43: 0.3 | R43: 0.4
H44: Option1 | I44: <80% | J44: 80% to <90% | K44: 90% to <95% | L44: 95% to <100% | M44: 1 | N44: >100% to <=105% | O44: >105% to <=110% | P44: >110% to <=115% | Q44: >115% to < =120% | R44: >120% to > 130%
H45: G1 | I45: =J6 -> 280 | J45: =J6 -> 280 | K45: =K6 -> 280 | L45: =L6 -> 280 | M45: =M6 -> 288.4 | N45: =N6 -> 302.4 | O45: =O6 -> 308 | P45: =P6 -> 322 | Q45: =Q6 -> 336 | R45: =R6 -> 364
H46: G2 | I46: =J10 -> 175 | J46: =J10 -> 175 | K46: =K10 -> 175 | L46: =L10 -> 175 | M46: =M10 -> 180.25 | N46: =N10 -> 189 | O46: =O10 -> 192.5 | P46: =P10 -> 201.25 | Q46: =Q10 -> 210 | R46: =R10 -> 227.5
H47: G3 | I47: =J16 -> 455 | J47: =J16 -> 455 | K47: =K16 -> 455 | L47: =L16 -> 455 | M47: =M16 -> 468.65 | N47: =N16 -> 491.4 | O47: =O16 -> 500.5 | P47: =P16 -> 523.25 | Q47: =Q16 -> 546 | R47: =R16 -> 591.5
H48: G4 | I48: =J19 -> 175 | J48: =J19 -> 175 | K48: =K19 -> 175 | L48: =L19 -> 175 | M48: =M19 -> 180.25 | N48: =N19 -> 189 | O48: =O19 -> 192.5 | P48: =P19 -> 201.25 | Q48: =Q19 -> 210 | R48: =R19 -> 227.5

Sheet Guide
A1: Sale Incentive Guide
A3: Annually
A4: Step No. | B4: Sheet | C4: Step detail
A5: 1 | B5: M_Month | C5: Set the Sales Incentive payment cycle to once per year.
A7: Monthly
A8: Step No. | B8: Sheet | C8: Step detail
A9: 1 | B9: Period | C9: Define the Sales Incentive period.
A10: 2 | B10: Actual | C10: Download data from BI and copy it into the Actual sheet.
A11: 3 | B11: AST_Base | C11: Update the data in the AST Base sheet and copy the formulas in the yellow-highlighted columns.
A12: 4 | B12: HR Rep | C12: Download Personal Employment (Main & Active)_AST report from HCM, Update the data in the HR Rep and copy the formulas in the yellow-highlighted columns.
A13: 5 | B13: For HR | C13: Enter the employee ID, then copy all formulas except the Employee ID and Payment Method columns.
A15: As needed
A16: Step No. | B16: Sheet | C16: Step detail
A17: 1 | B17: T_SectAbove | C17: Adjust the compensation rate based on position level.
A18: 2 | B18: Table | C18: Adjust the compensation rate based on Job Function.
A19: 3 | B19: Target & Cal | C19: Adjust sales targets based on business conditions.
A20: 4 | B20: Shortage | C20: Adjust shortages by product and month.
A21: 5 | B21: Fix Rate | C21: Adjust fixed rate based on employee.
A23: ***Please ensure that sales and employee data align with the Sales Incentive period for that month.
A25: Recheck Job Function

Sheet M_Month
A1: sales incentive ของเดือน | B1: รอบการจ่าย Incentive (Variable) | C1: รอบการจ่าย Incentive (Fixed) | D1: Default column
A2: 46113 | B2: 46174 | C2: 46143 | D2: 1
A3: 46143 | B3: 46204 | C3: 46174 | D3: 2
A4: 46174 | B4: 46235 | C4: 46204 | D4: 3
A5: 46204 | B5: 46266 | C5: 46235 | D5: 4
A6: 46235 | B6: 46296 | C6: 46266 | D6: 5
A7: 46266 | B7: 46327 | C7: 46296 | D7: 6
A8: 46296 | B8: 46357 | C8: 46327 | D8: 7
A9: 46327 | B9: 46388 | C9: 46357 | D9: 8
A10: 46357 | B10: 46419 | C10: 46388 | D10: 9
A11: 46388 | B11: 46447 | C11: 46419 | D11: 10
A12: 46419 | B12: 46478 | C12: 46447 | D12: 11
A13: 46447 | B13: 46508 | C13: 46478 | D13: 12

Sheet Product
A1: Product
A2: AJINOMOTO
A3: ROSDEE
A4: BIRDY
A5: YUMYUM
A6: POWDER COFFEE
A7: AJI-PLUS
A8: ROSDEE MENU
A9: Takumi-Aji
A10: ROSDEE CUBE
A11: ROSDEE MENU KKR
A12: ROSDEE NOODLE

Sheet Period
A1: sales incentive ของเดือน | B1: รอบการจ่าย Incentive (Variable) | C1: รอบการจ่าย Incentive (Fixed) | D1: Default column
A2: 46113 | B2: =VLOOKUP(A2,M_Month!A:B,2,FALSE) -> 46174 | C2: =VLOOKUP(A2,M_Month!A:D,3,FALSE) -> 46143 | D2: =VLOOKUP(A2,M_Month!A:E,4,FALSE) -> 1

Sheet T_SectAbove
A1: Position Level | B1: Compensation rate
A2: Division Manager | B2: 5000
A3: Department Manager | B3: 5000
A4: Section Manager | B4: 4000
A5: Associate Director | B5: 6000

Sheet ASTBase
A1: เดือน | B1: ปี | C1: Area | D1: Depot | E1: Salesman Code | F1: รหัสพนักงาน (พนักงานขาย) | G1: ชื่อ - นามสกุล (พนักงานขาย) | H1: รหัสพนักงาน (พนักงานผู้ช่วยขาย) | I1: ชื่อ - นามสกุล (พนักงานผู้ช่วยขาย) | J1: สถานะพนักงาน (พนักงานผู้ช่วยขาย) | K1: ทีม | L1: ทะเบียนรถ | M1: ประเภทรถยนต์ | N1: หมายเหตุ | O1: ตรวจสอบ | P1: Salesman Code | Q1: DirectSupCode | R1: DeptMgrCode | S1: DivMgrCode
A2: December | B2: 2025 | F2: 222222 | P2: 0 | Q2: #N/A | R2: 0 | S2: 0
A3: December | B3: 2025 | F3: 222223 | P3: 0 | Q3: 222222 | R3: 222223 | S3: 0
A4: December | B4: 2025 | F4: 222234 | P4: 0 | Q4: 222222 | R4: 222234 | S4: 0
A5: December | B5: 2025 | F5: 222235 | P5: 0 | Q5: 222223 | R5: 222223 | S5: 0
A6: December | B6: 2025 | F6: 222236 | P6: 0 | Q6: 222234 | R6: 222234 | S6: 0
A7: December | B7: 2025 | F7: 222237 | P7: 0 | Q7: 222223 | R7: 222223 | S7: 0
A8: December | B8: 2025 | F8: 222238 | P8: 0 | Q8: 222234 | R8: 222234 | S8: 0
A9: December | B9: 2025 | F9: 222208 | P9: 0 | Q9: 222234 | R9: 222234 | S9: 0
A10: December | B10: 2025 | E10: 5490000718 | F10: 222209 | P10: 5490000718 | Q10: 222208 | R10: 222234 | S10: 0
A11: December | B11: 2025 | E11: 5490000706 | F11: 222210 | P11: 5490000706 | Q11: 222208 | R11: 222234 | S11: 0
A12: December | B12: 2025 | E12: 5490000707 | F12: 222211 | P12: 5490000707 | Q12: 222208 | R12: 222234 | S12: 0
A13: December | B13: 2025 | E13: 5490000701 | F13: 222212 | P13: 5490000701 | Q13: 222208 | R13: 222234 | S13: 0
A14: December | B14: 2025 | E14: 5490000721 | F14: 222218 | P14: 5490000721 | Q14: 222208 | R14: 222234 | S14: 0
A15: December | B15: 2025 | E15: 5490000719 | F15: 222219 | P15: 5490000719 | Q15: 222208 | R15: 222234 | S15: 0
A16: December | B16: 2025 | E16: 5490000725 | F16: 222220 | P16: 5490000725 | Q16: 222238 | R16: 222234 | S16: 0
A17: December | B17: 2025 | E17: 5490000702 | F17: 222201 | P17: 5490000702 | Q17: 222238 | R17: 222234 | S17: 0
A18: December | B18: 2025 | E18: 5490000708 | F18: 222202 | P18: 5490000708 | Q18: 222238 | R18: 222234 | S18: 0
A19: December | B19: 2025 | E19: 5490000704 | F19: 222203 | P19: 5490000704 | Q19: 222238 | R19: 222234 | S19: 0
A20: December | B20: 2025 | E20: 5490000717 | F20: 222204 | P20: 5490000717 | Q20: 222237 | R20: 222223 | S20: 0
A21: December | B21: 2025 | E21: 5490000703 | F21: 222205 | P21: 5490000703 | Q21: 222237 | R21: 222223 | S21: 0
A22: December | B22: 2025 | E22: 5490000709 | F22: 222206 | P22: 5490000709 | Q22: 222237 | R22: 222223 | S22: 0
A23: December | B23: 2025 | E23: 5490000713 | F23: 222213 | P23: 5490000713 | Q23: 222237 | R23: 222223 | S23: 0
... A28: December | B28: 2025 | E28: 5490000711 | F28: 222229 | P28: 5490000711 | Q28: 222235 | R28: 222223 | S28: 0

Sheet Actual
A1: Salesman Code | B1: Merge | C1: Salesman BI | D1: Product Group | E1: April | F1: May | G1: June | H1: July | I1: August | J1: September | K1: October | L1: November | M1: December | N1: January | O1: February | P1: March
A2: =_xlfn.IFNA(VLOOKUP(B2,Mapping!C:D,2,FALSE),C2) -> 5490000725 | B2: =C2&D2 -> 5490000725BD | C2: 5490000725 | D2: BD | N2: 54159 | O2: 72860 | P2: 77301
A3: =_xlfn.IFNA(VLOOKUP(B3,Mapping!C:D,2,FALSE),C3) -> 5490000725 | B3: =C3&D3 -> 5490000725YY | C3: 5490000725 | D3: YY | N3: 4683 | O3: 5155 | P3: 3892
A4: =_xlfn.IFNA(VLOOKUP(B4,Mapping!C:D,2,FALSE),C4) -> 5490000725 | B4: =C4&D4 -> 5490000725AJ | C4: 5490000725 | D4: AJ | N4: 3291.2 | O4: 3803 | P4: 3996.4
A5: =_xlfn.IFNA(VLOOKUP(B5,Mapping!C:D,2,FALSE),C5) -> 5490000725 | B5: =C5&D5 -> 5490000725RD | C5: 5490000725 | D5: RD | N5: 1525.26 | O5: 1817.36 | P5: 2096.1
A6: =_xlfn.IFNA(VLOOKUP(B6,Mapping!C:D,2,FALSE),C6) -> 5490000725 | B6: =C6&D6 -> 5490000725PDC | C6: 5490000725 | D6: PDC | N6: 702.8496 | O6: 857.4606 | P6: 722.9904
A7: =_xlfn.IFNA(VLOOKUP(B7,Mapping!C:D,2,FALSE),C7) -> 5490000725 | B7: =C7&D7 -> 5490000725AJP | C7: 5490000725 | D7: AJP | N7: 493.92 | O7: 504 | P7: 362.88
A8: =_xlfn.IFNA(VLOOKUP(B8,Mapping!C:D,2,FALSE),C8) -> 5490000725 | B8: =C8&D8 -> 5490000725RDC | C8: 5490000725 | D8: RDC | N8: 702.72 | O8: 178.56 | P8: 126.72
A9: =_xlfn.IFNA(VLOOKUP(B9,Mapping!C:D,2,FALSE),C9) -> 5490000725 | B9: =C9&D9 -> 5490000725TKM | C9: 5490000725 | D9: TKM | N9: 136.8 | O9: 232.8 | P9: 141.6
A10: =_xlfn.IFNA(VLOOKUP(B10,Mapping!C:D,2,FALSE),C10) -> 5490000725 | B10: =C10&D10 -> 5490000725RM | C10: 5490000725 | D10: RM | N10: 62 | O10: 128.2 | P10: 64.8
A11: =_xlfn.IFNA(VLOOKUP(B11,Mapping!C:D,2,FALSE),C11) -> 5490000725 | B11: =C11&D11 -> 5490000725RKR | C11: 5490000725 | D11: RKR | N11: 25.2 | O11: 14.4 | P11: 14.4
A12: =_xlfn.IFNA(VLOOKUP(B12,Mapping!C:D,2,FALSE),C12) -> 5490000725 | B12: =C12&D12 -> 5490000725QM | C12: 5490000725 | D12: QM | N12: 16 | O12: 13 | P12: 8
A13: =_xlfn.IFNA(VLOOKUP(B13,Mapping!C:D,2,FALSE),C13) -> 1190064722 | B13: =C13&D13 -> 1190064722RD | C13: 1190064722 | D13: RD | E13: 532387.36 | F13: 455190.7 | G13: 464090.4 | H13: 449158.1 | I13: 30232
A14: =_xlfn.IFNA(VLOOKUP(B14,Mapping!C:D,2,FALSE),C14) -> 1190064722 | B14: =C14&D14 -> 1190064722AJ | C14: 1190064722 | D14: AJ | E14: 379972.1 | F14: 305303.1 | G14: 237457.6 | H14: 302376.1 | I14: 7856
A15: =_xlfn.IFNA(VLOOKUP(B15,Mapping!C:D,2,FALSE),C15) -> 1190064722 | B15: =C15&D15 -> 1190064722YY | C15: 1190064722 | D15: YY | E15: 234275 | F15: 220342 | G15: 211946 | H15: 270053 | I15: 9806
A16: =_xlfn.IFNA(VLOOKUP(B16,Mapping!C:D,2,FALSE),C16) -> 1190064722 | B16: =C16&D16 -> 1190064722BD | C16: 1190064722 | D16: BD | E16: 102602 | F16: 111639 | G16: 156116 | H16: 152244 | I16: 756
A17: =_xlfn.IFNA(VLOOKUP(B17,Mapping!C:D,2,FALSE),C17) -> 1190064722 | B17: =C17&D17 -> 1190064722PDC | C17: 1190064722 | D17: PDC | E17: 63013.214 | F17: 37471.603 | G17: 34061.271 | H17: 38720.305 | I17: 4823.1648
A18: =_xlfn.IFNA(VLOOKUP(B18,Mapping!C:D,2,FALSE),C18) -> 1190064722 | B18: =C18&D18 -> 1190064722TKM | C18: 1190064722 | D18: TKM | E18: 35876.4 | F18: 30744 | G18: 28983.6 | H18: 51828 | I18: 2808
A19: =_xlfn.IFNA(VLOOKUP(B19,Mapping!C:D,2,FALSE),C19) -> 1190064722 | B19: =C19&D19 -> 1190064722RM | C19: 1190064722 | D19: RM | E19: 32320.9 | F19: 27392.1 | G19: 24362.4 | H19: 29863.9 | I19: 1166.5
A20: =_xlfn.IFNA(VLOOKUP(B20,Mapping!C:D,2,FALSE),C20) -> 1190064722 | B20: =C20&D20 -> 1190064722RDC | C20: 1190064722 | D20: RDC | E20: 22019.04 | F20: 19909.44 | G20: 15828.192 | H20: 16240.032 | I20: 1908.864
A21: =_xlfn.IFNA(VLOOKUP(B21,Mapping!C:D,2,FALSE),C21) -> 1190064722 | B21: =C21&D21 -> 1190064722AJP | C21: 1190064722 | D21: AJP | E21: 15906.24 | F21: 12176.64 | G21: 10120.32 | H21: 12952.8 | I21: 715.68
A22: =_xlfn.IFNA(VLOOKUP(B22,Mapping!C:D,2,FALSE),C22) -> 1190064722 | B22: =C22&D22 -> 1190064722RKR | C22: 1190064722 | D22: RKR | E22: 16165.2 | F22: 10859.4 | G22: 11651.4 | H22: 4128
A23: =_xlfn.IFNA(VLOOKUP(B23,Mapping!C:D,2,FALSE),C23) -> 1190064722 | B23: =C23&D23 -> 1190064722ND | C23: 1190064722 | D23: ND | E23: 2351.72 | F23: 2305.74 | G23: 2917.56 | H23: 2132.66 | I23: 196.02
A24: =_xlfn.IFNA(VLOOKUP(B24,Mapping!C:D,2,FALSE),C24) -> 1190064722 | B24: =C24&D24 -> 1190064722FP | C24: 1190064722 | D24: FP | E24: 4234.464 | F24: 1310.928 | G24: 955.848 | H24: 1381.056 | I24: 131.256 | J24: -14.568
A25: =_xlfn.IFNA(VLOOKUP(B25,Mapping!C:D,2,FALSE),C25) -> 1190064722 | B25: =C25&D25 -> 1190064722AMV | C25: 1190064722 | D25: AMV | E25: 7 | F25: 7 | G25: 11 | H25: 145
A26: =_xlfn.IFNA(VLOOKUP(B26,Mapping!C:D,2,FALSE),C26) -> 1190064722 | B26: =C26&D26 -> 1190064722LPD | C26: 1190064722 | D26: LPD | G26: 12 | H26: 12 | I26: 12
A27: =_xlfn.IFNA(VLOOKUP(B27,Mapping!C:D,2,FALSE),C27) -> 1190064722 | B27: =C27&D27 -> 1190064722AJA | C27: 1190064722 | D27: AJA | F27: 1 | G27: 4 | H27: 28 | N27: -18.1 | O27: -0.2
A28: =_xlfn.IFNA(VLOOKUP(B28,Mapping!C:D,2,FALSE),C28) -> 5490000721 | B28: =C28&D28 -> 5490000721AJ | C28: 5490000721 | D28: AJ | E28: 373.2 | F28: 1183.656 | G28: 547.6 | H28: 1214.4 | I28: 1178.7 | J28: 682.8 | K28: 1117.9 | L28: 2231.6 | M28: 2499.2 | N28: 729.6 | O28: 2481.6 | P28: 1599.2
A29: =_xlfn.IFNA(VLOOKUP(B29,Mapping!C:D,2,FALSE),C29) -> 5490000721 | B29: =C29&D29 -> 5490000721RD | C29: 5490000721 | D29: RD | E29: 386.8 | F29: 642.9 | G29: 320.38 | H29: 541.53 | I29: 370.2 | J29: 495.5 | K29: 561 | L29: 1364.665 | M29: 1152.8 | N29: 219.2 | O29: 602 | P29: 672.8
A30: =_xlfn.IFNA(VLOOKUP(B30,Mapping!C:D,2,FALSE),C30) -> 5490000721 | B30: =C30&D30 -> 5490000721FP | C30: 5490000721 | D30: FP | E30: 218.88 | F30: 817.452 | G30: 189.312 | H30: 386.604 | I30: 613.398 | J30: 540.252 | K30: 541.848 | L30: 570.18 | M30: 525.072 | N30: 199.776
A31: =_xlfn.IFNA(VLOOKUP(B31,Mapping!C:D,2,FALSE),C31) -> 5490000721 | B31: =C31&D31 -> 5490000721BD | C31: 5490000721 | D31: BD | E31: 166 | F31: 150.81667 | G31: 214 | H31: 200 | I31: 219.8 | J31: 173 | K31: 296.5 | L31: 223.58333 | M31: 282 | N31: 101.16667 | O31: 267.83333 | P31: 213
A32: =_xlfn.IFNA(VLOOKUP(B32,Mapping!C:D,2,FALSE),C32) -> 5490000721 | B32: =C32&D32 -> 5490000721YY | C32: 5490000721 | D32: YY | E32: 152 | F32: 266.83333 | G32: 154.94167 | H32: 92.183333 | I32: 309.05833 | J32: 102.5 | K32: 248.61667 | L32: 211.84444 | M32: 346.05556 | N32: 15.791667 | O32: 179.62222 | P32: 175.56944
A33: =_xlfn.IFNA(VLOOKUP(B33,Mapping!C:D,2,FALSE),C33) -> 5490000721 | B33: =C33&D33 -> 5490000721TKM | C33: 5490000721 | D33: TKM | E33: 85.2 | F33: 211 | G33: 152.6 | H33: 141.8 | I33: 207.1 | J33: 207.6 | K33: 252.2 | L33: 213.6 | M33: 205.4 | N33: 170.8 | O33: 89.8 | P33: 226.6
A34: =_xlfn.IFNA(VLOOKUP(B34,Mapping!C:D,2,FALSE),C34) -> 5490000721 | B34: =C34&D34 -> 5490000721PDC | C34: 5490000721 | D34: PDC | E34: 114.2598 | F34: 64.53 | G34: 75.4742 | H34: 58.977 | I34: 122.3052 | J34: 81.84 | K34: 159.8926 | L34: 168.804 | M34: 155.7372 | N34: 84.3822 | O34: 45.7307 | P34: 119.6058
A35: =_xlfn.IFNA(VLOOKUP(B35,Mapping!C:D,2,FALSE),C35) -> 5490000721 | B35: =C35&D35 -> 5490000721RM | C35: 5490000721 | D35: RM | E35: 77.5 | F35: 88.74 | G35: 56.08 | H35: 56.5 | I35: 148.08 | J35: 107.6 | K35: 119.6 | L35: 45.73 | M35: 114 | N35: 35 | O35: 53.875 | P35: 51.3
A36: =_xlfn.IFNA(VLOOKUP(B36,Mapping!C:D,2,FALSE),C36) -> 5490000721 | B36: =C36&D36 -> 5490000721RDC | C36: 5490000721 | D36: RDC | E36: 31.68 | F36: 61.92 | G36: 20.16 | H36: 56.16 | I36: 25.2 | J36: 54.72 | K36: 47.52 | L36: 14.4 | M36: 51.84 | N36: 46.08 | O36: 43.2 | P36: 21.6
A37: =_xlfn.IFNA(VLOOKUP(B37,Mapping!C:D,2,FALSE),C37) -> 5490000721 | B37: =C37&D37 -> 5490000721FP | C37: 5490000721 | D37: FP | O37: 316.128 | P37: 126.192
A38: =_xlfn.IFNA(VLOOKUP(B38,Mapping!C:D,2,FALSE),C38) -> 5490000721 | B38: =C38&D38 -> 5490000721AMV | C38: 5490000721 | D38: AMV | E38: 17 | F38: 10 | G38: 45 | I38: 38 | J38: 41 | K38: 24 | L38: 40 | M38: 12 | N38: 4 | O38: 14 | P38: 33
A39: =_xlfn.IFNA(VLOOKUP(B39,Mapping!C:D,2,FALSE),C39) -> 5490000721 | B39: =C39&D39 -> 5490000721RKR | C39: 5490000721 | D39: RKR | E39: 5.4 | F39: 4.59 | G39: 16.2 | H39: 5.4 | I39: 10.8 | J39: 34.2 | K39: 27 | L39: 16.2 | M39: 28.8 | N39: 5.13 | O39: 23.4 | P39: 5.4
A40: =_xlfn.IFNA(VLOOKUP(B40,Mapping!C:D,2,FALSE),C40) -> 5490000721 | B40: =C40&D40 -> 5490000721AJP | C40: 5490000721 | D40: AJP | E40: 10.08 | G40: 10.08 | I40: 20.16 | J40: 10.08 | K40: 20.16 | M40: 30.24 | P40: 30.24
A41: =_xlfn.IFNA(VLOOKUP(B41,Mapping!C:D,2,FALSE),C41) -> 5490000721 | B41: =C41&D41 -> 5490000721QM | C41: 5490000721 | D41: QM | I41: 14 | J41: 13 | K41: 23 | L41: 8 | M41: 15 | N41: 4 | O41: 10 | P41: 8
A42: =_xlfn.IFNA(VLOOKUP(B42,Mapping!C:D,2,FALSE),C42) -> 5490000721 | B42: =C42&D42 -> 5490000721AJA | C42: 5490000721 | D42: AJA | O42: 3
A43: =_xlfn.IFNA(VLOOKUP(B43,Mapping!C:D,2,FALSE),C43) -> 5490000721 | B43: =C43&D43 -> 5490000721SWEET | C43: 5490000721 | D43: SWEET | H43: -0.4
A44: =_xlfn.IFNA(VLOOKUP(B44,Mapping!C:D,2,FALSE),C44) -> 5490000721 | B44: =C44&D44 -> 5490000721STICK | C44: 5490000721 | D44: STICK | F44: -0.24 | I44: -0.06 | K44: -0.288 | N44: -0.288
A45: =_xlfn.IFNA(VLOOKUP(B45,Mapping!C:D,2,FALSE),C45) -> 5490000720 | B45: =C45&D45 -> 5490000720RD | C45: 5490000720 | D45: RD | E45: 24742.5 | F45: 15600.1 | G45: 175624.8 | H45: 47132.7 | I45: 11655.4 | J45: 21063.6 | K45: 23159.3 | L45: 16213.9 | M45: 31911.8 | N45: 30826.2 | O45: 23161 | P45: 32116.6
A46: =_xlfn.IFNA(VLOOKUP(B46,Mapping!C:D,2,FALSE),C46) -> 5490000720 | B46: =C46&D46 -> 5490000720AJ | C46: 5490000720 | D46: AJ | E46: 20763.1 | F46: 21043.4 | G46: 31462 | H46: 12542.2 | I46: 25783.3 | J46: 22771 | K46: 38293 | L46: 45497.2 | M46: 33922.9 | N46: 27893.6 | O46: 45596 | P46: 44299
A47: =_xlfn.IFNA(VLOOKUP(B47,Mapping!C:D,2,FALSE),C47) -> 5490000720 | B47: =C47&D47 -> 5490000720BD | C47: 5490000720 | D47: BD | E47: 34623 | F47: 16904 | G47: 14808 | H47: 23693 | I47: 7055 | J47: 17290 | K47: 8023 | L47: 27273 | M47: 22042 | N47: 12045 | O47: 15253 | P47: 20634
A48: =_xlfn.IFNA(VLOOKUP(B48,Mapping!C:D,2,FALSE),C48) -> 5490000720 | B48: =C48&D48 -> 5490000720YY | C48: 5490000720 | D48: YY | E48: 10915 | F48: 13286 | G48: 7306 | H48: 18327 | I48: 20180 | J48: 3914 | K48: 7751 | L48: 20357 | M48: 23683 | N48: 14246 | O48: 3986 | P48: 17029
A49: =_xlfn.IFNA(VLOOKUP(B49,Mapping!C:D,2,FALSE),C49) -> 5490000720 | B49: =C49&D49 -> 5490000720AJP | C49: 5490000720 | D49: AJP | E49: 1743.84 | F49: 3094.56 | G49: 3870.72 | H49: 3709.44 | I49: 2338.56 | J49: 2479.68 | K49: 4233.6 | L49: 4445.28 | M49: 5140.8 | N49: 2328.48 | O49: 4374.72 | P49: 6219.36
A50: =_xlfn.IFNA(VLOOKUP(B50,Mapping!C:D,2,FALSE),C50) -> 5490000720 | B50: =C50&D50 -> 5490000720TKM | C50: 5490000720 | D50: TKM | E50: 1219.2 | F50: 2089.2 | G50: 2428.8 | H50: 1905.6 | I50: 3651.6 | J50: 2514 | K50: 3355.2 | L50: 3836.4 | M50: 2574 | N50: 3891.6 | O50: 2512.8 | P50: 3927.6
A51: =_xlfn.IFNA(VLOOKUP(B51,Mapping!C:D,2,FALSE),C51) -> 5490000720 | B51: =C51&D51 -> 5490000720PDC | C51: 5490000720 | D51: PDC | E51: 6992.1594 | F51: 162.9864 | G51: 1052.7084 | H51: 1401.0318 | I51: 1039.9086 | J51: 1336.4802 | K51: 1099.2618 | L51: 2651.6376 | M51: 2195.208 | N51: 1611.2286 | O51: 1534.0068 | P51: 2629.5354
A52: =_xlfn.IFNA(VLOOKUP(B52,Mapping!C:D,2,FALSE),C52) -> 5490000720 | B52: =C52&D52 -> 5490000720ND | C52: 5490000720 | D52: ND | E52: 380.76 | F52: 979.04 | G52: 1593.5 | H52: 594.9 | I52: 616.92 | J52: 1128.46 | K52: 981.6 | L52: 786.2 | M52: 678.06 | N52: 1149.86 | O52: 991.84 | P52: 1120.98
A53: =_xlfn.IFNA(VLOOKUP(B53,Mapping!C:D,2,FALSE),C53) -> 5490000720 | B53: =C53&D53 -> 5490000720RM | C53: 5490000720 | D53: RM | E53: 567.8 | F53: 708.4 | G53: 1047.2 | H53: 303 | I53: 210.6 | J53: 751.8 | K53: 1350.8 | L53: 707.2 | M53: 1269.2 | N53: 768.8 | O53: 732.6 | P53: 896.2
A54: =_xlfn.IFNA(VLOOKUP(B54,Mapping!C:D,2,FALSE),C54) -> 5490000720 | B54: =C54&D54 -> 5490000720RDC | C54: 5490000720 | D54: RDC | E54: 184.896 | F54: 323.712 | G54: 326.592 | H54: 203.328 | I54: 261.504 | J54: 433.728 | K54: 202.752 | L54: 337.536 | M54: 639.936 | N54: 318.528 | O54: 230.976 | P54: 385.344
A55: =_xlfn.IFNA(VLOOKUP(B55,Mapping!C:D,2,FALSE),C55) -> 5490000720 | B55: =C55&D55 -> 5490000720RKR | C55: 5490000720 | D55: RKR | E55: 210.6 | F55: 151.2 | G55: 232.2 | H55: 48.6 | I55: 194.4 | J55: 156.6 | K55: 540 | L55: 345.6 | M55: 356.4 | N55: 97.2 | O55: 334.8 | P55: 162
A56: =_xlfn.IFNA(VLOOKUP(B56,Mapping!C:D,2,FALSE),C56) -> 5490000720 | B56: =C56&D56 -> 5490000720HDSH | C56: 5490000720 | D56: HDSH | E56: 96 | F56: 204 | G56: 168 | H56: 252 | I56: 276 | J56: 144 | K56: 240 | L56: 252 | M56: 228 | N56: 240 | O56: 144 | P56: 312
... A68: =_xlfn.IFNA(VLOOKUP(B68,Mapping!C:D,2,FALSE),C68) -> 5490000719 | B68: =C68&D68 -> 5490000719RKR | C68: 5490000719 | D68: RKR | E68: 4033.8 | F68: 3780 | G68: 2802.6 | H68: 2683.8 | I68: 4455 | J68: 2219.4 | K68: 4617 | L68: 3942 | M68: 2673 | N68: 4249.8 | O68: 4525.2 | P68: 3564
A69: =_xlfn.IFNA(VLOOKUP(B69,Mapping!C:D,2,FALSE),C69) -> 5490000719 | B69: =C69&D69 -> 5490000719SWEET | C69: 5490000719 | D69: SWEET | E69: 396
A70: =_xlfn.IFNA(VLOOKUP(B70,Mapping!C:D,2,FALSE),C70) -> 5490000718 | B70: =C70&D70 -> 5490000718YY | C70: 5490000718 | D70: YY | E70: 2083 | F70: 3776 | G70: 5598 | H70: 4648 | I70: 2563 | J70: 4410 | K70: 5566 | L70: 3297 | M70: 4408 | N70: 2621 | O70: 2138 | P70: 2884
A71: =_xlfn.IFNA(VLOOKUP(B71,Mapping!C:D,2,FALSE),C71) -> 5490000718 | B71: =C71&D71 -> 5490000718AJ | C71: 5490000718 | D71: AJ | E71: 1538.6 | F71: 1438.4 | G71: 1355 | H71: 1555.3 | I71: 1514 | J71: 1270.4 | K71: 1123.1 | L71: 1294.6 | M71: 1179.8 | N71: 3996 | O71: 2151.6 | P71: 2883.1
A72: =_xlfn.IFNA(VLOOKUP(B72,Mapping!C:D,2,FALSE),C72) -> 5490000718 | B72: =C72&D72 -> 5490000718BD | C72: 5490000718 | D72: BD | E72: 1417 | F72: 2458 | G72: 1374 | H72: 2010 | I72: 2120 | J72: 1956 | K72: 2270 | L72: 1783 | M72: 2185 | N72: 1480 | O72: 392 | P72: 1204
A73: =_xlfn.IFNA(VLOOKUP(B73,Mapping!C:D,2,FALSE),C73) -> 5490000718 | B73: =C73&D73 -> 5490000718RD | C73: 5490000718 | D73: RD | E73: 630.4 | F73: 1179.2 | G73: 963.2 | H73: 752.2 | I73: 1510.1 | J73: 849.6 | K73: 1098 | L73: 653.7 | M73: 1173.1 | N73: 1571.5 | O73: 1436.8 | P73: 2088.9
A74: =_xlfn.IFNA(VLOOKUP(B74,Mapping!C:D,2,FALSE),C74) -> 5490000718 | B74: =C74&D74 -> 5490000718TKM | C74: 5490000718 | D74: TKM | E74: 1142.4 | F74: 765.6 | G74: 1363.2 | H74: 542.4 | I74: 1291.2 | J74: 988.8 | K74: 1036.8 | L74: 604.8 | M74: 867.6 | N74: 561.6 | O74: 708 | P74: 1184.4
A75: =_xlfn.IFNA(VLOOKUP(B75,Mapping!C:D,2,FALSE),C75) -> 5490000718 | B75: =C75&D75 -> 5490000718FP | C75: 5490000718 | D75: FP | E75: 442.32 | F75: 293.88 | G75: 10.2 | H75: 144 | I75: 3150.6 | K75: 407.4 | L75: 108 | M75: 118.2 | N75: 10.2
A76: =_xlfn.IFNA(VLOOKUP(B76,Mapping!C:D,2,FALSE),C76) -> 5490000718 | B76: =C76&D76 -> 5490000718PDC | C76: 5490000718 | D76: PDC | E76: 236.0358 | F76: 337.0824 | G76: 83.9826 | H76: 241.9812 | I76: 270.207 | J76: 94.788 | K76: 272.8188 | L76: 271.4022 | M76: 164.8764 | N76: 183.204 | O76: 186.8076 | P76: 176.9292
A77: =_xlfn.IFNA(VLOOKUP(B77,Mapping!C:D,2,FALSE),C77) -> 5490000718 | B77: =C77&D77 -> 5490000718RM | C77: 5490000718 | D77: RM | E77: 227.2 | F77: 163.5 | G77: 258.2 | H77: 147 | I77: 166 | J77: 204.6 | K77: 194.4 | L77: 174.7 | M77: 284 | N77: 85.6 | O77: 18 | P77: 482.3
A78: =_xlfn.IFNA(VLOOKUP(B78,Mapping!C:D,2,FALSE),C78) -> 5490000718 | B78: =C78&D78 -> 5490000718RDC | C78: 5490000718 | D78: RDC | E78: 84.96 | F78: 253.44 | G78: 211.68 | H78: 177.12 | I78: 216 | J78: 144 | K78: 325.44 | L78: 96.48 | M78: 190.08 | N78: 139.68 | O78: 34.56 | P78: 459.36
A79: =_xlfn.IFNA(VLOOKUP(B79,Mapping!C:D,2,FALSE),C79) -> 5490000718 | B79: =C79&D79 -> 5490000718AJP | C79: 5490000718 | D79: AJP | E79: 151.2 | F79: 171.36 | G79: 171.36 | H79: 80.64 | I79: 181.44 | J79: 120.96 | K79: 362.88 | N79: 70.56 | O79: 514.08 | P79: 20.16
A80: =_xlfn.IFNA(VLOOKUP(B80,Mapping!C:D,2,FALSE),C80) -> 5490000718 | B80: =C80&D80 -> 5490000718RKR | C80: 5490000718 | D80: RKR | E80: 122.4 | F80: 106.2 | G80: 91.8 | H80: 66.6 | I80: 124.2 | J80: 23.4 | K80: 277.2 | L80: 32.4 | M80: 136.8 | N80: 63 | O80: 72 | P80: 79.2
A81: =_xlfn.IFNA(VLOOKUP(B81,Mapping!C:D,2,FALSE),C81) -> 5490000718 | B81: =C81&D81 -> 5490000718FP | C81: 5490000718 | D81: FP | O81: 21.024 | P81: 348.792
A82: =_xlfn.IFNA(VLOOKUP(B82,Mapping!C:D,2,FALSE),C82) -> 5490000718 | B82: =C82&D82 -> 5490000718AMV | C82: 5490000718 | D82: AMV | E82: 20 | F82: 7 | G82: 12 | H82: 27 | I82: 7 | J82: 21 | K82: 36 | L82: 10 | M82: 38 | N82: 1 | O82: 5 | P82: 60
A83: =_xlfn.IFNA(VLOOKUP(B83,Mapping!C:D,2,FALSE),C83) -> 5490000718 | B83: =C83&D83 -> 5490000718QM | C83: 5490000718 | D83: QM | N83: 104 | O83: 50
A84: =_xlfn.IFNA(VLOOKUP(B84,Mapping!C:D,2,FALSE),C84) -> 5490000718 | B84: =C84&D84 -> 5490000718SWEET | C84: 5490000718 | D84: SWEET | E84: 12
A85: =_xlfn.IFNA(VLOOKUP(B85,Mapping!C:D,2,FALSE),C85) -> 5490000718 | B85: =C85&D85 -> 5490000718STICK | C85: 5490000718 | D85: STICK | F85: 9.36
A86: =_xlfn.IFNA(VLOOKUP(B86,Mapping!C:D,2,FALSE),C86) -> 5490000717 | B86: =C86&D86 -> 5490000717AJ | C86: 5490000717 | D86: AJ | E86: 209871.2 | F86: 102929.8 | G86: 150764.1 | H86: 173563.1 | I86: 116599.3 | J86: 135695 | K86: 200239.5 | L86: 122404.9 | M86: 165910.9 | N86: 137059.8 | O86: 91694.8 | P86: 239399.8
A87: =_xlfn.IFNA(VLOOKUP(B87,Mapping!C:D,2,FALSE),C87) -> 5490000717 | B87: =C87&D87 -> 5490000717RD | C87: 5490000717 | D87: RD | E87: 180237.56 | F87: 63610.62 | G87: 105005.68 | H87: 118706.58 | I87: 98137.38 | J87: 119604.92 | K87: 97990.98 | L87: 123270.72 | M87: 158118.54 | N87: 129151.72 | O87: 80159.92 | P87: 148168.28
A88: =_xlfn.IFNA(VLOOKUP(B88,Mapping!C:D,2,FALSE),C88) -> 5490000703 | B88: =C88&D88 -> 5490000717YY | C88: 5490000717 | D88: YY | E88: 128508 | F88: 87537 | G88: 90042 | H88: 90682 | I88: 77960 | J88: 145943 | K88: 124534 | L88: 90103 | M88: 110548 | N88: 121358 | O88: 88143 | P88: 122333
A89: =_xlfn.IFNA(VLOOKUP(B89,Mapping!C:D,2,FALSE),C89) -> 5490000703 | B89: =C89&D89 -> 5490000717BD | C89: 5490000717 | D89: BD | E89: 55597 | F89: 23081 | G89: 23243 | H89: 37393 | I89: 42984 | J89: 33342 | K89: 54125 | L89: 51740 | M89: 54646 | N89: 46291 | O89: 18551 | P89: 46269
A90: =_xlfn.IFNA(VLOOKUP(B90,Mapping!C:D,2,FALSE),C90) -> 5490000703 | B90: =C90&D90 -> 5490000717PDC | C90: 5490000717 | D90: PDC | E90: 48870.723 | F90: 23250.269 | G90: 21047.892 | H90: 39786.344 | I90: 29118.312 | J90: 34908.676 | K90: 34973.792 | L90: 56204.787 | M90: 46399.067 | N90: 47689.205 | O90: 25511.433 | P90: 34595.957
A91: =_xlfn.IFNA(VLOOKUP(B91,Mapping!C:D,2,FALSE),C91) -> 5490000717 | B91: =C91&D91 -> 5490000717RM | C91: 5490000717 | D91: RM | E91: 18084.5 | F91: 11270.1 | G91: 12770.1 | H91: 14651.4 | I91: 12186.7 | J91: 13219.3 | K91: 13329.3 | L91: 15381.8 | M91: 18951.1 | N91: 14109.4 | O91: 13722.4 | P91: 18678.2
A92: =_xlfn.IFNA(VLOOKUP(B92,Mapping!C:D,2,FALSE),C92) -> 5490000717 | B92: =C92&D92 -> 5490000717TKM | C92: 5490000717 | D92: TKM | E92: 13520.4 | F92: 11106 | G92: 15915.6 | H92: 11281.2 | I92: 14844 | J92: 14520 | K92: 11487.6 | L92: 11629.2 | M92: 12432 | N92: 11974.8 | O92: 11613.6 | P92: 11868
A93: =_xlfn.IFNA(VLOOKUP(B93,Mapping!C:D,2,FALSE),C93) -> 5490000717 | B93: =C93&D93 -> 5490000717AJP | C93: 5490000717 | D93: AJP | E93: 20660.16 | F93: 3265.92 | G93: 9907.44 | H93: 14072.16 | I93: 7321.32 | J93: 9555.48 | K93: 11892.84 | L93: 11892.84 | M93: 11434.8 | N93: 12910.92 | O93: 10221.12 | P93: 20698.68
A94: =_xlfn.IFNA(VLOOKUP(B94,Mapping!C:D,2,FALSE),C94) -> 5490000717 | B94: =C94&D94 -> 5490000717RDC | C94: 5490000717 | D94: RDC | E94: 8602.848 | F94: 5421.888 | G94: 6954.048 | H94: 7028.352 | I94: 6060.96 | J94: 6981.984 | K94: 5924.448 | L94: 5204.736 | M94: 7939.296 | N94: 6175.296 | O94: 6663.744 | P94: 8435.52
A95: =_xlfn.IFNA(VLOOKUP(B95,Mapping!C:D,2,FALSE),C95) -> 5490000703 | B95: =C95&D95 -> 5490000717RKR | C95: 5490000717 | D95: RKR | E95: 3562.2 | F95: 3544.2 | G95: 3879 | H95: 2691 | I95: 2880 | J95: 3970.8 | K95: 3506.4 | L95: 2768.4 | M95: 3796.2 | N95: 2313 | O95: 4633.2 | P95: 3015
A96: =_xlfn.IFNA(VLOOKUP(B96,Mapping!C:D,2,FALSE),C96) -> 5490000717 | B96: =C96&D96 -> 5490000717ND | C96: 5490000717 | D96: ND | E96: 534.6 | F96: 677.16 | G96: 677.16 | H96: 689.04 | I96: 748.44 | J96: 623.7 | K96: 564.3 | L96: 689.04 | M96: 5518.44 | N96: 3277.98 | O96: 2614.86 | P96: 4602.42
A97: =_xlfn.IFNA(VLOOKUP(B97,Mapping!C:D,2,FALSE),C97) -> 1190064716 | B97: =C97&D97 -> 1190064716BD | C97: 1190064716 | D97: BD | E97: 52538 | F97: 21764 | G97: 30826 | H97: 45722 | I97: 37312 | J97: 24555 | K97: 45293 | L97: 37672 | M97: 49397 | N97: 878
A98: =_xlfn.IFNA(VLOOKUP(B98,Mapping!C:D,2,FALSE),C98) -> 1190064716 | B98: =C98&D98 -> 1190064716YY | C98: 1190064716 | D98: YY | E98: 7584 | F98: 7435 | G98: 4820 | H98: 4094 | I98: 5868 | J98: 9181 | K98: 5225 | L98: 4541 | M98: 5587
A99: =_xlfn.IFNA(VLOOKUP(B99,Mapping!C:D,2,FALSE),C99) -> 1190064716 | B99: =C99&D99 -> 1190064716AJ | C99: 1190064716 | D99: AJ | E99: 3694.2 | F99: 4687.6 | G99: 4089.4 | H99: 5517.4 | I99: 4061.4 | J99: 4282 | K99: 3910.8 | L99: 2844.6 | M99: 4357.2
A100: =_xlfn.IFNA(VLOOKUP(B100,Mapping!C:D,2,FALSE),C100) -> 1190064716 | B100: =C100&D100 -> 1190064716RD | C100: 1190064716 | D100: RD | E100: 2169.8 | F100: 2418.4 | G100: 1587.56 | H100: 2107.18 | I100: 1908.12 | J100: 2584.36 | K100: 1802.12 | L100: 1561.56 | M100: 2665.92
A101: =_xlfn.IFNA(VLOOKUP(B101,Mapping!C:D,2,FALSE),C101) -> 1190064716 | B101: =C101&D101 -> 1190064716PDC | C101: 1190064716 | D101: PDC | E101: 1012.5222 | F101: 1561.0062 | G101: 1185.8004 | H101: 733.572 | I101: 1402.401 | J101: 1470.8268 | K101: 866.7492 | L101: 2920.1946 | M101: 767.5074
A102: =_xlfn.IFNA(VLOOKUP(B102,Mapping!C:D,2,FALSE),C102) -> 1190064716 | B102: =C102&D102 -> 1190064716AJP | C102: 1190064716 | D102: AJP | E102: 423.36 | F102: 544.32 | G102: 725.76 | H102: 1179.36 | I102: 655.2 | J102: 423.36 | K102: 504 | L102: 302.4 | M102: 433.44
A103: =_xlfn.IFNA(VLOOKUP(B103,Mapping!C:D,2,FALSE),C103) -> 1190064716 | B103: =C103&D103 -> 1190064716TKM | C103: 1190064716 | D103: TKM | E103: 182.4 | F103: 148.8 | G103: 228 | H103: 158.4 | I103: 196.8 | J103: 271.2 | K103: 151.2 | L103: 93.6 | M103: 237.6
A104: =_xlfn.IFNA(VLOOKUP(B104,Mapping!C:D,2,FALSE),C104) -> 1190064716 | B104: =C104&D104 -> 1190064716RDC | C104: 1190064716 | D104: RDC | E104: 205.056 | F104: 172.8 | G104: 134.784 | H104: 126.72 | I104: 142.848 | J104: 294.912 | K104: 119.808 | L104: 93.312 | M104: 162.432
A105: =_xlfn.IFNA(VLOOKUP(B105,Mapping!C:D,2,FALSE),C105) -> 1190064716 | B105: =C105&D105 -> 1190064716RM | C105: 1190064716 | D105: RM | E105: 132.6 | F105: 473.8 | G105: 113.6 | H105: 73.8 | I105: 127.8 | J105: 187.6 | K105: 87.2 | L105: 75.8 | M105: 117.2
A106: =_xlfn.IFNA(VLOOKUP(B106,Mapping!C:D,2,FALSE),C106) -> 1190064716 | B106: =C106&D106 -> 1190064716RKR | C106: 1190064716 | D106: RKR | E106: 48.6 | F106: 73.8 | G106: 43.2 | H106: 61.2 | I106: 68.4 | J106: 43.2 | K106: 46.8 | L106: 61.2 | M106: 52.2
A107: =_xlfn.IFNA(VLOOKUP(B107,Mapping!C:D,2,FALSE),C107) -> 1190064716 | B107: =C107&D107 -> 1190064716QM | C107: 1190064716 | D107: QM | I107: 170 | K107: 23 | L107: 16 | M107: 20
A108: =_xlfn.IFNA(VLOOKUP(B108,Mapping!C:D,2,FALSE),C108) -> 1190064716 | B108: =C108&D108 -> 1190064716STICK | C108: 1190064716 | D108: STICK | H108: 1.44
A109: =_xlfn.IFNA(VLOOKUP(B109,Mapping!C:D,2,FALSE),C109) -> 5490000705 | B109: =C109&D109 -> 1190064712RD | C109: 1190064712 | D109: RD | E109: 1444254.2 | F109: 1467780.7 | G109: 1691290.7 | H109: 1869665.9 | I109: 1462692.6 | J109: 1675708.9 | K109: 900419 | L109: 2116399.3 | M109: 1648960.2 | N109: 2229459.3 | O109: 1333895.7 | P109: 1351927.4
A110: =_xlfn.IFNA(VLOOKUP(B110,Mapping!C:D,2,FALSE),C110) -> 5490000711 | B110: =C110&D110 -> 1190064712AJ | C110: 1190064712 | D110: AJ | E110: 1236813.6 | F110: 1252688.8 | G110: 1629270.4 | H110: 1390728 | I110: 1285443.2 | J110: 1434184 | K110: 1364165.6 | L110: 1578297.6 | M110: 1351440 | N110: 1399042.8 | O110: 1332106.4 | P110: 1310376
A111: =_xlfn.IFNA(VLOOKUP(B111,Mapping!C:D,2,FALSE),C111) -> 5490000711 | B111: =C111&D111 -> 1190064712YY | C111: 1190064712 | D111: YY | E111: 432073 | F111: 300105 | G111: 399058 | H111: 378835 | I111: 481380 | J111: 364685 | K111: 359897 | L111: 470486 | M111: 388405 | N111: 620702 | O111: 297052 | P111: 343488
...

Sheet HR Rep
A1: User/Employee ID | B1: Full Name Alt1 (Auto) | C1: Full Name (Auto) | D1: Date of Birth | E1: Age (YY.MM.DD) (Auto) | F1: Employment Details Hire Date/Concurrent Date | G1: Company Company Name | H1: Location Location Name | I1: Division Name | J1: Department Department Name | K1: Section Section Name | L1: Job Title | M1: Position Name (TH) | N1: Position Level | O1: Company E-mail (Personnel) Email Information Company Email | P1: Company E-mail (Center) Email Information Company Email | Q1: Job Grade | R1: Cost Centre | S1: Employment Details Service Year | T1: Employment Details Time in Job Grade | U1: Employment Details Retirement Date | V1: *Direct Superior | W1: Department Head of Department | X1: Head of Division | Y1: Last Name | Z1: First Name | AA1: MergeName | AB1: EmpCode | AC1: Direct Sup
A2: 222235 | W2: 222223 | AA2: =Y2&", " &Z2 -> , | AB2: 222235 | AC2: 222223
A3: 066048 | AA3: =Y3&", " &Z3 -> , | AB3: 066048 | AC3: #N/A
A4: 222223 | W4: 222223 | AA4: =Y4&", " &Z4 -> , | AB4: 222223 | AC4: 222222
A5: 222234 | W5: 222234 | AA5: =Y5&", " &Z5 -> , | AB5: 222234 | AC5: 222222
A6: 222238 | W6: 222234 | AA6: =Y6&", " &Z6 -> , | AB6: 222238 | AC6: 222234
A7: 222214 | W7: 222234 | AA7: =Y7&", " &Z7 -> , | AB7: 222214 | AC7: 222236
A8: 222218 | W8: 222234 | AA8: =Y8&", " &Z8 -> , | AB8: 222218 | AC8: 222208
A9: 222229 | W9: 222223 | AA9: =Y9&", " &Z9 -> , | AB9: 222229 | AC9: 222235
A10: 222208 | W10: 222234 | AA10: =Y10&", " &Z10 -> , | AB10: 222208 | AC10: 222234
A11: 222204 | W11: 222223 | AA11: =Y11&", " &Z11 -> , | AB11: 222204 | AC11: 222237
A12: 222203 | W12: 222234 | AA12: =Y12&", " &Z12 -> , | AB12: 222203 | AC12: 222238
A13: 222212 | W13: 222234 | AA13: =Y13&", " &Z13 -> , | AB13: 222212 | AC13: 222208
A14: 222207 | W14: 222223 | AA14: =Y14&", " &Z14 -> , | AB14: 222207 | AC14: 222235
A15: 222219 | W15: 222234 | AA15: =Y15&", " &Z15 -> , | AB15: 222219 | AC15: 222208
... A20: 222209 | W20: 222234 | AA20: =Y20&", " &Z20 -> , | AB20: 222209 | AC20: 222208
A21: 222222 | AA21: =Y21&", " &Z21 -> , | AB21: 222222 | AC21: #N/A
A22: 222215 | W22: 222223 | AA22: =Y22&", " &Z22 -> , | AB22: 222215 | AC22: 222235
A23: 222201 | W23: 222234 | AA23: =Y23&", " &Z23 -> , | AB23: 222201 | AC23: 222238
A24: 222216 | W24: 222223 | AA24: =Y24&", " &Z24 -> , | AB24: 222216 | AC24: 222235
A25: 222213 | W25: 222223 | AA25: =Y25&", " &Z25 -> , | AB25: 222213 | AC25: 222237
A26: 222237 | W26: 222223 | AA26: =Y26&", " &Z26 -> , | AB26: 222237 | AC26: 222223
A27: 222211 | W27: 222234 | AA27: =Y27&", " &Z27 -> , | AB27: 222211 | AC27: 222208
A28: 222236 | W28: 222234 | AA28: =Y28&", " &Z28 -> , | AB28: 222236 | AC28: 222234
A29: 222220 | W29: 222234 | AA29: =Y29&", " &Z29 -> , | AB29: 222220 | AC29: 222238

Sheet Mapping
A1: SalesCode_BI | B1: Product Group | C1: Merge | D1: Salesman Code
A2: 1190064712 | B2: AJ | C2: =A2&B2 -> 1190064712AJ | D2: 5490000711
A3: 1190064712 | B3: AJP | C3: =A3&B3 -> 1190064712AJP | D3: 5490000711
A4: 1190064712 | B4: YY | C4: =A4&B4 -> 1190064712YY | D4: 5490000711
A5: 1190064712 | B5: RKR | C5: =A5&B5 -> 1190064712RKR | D5: 5490000711
A6: 1190064712 | B6: RDC | C6: =A6&B6 -> 1190064712RDC | D6: 5490000705
A7: 1190064712 | B7: RM | C7: =A7&B7 -> 1190064712RM | D7: 5490000705
A8: 1190064712 | B8: ND | C8: =A8&B8 -> 1190064712ND | D8: 5490000705
A9: 1190064712 | B9: RD | C9: =A9&B9 -> 1190064712RD | D9: 5490000705
A10: 1190064712 | B10: BD | C10: =A10&B10 -> 1190064712BD | D10: 5490000714
A11: 1190064712 | B11: PDC | C11: =A11&B11 -> 1190064712PDC | D11: 5490000714
A12: 1190064712 | B12: TKM | C12: =A12&B12 -> 1190064712TKM | D12: 5490000714
A13: 5490000704 | B13: YY | C13: =A13&B13 -> 5490000704YY | D13: 5490000702
... A25: 5490000704 | B25: PDC | C25: =A25&B25 -> 5490000704PDC | D25: 5490000708

Sheet 2) หลักการคำนวน Table
A1: Sales | B1: Standard | C1: Money and Goal | L1: Product
C2: 0.9 | D2: 0.95 | E2: 1 | F2: 1.03 | G2: 1.08 | H2: 1.1 | I2: 1.15 | J2: 1.2 | K2: 1.3
A3: Team | B3: Incentive | C3: 0.9 | D3: 0.95 | E3: 1 | F3: 1.03 | G3: 1.06 | H3: 1.1 | I3: 1.15 | J3: 1.2 | K3: 20 | L3: AJ | M3: RD | N3: BD | O3: AJP | P3: RDC | Q3: RM | R3: ND | S3: YY | T3: PDC | U3: TKM | V3: RKR | W3: AMV | X3: AJA | Y3: FP | Z3: QM
A4: 5490000718 | B4: 4000 | C4: =($B4*C$2) -> 3600 | D4: =($B4*D$2) -> 3800 | E4: =($B4*E$2) -> 4000 | F4: =($B4*F$2) -> 4120 | G4: =($B4*G$2) -> 4320 | H4: =($B4*H$2) -> 4400 | I4: =($B4*I$2) -> 4600 | J4: =($B4*J$2) -> 4800 | K4: =($B4*K$2) -> 5200 | L4: 0.033333333 | M4: 0.055555556 | N4: 0.11111111 | O4: 0.055555556 | P4: 0.11111111 | Q4: 0.11111111 | S4: 0.11111111 | T4: 0.16666667 | U4: 0.044444444 | V4: 0.044444444 | W4: 0.022222222 | X4: 0.011111111 | Y4: 0.11111111 | Z4: 0.011111111
A5: 5490000706 | B5: 4000 | C5: =($B5*C$2) -> 3600 | D5: =($B5*D$2) -> 3800 | E5: =($B5*E$2) -> 4000 | F5: =($B5*F$2) -> 4120 | G5: =($B5*G$2) -> 4320 | H5: =($B5*H$2) -> 4400 | I5: =($B5*I$2) -> 4600 | J5: =($B5*J$2) -> 4800 | K5: =($B5*K$2) -> 5200 | L5: 0.03030303 | M5: 0.050505051 | N5: 0.1010101 | O5: 0.050505051 | P5: 0.1010101 | Q5: 0.1010101 | R5: 0.1010101 | S5: 0.1010101 | T5: 0.15151515 | U5: 0.04040404 | V5: 0.04040404 | W5: 0.02020202 | Y5: 0.1010101 | Z5: 0.01
A6: 5490000707 | B6: 5000 | C6: =($B6*C$2) -> 4500 | D6: =($B6*D$2) -> 4750 | E6: =($B6*E$2) -> 5000 | F6: =($B6*F$2) -> 5150 | G6: =($B6*G$2) -> 5400 | H6: =($B6*H$2) -> 5500 | I6: =($B6*I$2) -> 5750 | J6: =($B6*J$2) -> 6000 | K6: =($B6*K$2) -> 6500 | L6: 0.034883721 | M6: 0.058139535 | N6: 0.11627907 | O6: 0.058139535 | P6: 0.11627907 | Q6: 0.11627907 | R6: 0.11627907 | S6: 0.11627907 | T6: 0.1744186 | U6: 0.046511628 | V6: 0.046511628
A7: 5490000701 | B7: 5000 | C7: =($B7*C$2) -> 4500 | D7: =($B7*D$2) -> 4750 | E7: =($B7*E$2) -> 5000 | F7: =($B7*F$2) -> 5150 | G7: =($B7*G$2) -> 5400 | H7: =($B7*H$2) -> 5500 | I7: =($B7*I$2) -> 5750 | J7: =($B7*J$2) -> 6000 | K7: =($B7*K$2) -> 6500 | L7: 0.030927835 | M7: 0.051546392 | N7: 0.10309278 | O7: 0.051546392 | P7: 0.10309278 | Q7: 0.10309278 | R7: 0.10309278 | S7: 0.10309278 | T7: 0.15463918 | U7: 0.041237113 | V7: 0.041237113 | Y7: 0.10309278 | Z7: 0.010309278
A8: 5490000721 | B8: 5000 | C8: =($B8*C$2) -> 4500 | D8: =($B8*D$2) -> 4750 | E8: =($B8*E$2) -> 5000 | F8: =($B8*F$2) -> 5150 | G8: =($B8*G$2) -> 5400 | H8: =($B8*H$2) -> 5500 | I8: =($B8*I$2) -> 5750 | J8: =($B8*J$2) -> 6000 | K8: =($B8*K$2) -> 6500 | L8: 0.033333333 | M8: 0.055555556 | N8: 0.11111111 | O8: 0.055555556 | P8: 0.11111111 | Q8: 0.11111111 | S8: 0.11111111 | T8: 0.16666667 | U8: 0.044444444 | V8: 0.044444444 | W8: 0.022222222 | X8: 0.011111111 | Y8: 0.11111111 | Z8: 0.011111111
A9: 5490000719 | B9: 5000 | C9: =($B9*C$2) -> 4500 | D9: =($B9*D$2) -> 4750 | E9: =($B9*E$2) -> 5000 | F9: =($B9*F$2) -> 5150 | G9: =($B9*G$2) -> 5400 | H9: =($B9*H$2) -> 5500 | I9: =($B9*I$2) -> 5750 | J9: =($B9*J$2) -> 6000 | K9: =($B9*K$2) -> 6500 | L9: 0.034883721 | M9: 0.058139535 | N9: 0.11627907 | O9: 0.058139535 | P9: 0.11627907 | Q9: 0.11627907 | R9: 0.11627907 | S9: 0.11627907 | T9: 0.1744186 | U9: 0.046511628 | V9: 0.046511628
A10: 222208 | B10: 5000 | C10: =($B10*C$2) -> 4500 | D10: =($B10*D$2) -> 4750 | E10: =($B10*E$2) -> 5000 | F10: =($B10*F$2) -> 5150 | G10: =($B10*G$2) -> 5400 | H10: =($B10*H$2) -> 5500 | I10: =($B10*I$2) -> 5750 | J10: =($B10*J$2) -> 6000 | K10: =($B10*K$2) -> 6500 | L10: 0.03 | M10: 0.05 | N10: 0.1 | O10: 0.05 | P10: 0.1 | Q10: 0.1 | R10: 0.1 | S10: 0.1 | T10: 0.15 | U10: 0.04 | V10: 0.04 | W10: 0.02 | X10: 0.01 | Y10: 0.1 | Z10: 0.01
A11: 5490000725 | B11: 4000 | C11: =($B11*C$2) -> 3600 | D11: =($B11*D$2) -> 3800 | E11: =($B11*E$2) -> 4000 | F11: =($B11*F$2) -> 4120 | G11: =($B11*G$2) -> 4320 | H11: =($B11*H$2) -> 4400 | I11: =($B11*I$2) -> 4600 | J11: =($B11*J$2) -> 4800 | K11: =($B11*K$2) -> 5200 | L11: 0.056179775 | M11: 0.056179775 | N11: 0.16853933 | O11: 0.056179775 | P11: 0.11235955 | Q11: 0.11235955 | S11: 0.15730337 | T11: 0.16853933 | U11: 0.056179775 | V11: 0.056179775
A12: 5490000702 | B12: 4000 | C12: =($B12*C$2) -> 3600 | D12: =($B12*D$2) -> 3800 | E12: =($B12*E$2) -> 4000 | F12: =($B12*F$2) -> 4120 | G12: =($B12*G$2) -> 4320 | H12: =($B12*H$2) -> 4400 | I12: =($B12*I$2) -> 4600 | J12: =($B12*J$2) -> 4800 | K12: =($B12*K$2) -> 5200 | S12: 0.92307692 | X12: 0.076923077
A13: 5490000708 | B13: 4000 | C13: =($B13*C$2) -> 3600 | D13: =($B13*D$2) -> 3800 | E13: =($B13*E$2) -> 4000 | F13: =($B13*F$2) -> 4120 | G13: =($B13*G$2) -> 4320 | H13: =($B13*H$2) -> 4400 | I13: =($B13*I$2) -> 4600 | J13: =($B13*J$2) -> 4800 | K13: =($B13*K$2) -> 5200 | N13: 0.5 | T13: 0.5
A14: 5490000704 | B14: 5000 | C14: =($B14*C$2) -> 4500 | D14: =($B14*D$2) -> 4750 | E14: =($B14*E$2) -> 5000 | F14: =($B14*F$2) -> 5150 | G14: =($B14*G$2) -> 5400 | H14: =($B14*H$2) -> 5500 | I14: =($B14*I$2) -> 5750 | J14: =($B14*J$2) -> 6000 | K14: =($B14*K$2) -> 6500 | L14: 0.053571429 | M14: 0.089285714 | O14: 0.089285714 | P14: 0.19642857 | Q14: 0.21428571 | R14: 0.17857143 | U14: 0.089285714 | V14: 0.089285714
A15: 222238 | B15: 5000 | C15: =($B15*C$2) -> 4500 | D15: =($B15*D$2) -> 4750 | E15: =($B15*E$2) -> 5000 | F15: =($B15*F$2) -> 5150 | G15: =($B15*G$2) -> 5400 | H15: =($B15*H$2) -> 5500 | I15: =($B15*I$2) -> 5750 | J15: =($B15*J$2) -> 6000 | K15: =($B15*K$2) -> 6500 | L15: 0.03030303 | M15: 0.050505051 | N15: 0.15151515 | O15: 0.050505051 | P15: 0.11111111 | Q15: 0.12121212 | R15: 0.1010101 | S15: 0.12121212 | T15: 0.15151515 | U15: 0.050505051 | V15: 0.050505051 | X15: 0.01010101
A16: 5490000713 | B16: 5000 | C16: =($B16*C$2) -> 4500 | D16: =($B16*D$2) -> 4750 | E16: =($B16*E$2) -> 5000 | F16: =($B16*F$2) -> 5150 | G16: =($B16*G$2) -> 5400 | H16: =($B16*H$2) -> 5500 | I16: =($B16*I$2) -> 5750 | J16: =($B16*J$2) -> 6000 | K16: =($B16*K$2) -> 6500 | N16: 0.26666667 | S16: 0.22222222 | T16: 0.26666667 | Y16: 0.22222222 | Z16: 0.022222222
A17: 5490000709 | B17: 5000 | C17: =($B17*C$2) -> 4500 | D17: =($B17*D$2) -> 4750 | E17: =($B17*E$2) -> 5000 | F17: =($B17*F$2) -> 5150 | G17: =($B17*G$2) -> 5400 | H17: =($B17*H$2) -> 5500 | I17: =($B17*I$2) -> 5750 | J17: =($B17*J$2) -> 6000 | K17: =($B17*K$2) -> 6500 | L17: 0.055555556 | M17: 0.092592593 | O17: 0.092592593 | P17: 0.18518519 | Q17: 0.2037037 | R17: 0.18518519 | U17: 0.074074074 | V17: 0.074074074 | W17: 0.037037037
A18: 5490000703 | B18: 5000 | C18: =($B18*C$2) -> 4500 | D18: =($B18*D$2) -> 4750 | E18: =($B18*E$2) -> 5000 | F18: =($B18*F$2) -> 5150 | G18: =($B18*G$2) -> 5400 | H18: =($B18*H$2) -> 5500 | I18: =($B18*I$2) -> 5750 | J18: =($B18*J$2) -> 6000 | K18: =($B18*K$2) -> 6500 | N18: 0.35294118 | S18: 0.29411765 | T18: 0.35294118
A19: 5490000717 | B19: 5000 | C19: =($B19*C$2) -> 4500 | D19: =($B19*D$2) -> 4750 | E19: =($B19*E$2) -> 5000 | F19: =($B19*F$2) -> 5150 | G19: =($B19*G$2) -> 5400 | H19: =($B19*H$2) -> 5500 | I19: =($B19*I$2) -> 5750 | J19: =($B19*J$2) -> 6000 | K19: =($B19*K$2) -> 6500 | L19: 0.057692308 | M19: 0.096153846 | O19: 0.096153846 | P19: 0.19230769 | Q19: 0.21153846 | R19: 0.19230769 | U19: 0.076923077 | V19: 0.076923077
A20: 222237 | B20: 5000 | C20: =($B20*C$2) -> 4500 | D20: =($B20*D$2) -> 4750 | E20: =($B20*E$2) -> 5000 | F20: =($B20*F$2) -> 5150 | G20: =($B20*G$2) -> 5400 | H20: =($B20*H$2) -> 5500 | I20: =($B20*I$2) -> 5750 | J20: =($B20*J$2) -> 6000 | K20: =($B20*K$2) -> 6500 | L20: 0.03030303 | M20: 0.050505051 | N20: 0.12121212 | O20: 0.050505051 | P20: 0.1010101 | Q20: 0.11111111 | R20: 0.1010101 | S20: 0.1010101 | T20: 0.12121212 | U20: 0.04040404 | V20: 0.04040404 | W20: 0.02020202 | Y20: 0.1010101 | Z20: 0.01010101
A21: 5490000710 | B21: 5000 | C21: =($B21*C$2) -> 4500 | D21: =($B21*D$2) -> 4750 | E21: =($B21*E$2) -> 5000 | F21: =($B21*F$2) -> 5150 | G21: =($B21*G$2) -> 5400 | H21: =($B21*H$2) -> 5500 | I21: =($B21*I$2) -> 5750 | J21: =($B21*J$2) -> 6000 | K21: =($B21*K$2) -> 6500 | W21: 0.7 | X21: 0.3
A22: 222236 | B22: 5000 | C22: =($B22*C$2) -> 4500 | D22: =($B22*D$2) -> 4750 | E22: =($B22*E$2) -> 5000 | F22: =($B22*F$2) -> 5150 | G22: =($B22*G$2) -> 5400 | H22: =($B22*H$2) -> 5500 | I22: =($B22*I$2) -> 5750 | J22: =($B22*J$2) -> 6000 | K22: =($B22*K$2) -> 6500 | W22: 0.7 | X22: 0.3
A23: 5490000720 | B23: 5500 | C23: =($B23*C$2) -> 4950 | D23: =($B23*D$2) -> 5225 | E23: =($B23*E$2) -> 5500 | F23: =($B23*F$2) -> 5665 | G23: =($B23*G$2) -> 5940 | H23: =($B23*H$2) -> 6050 | I23: =($B23*I$2) -> 6325 | J23: =($B23*J$2) -> 6600 | K23: =($B23*K$2) -> 7150 | L23: 0.031578947 | M23: 0.031578947 | N23: 0.15789474 | O23: 0.052631579 | P23: 0.11578947 | Q23: 0.10526316 | R23: 0.12631579 | S23: 0.12631579 | T23: 0.15789474 | U23: 0.052631579 | V23: 0.042105263
A24: 5490000714 | B24: 5500 | C24: =($B24*C$2) -> 4950 | D24: =($B24*D$2) -> 5225 | E24: =($B24*E$2) -> 5500 | F24: =($B24*F$2) -> 5665 | G24: =($B24*G$2) -> 5940 | H24: =($B24*H$2) -> 6050 | I24: =($B24*I$2) -> 6325 | J24: =($B24*J$2) -> 6600 | K24: =($B24*K$2) -> 7150 | N24: 0.42857143 | T24: 0.42857143 | U24: 0.14285714
A25: 5490000705 | B25: 5500 | C25: =($B25*C$2) -> 4950 | D25: =($B25*D$2) -> 5225 | E25: =($B25*E$2) -> 5500 | F25: =($B25*F$2) -> 5665 | G25: =($B25*G$2) -> 5940 | H25: =($B25*H$2) -> 6050 | I25: =($B25*I$2) -> 6325 | J25: =($B25*J$2) -> 6600 | K25: =($B25*K$2) -> 7150 | M25: 0.083333333 | P25: 0.30555556 | Q25: 0.27777778 | R25: 0.33333333
A26: 5490000711 | B26: 5500 | C26: =($B26*C$2) -> 4950 | D26: =($B26*D$2) -> 5225 | E26: =($B26*E$2) -> 5500 | F26: =($B26*F$2) -> 5665 | G26: =($B26*G$2) -> 5940 | H26: =($B26*H$2) -> 6050 | I26: =($B26*I$2) -> 6325 | J26: =($B26*J$2) -> 6600 | K26: =($B26*K$2) -> 7150 | L26: 0.125 | O26: 0.20833333 | S26: 0.5 | V26: 0.16666667
A27: 222235 | B27: 6000 | C27: =($B27*C$2) -> 5400 | D27: =($B27*D$2) -> 5700 | E27: =($B27*E$2) -> 6000 | F27: =($B27*F$2) -> 6180 | G27: =($B27*G$2) -> 6480 | H27: =($B27*H$2) -> 6600 | I27: =($B27*I$2) -> 6900 | J27: =($B27*J$2) -> 7200 | K27: =($B27*K$2) -> 7800 | L27: 0.031578947 | M27: 0.031578947 | N27: 0.15789474 | O27: 0.052631579 | P27: 0.11578947 | Q27: 0.10526316 | R27: 0.12631579 | S27: 0.12631579 | T27: 0.15789474 | U27: 0.052631579 | V27: 0.042105263
A28: 222234 | B28: 6000 | C28: =($B28*C$2) -> 5400 | D28: =($B28*D$2) -> 5700 | E28: =($B28*E$2) -> 6000 | F28: =($B28*F$2) -> 6180 | G28: =($B28*G$2) -> 6480 | H28: =($B28*H$2) -> 6600 | I28: =($B28*I$2) -> 6900 | J28: =($B28*J$2) -> 7200 | K28: =($B28*K$2) -> 7800 | L28: 0.1719 | M28: 0.1257 | N28: 0.3654 | O28: 0.0203 | P28: 0.0133 | Q28: 0.0204 | R28: 0.0031 | S28: 0.2008 | T28: 0.056 | U28: 0.012 | V28: 0.0052 | W28: 0.0033 | X28: 0.0001 | Y28: 0.0024 | Z28: 0.0001
A29: 222223 | B29: 6000 | C29: =($B29*C$2) -> 5400 | D29: =($B29*D$2) -> 5700 | E29: =($B29*E$2) -> 6000 | F29: =($B29*F$2) -> 6180 | G29: =($B29*G$2) -> 6480 | H29: =($B29*H$2) -> 6600 | I29: =($B29*I$2) -> 6900 | J29: =($B29*J$2) -> 7200 | K29: =($B29*K$2) -> 7800 | L29: 0.21112111 | M29: 0.28692869 | N29: 0.20632063 | O29: 0.02170217 | P29: 0.0090009001 | Q29: 0.0270027 | R29: 0.00380038 | S29: 0.13521352 | T29: 0.079707971 | U29: 0.01450145 | V29: 0.00410041 | W29: 0.00010001 | Y29: 0.00040004 | Z29: 0.00010001
A30: 222222 | B30: 6000 | C30: =($B30*C$2) -> 5400 | D30: =($B30*D$2) -> 5700 | E30: =($B30*E$2) -> 6000 | F30: =($B30*F$2) -> 6180 | G30: =($B30*G$2) -> 6480 | H30: =($B30*H$2) -> 6600 | I30: =($B30*I$2) -> 6900 | J30: =($B30*J$2) -> 7200 | K30: =($B30*K$2) -> 7800 | L30: 0.03 | M30: 0.03 | N30: 0.1 | O30: 0.05 | P30: 0.1 | Q30: 0.1 | R30: 0.1 | S30: 0.08 | T30: 0.07 | U30: 0.03 | V30: 0.03 | W30: 0.09 | X30: 0.08 | Y30: 0.1 | Z30: 0.01
P40: 0.05
P41: 0.05
P42: 0.12
P43: 0.12
P44: 0.12
P45: 0.12
P46: 0.05
P47: 0.14
P48: 0.13
P49: 0.05
P50: 0.05

Sheet 3)Target & Cal_Staff
A1: Direct Sup. | D1: Target | P1: Actual | AB1: Percent (Actual vs Target) | AN1: Percent (Round) (Actual vs Target) | AZ1: Incentive
D2: 2 | E2: 3 | F2: 4 | G2: 5 | H2: 6 | I2: 7 | J2: 8 | K2: 9 | L2: 10 | M2: 11 | N2: 12 | O2: 13 | P2: 2 | Q2: 3 | R2: 4 | S2: 5 | T2: 6 | U2: 7 | V2: 8 | W2: 9 | X2: 10 | Y2: 11 | Z2: 12 | AA2: 13 | AB2: 2 | AC2: 3 | AD2: 4 | AE2: 5 | AF2: 6 | AG2: 7 | AH2: 8 | AI2: 9 | AJ2: 10 | AK2: 11 | AL2: 12 | AM2: 13 | AN2: 2 | AO2: 3 | AP2: 4 | AQ2: 5 | AR2: 6 | AS2: 7 | AT2: 8 | AU2: 9 | AV2: 10 | AW2: 11 | AX2: 12 | AY2: 13 | AZ2: 2 | BA2: 3 | BB2: 4 | BC2: 5 | BD2: 6 | BE2: 7 | BF2: 8 | BG2: 9 | BH2: 10 | BI2: 11 | BJ2: 12 | BK2: 13
A3: DirectSupCode | B3: Product | C3: Team | D3: Apr_T | E3: May_T | F3: Jun_T | G3: Jul_T | H3: Aug_T | I3: Sep_T | J3: Oct_T | K3: Nov_T | L3: Dec_T | M3: Jan_T | N3: Feb_T | O3: Mar_T | P3: Apr_A | Q3: May_A | R3: Jun_A | S3: Jul_A | T3: Aug_A | U3: Sep_A | V3: Oct_A | W3: Nov_A | X3: Dec_A | Y3: Jan_A | Z3: Feb_A | AA3: Mar_A | AB3: Apr_P | AC3: May_P | AD3: Jun_P | AE3: Jul_P | AF3: Aug_P | AG3: Sep_P | AH3: Oct_P | AI3: Nov_P | AJ3: Dec_P | AK3: Jan_P | AL3: Feb_P | AM3: Mar_P | AN3: Apr_I | AO3: May_I | AP3: Jun_I | AQ3: Jul_I | AR3: Aug_I | AS3: Sep_I | AT3: Oct_I | AU3: Nov_I | AV3: Dec_I | AW3: Jan_I | AX3: Feb_I | AY3: Mar_I | AZ3: Apr_I | BA3: May_I | BB3: Jun_I | BC3: Jul_I | BD3: Aug_I | BE3: Sep_I | BF3: Oct_I | BG3: Nov_I | BH3: Dec_I | BI3: Jan_I | BJ3: Feb_I | BK3: Mar_I | BM3: Emp Code | BN3: Incentive
A4: =VLOOKUP(C4,ASTBase!E:S,13,FALSE) -> 222208 | B4: AJ | C4: 5490000718 | D4: 2360 | E4: 2320 | F4: 2194 | G4: 2210 | H4: 2300 | I4: 2100 | J4: 2220 | K4: 2200 | L4: 2300 | M4: 2100 | N4: 2070 | O4: 2120 | P4: 3245.4 | AB4: =IFERROR(IF(VLOOKUP($B4,Shortage!$A:$M,AB$2,FALSE)="Shortage",1,IFERROR(ROUND(P4/D4,4),0)),IFERROR(ROUND(P4/D4,4),0)) -> 1 | AC4: =IFERROR(IF(VLOOKUP($B4,Shortage!$A:$M,AC$2,FALSE)="Shortage",1,IFERROR(ROUND(Q4/E4,4),0)),IFERROR(ROUND(Q4/E4,4),0)) -> 0 | AD4: =IFERROR(IF(VLOOKUP($B4,Shortage!$A:$M,AD$2,FALSE)="Shortage",1,IFERROR(ROUND(R4/F4,4),0)),IFERROR(ROUND(R4/F4,4),0)) -> 0 | AE4: =IFERROR(IF(VLOOKUP($B4,Shortage!$A:$M,AE$2,FALSE)="Shortage",1,IFERROR(ROUND(S4/G4,4),0)),IFERROR(ROUND(S4/G4,4),0)) -> 0 | AF4: =IFERROR(IF(VLOOKUP($B4,Shortage!$A:$M,AF$2,FALSE)="Shortage",1,IFERROR(ROUND(T4/H4,4),0)),IFERROR(ROUND(T4/H4,4),0)) -> 0 | AG4: =IFERROR(IF(VLOOKUP($B4,Shortage!$A:$M,AG$2,FALSE)="Shortage",1,IFERROR(ROUND(U4/I4,4),0)),IFERROR(ROUND(U4/I4,4),0)) -> 0 | AH4: =IFERROR(IF(VLOOKUP($B4,Shortage!$A:$M,AH$2,FALSE)="Shortage",1,IFERROR(ROUND(V4/J4,4),0)),IFERROR(ROUND(V4/J4,4),0)) -> 0 | AI4: =IFERROR(IF(VLOOKUP($B4,Shortage!$A:$M,AI$2,FALSE)="Shortage",1,IFERROR(ROUND(W4/K4,4),0)),IFERROR(ROUND(W4/K4,4),0)) -> 0 | ... AM4: =IFERROR(IF(VLOOKUP($B4,Shortage!$A:$M,AM$2,FALSE)="Shortage",1,IFERROR(ROUND(AA4/O4,4),0)),IFERROR(ROUND(AA4/O4,4),0)) -> 0 | AN4: =IFERROR(_xlfn.XLOOKUP(AB4,'2) หลักการคำนวน Table'!$C$3:$K$3,'2) หลักการคำนวน Table'!$C$3:$K$3,,1),INDEX('2) หลักการคำนวน Table'!$C$3:$K$3,1)) -> 1 | AO4: =IFERROR( _xlfn.XLOOKUP(AC4,'2) หลักการคำนวน Table'!$C$3:$K$3,'2) หลักการคำนวน Table'!$C$3:$K$3,,1), IF(AC4<MIN('2) หลักการคำนวน Table'!$C$3:$K$3), MIN('2) หลักการคำนวน Table'!$C$3:$K$3), MAX('2) หลักการคำนวน Table'!$C$3:$K$3) ) ) -> 0.9 | AP4: =IFERROR( _xlfn.XLOOKUP(AD4,'2) หลักการคำนวน Table'!$C$3:$K$3,'2) หลักการคำนวน Table'!$C$3:$K$3,,1), IF(AD4<MIN('2) หลักการคำนวน Table'!$C$3:$K$3), MIN('2) หลักการคำนวน Table'!$C$3:$K$3), MAX('2) หลักการคำนวน Table'!$C$3:$K$3) ) ) -> 0.9 | AQ4: =IFERROR( _xlfn.XLOOKUP(AE4,'2) หลักการคำนวน Table'!$C$3:$K$3,'2) หลักการคำนวน Table'!$C$3:$K$3,,1), IF(AE4<MIN('2) หลักการคำนวน Table'!$C$3:$K$3), MIN('2) หลักการคำนวน Table'!$C$3:$K$3), MAX('2) หลักการคำนวน Table'!$C$3:$K$3) ) ) -> 0.9 | AR4: =IFERROR( _xlfn.XLOOKUP(AF4,'2) หลักการคำนวน Table'!$C$3:$K$3,'2) หลักการคำนวน Table'!$C$3:$K$3,,1), IF(AF4<MIN('2) หลักการคำนวน Table'!$C$3:$K$3), MIN('2) หลักการคำนวน Table'!$C$3:$K$3), MAX('2) หลักการคำนวน Table'!$C$3:$K$3) ) ) -> 0.9 | AS4: =IFERROR( _xlfn.XLOOKUP(AG4,'2) หลักการคำนวน Table'!$C$3:$K$3,'2) หลักการคำนวน Table'!$C$3:$K$3,,1), IF(AG4<MIN('2) หลักการคำนวน Table'!$C$3:$K$3), MIN('2) หลักการคำนวน Table'!$C$3:$K$3), MAX('2) หลักการคำนวน Table'!$C$3:$K$3) ) ) -> 0.9 | AT4: =IFERROR( _xlfn.XLOOKUP(AH4,'2) หลักการคำนวน Table'!$C$3:$K$3,'2) หลักการคำนวน Table'!$C$3:$K$3,,1), IF(AH4<MIN('2) หลักการคำนวน Table'!$C$3:$K$3), MIN('2) หลักการคำนวน Table'!$C$3:$K$3), MAX('2) หลักการคำนวน Table'!$C$3:$K$3) ) ) -> 0.9 | AU4: =IFERROR( _xlfn.XLOOKUP(AI4,'2) หลักการคำนวน Table'!$C$3:$K$3,'2) หลักการคำนวน Table'!$C$3:$K$3,,1), IF(AI4<MIN('2) หลักการคำนวน Table'!$C$3:$K$3), MIN('2) หลักการคำนวน Table'!$C$3:$K$3), MAX('2) หลักการคำนวน Table'!$C$3:$K$3) ) ) -> 0.9 | AV4: =IFERROR( _xlfn.XLOOKUP(AJ4,'2) หลักการคำนวน Table'!$C$3:$K$3,'2) หลักการคำนวน Table'!$C$3:$K$3,,1), IF(AJ4<MIN('2) หลักการคำนวน Table'!$C$3:$K$3), MIN('2) หลักการคำนวน Table'!$C$3:$K$3), MAX('2) หลักการคำนวน Table'!$C$3:$K$3) ) ) -> 0.9 | ... AY4: =IFERROR( _xlfn.XLOOKUP(AM4,'2) หลักการคำนวน Table'!$C$3:$K$3,'2) หลักการคำนวน Table'!$C$3:$K$3,,1), IF(AM4<MIN('2) หลักการคำนวน Table'!$C$3:$K$3), MIN('2) หลักการคำนวน Table'!$C$3:$K$3), MAX('2) หลักการคำนวน Table'!$C$3:$K$3) ) ) -> 0.9 | AZ4: {=ROUND((_xlfn.XLOOKUP($C4,'2) หลักการคำนวน Table'!$A$4:$A$36, _xlfn.XLOOKUP(AN4,'2) หลักการคำนวน Table'!$C$3:$K$3,'2) หลักการคำนวน Table'!$C$4:$K$36,,-1)))*(_xlfn.XLOOKUP($C4,'2) หลักการคำนวน Table'!$A$4:$A$36, _xlfn.XLOOKUP($B4,'2) หลักการคำนวน Table'!$L$3:$Z$3,'2) หลักการคำนวน Table'!$L$4:$Z$36))),0)} -> 133 | BA4: {=ROUND((_xlfn.XLOOKUP($C4,'2) หลักการคำนวน Table'!$A$4:$A$36, _xlfn.XLOOKUP(AO4,'2) หลักการคำนวน Table'!$C$3:$K$3,'2) หลักการคำนวน Table'!$C$4:$K$36,,-1)))*(_xlfn.XLOOKUP($C4,'2) หลักการคำนวน Table'!$A$4:$A$36, _xlfn.XLOOKUP($B4,'2) หลักการคำนวน Table'!$L$3:$Z$3,'2) หลักการคำนวน Table'!$L$4:$Z$36))),0)} -> 120 | BB4: {=ROUND((_xlfn.XLOOKUP($C4,'2) หลักการคำนวน Table'!$A$4:$A$36, _xlfn.XLOOKUP(AP4,'2) หลักการคำนวน Table'!$C$3:$K$3,'2) หลักการคำนวน Table'!$C$4:$K$36,,-1)))*(_xlfn.XLOOKUP($C4,'2) หลักการคำนวน Table'!$A$4:$A$36, _xlfn.XLOOKUP($B4,'2) หลักการคำนวน Table'!$L$3:$Z$3,'2) หลักการคำนวน Table'!$L$4:$Z$36))),0)} -> 120 | BC4: {=ROUND((_xlfn.XLOOKUP($C4,'2) หลักการคำนวน Table'!$A$4:$A$36, _xlfn.XLOOKUP(AQ4,'2) หลักการคำนวน Table'!$C$3:$K$3,'2) หลักการคำนวน Table'!$C$4:$K$36,,-1)))*(_xlfn.XLOOKUP($C4,'2) หลักการคำนวน Table'!$A$4:$A$36, _xlfn.XLOOKUP($B4,'2) หลักการคำนวน Table'!$L$3:$Z$3,'2) หลักการคำนวน Table'!$L$4:$Z$36))),0)} -> 120 | BD4: {=ROUND((_xlfn.XLOOKUP($C4,'2) หลักการคำนวน Table'!$A$4:$A$36, _xlfn.XLOOKUP(AR4,'2) หลักการคำนวน Table'!$C$3:$K$3,'2) หลักการคำนวน Table'!$C$4:$K$36,,-1)))*(_xlfn.XLOOKUP($C4,'2) หลักการคำนวน Table'!$A$4:$A$36, _xlfn.XLOOKUP($B4,'2) หลักการคำนวน Table'!$L$3:$Z$3,'2) หลักการคำนวน Table'!$L$4:$Z$36))),0)} -> 120 | BE4: {=ROUND((_xlfn.XLOOKUP($C4,'2) หลักการคำนวน Table'!$A$4:$A$36, _xlfn.XLOOKUP(AS4,'2) หลักการคำนวน Table'!$C$3:$K$3,'2) หลักการคำนวน Table'!$C$4:$K$36,,-1)))*(_xlfn.XLOOKUP($C4,'2) หลักการคำนวน Table'!$A$4:$A$36, _xlfn.XLOOKUP($B4,'2) หลักการคำนวน Table'!$L$3:$Z$3,'2) หลักการคำนวน Table'!$L$4:$Z$36))),0)} -> 120 | BF4: {=ROUND((_xlfn.XLOOKUP($C4,'2) หลักการคำนวน Table'!$A$4:$A$36, _xlfn.XLOOKUP(AT4,'2) หลักการคำนวน Table'!$C$3:$K$3,'2) หลักการคำนวน Table'!$C$4:$K$36,,-1)))*(_xlfn.XLOOKUP($C4,'2) หลักการคำนวน Table'!$A$4:$A$36, _xlfn.XLOOKUP($B4,'2) หลักการคำนวน Table'!$L$3:$Z$3,'2) หลักการคำนวน Table'!$L$4:$Z$36))),0)} -> 120 | BG4: {=ROUND((_xlfn.XLOOKUP($C4,'2) หลักการคำนวน Table'!$A$4:$A$36, _xlfn.XLOOKUP(AU4,'2) หลักการคำนวน Table'!$C$3:$K$3,'2) หลักการคำนวน Table'!$C$4:$K$36,,-1)))*(_xlfn.XLOOKUP($C4,'2) หลักการคำนวน Table'!$A$4:$A$36, _xlfn.XLOOKUP($B4,'2) หลักการคำนวน Table'!$L$3:$Z$3,'2) หลักการคำนวน Table'!$L$4:$Z$36))),0)} -> 120 | ... BK4: {=ROUND((_xlfn.XLOOKUP($C4,'2) หลักการคำนวน Table'!$A$4:$A$36, _xlfn.XLOOKUP(AY4,'2) หลักการคำนวน Table'!$C$3:$K$3,'2) หลักการคำนวน Table'!$C$4:$K$36,,-1)))*(_xlfn.XLOOKUP($C4,'2) หลักการคำนวน Table'!$A$4:$A$36, _xlfn.XLOOKUP($B4,'2) หลักการคำนวน Table'!$L$3:$Z$3,'2) หลักการคำนวน Table'!$L$4:$Z$36))),0)} -> 120 | BM4: 222209 | BN4: 133
A5: =VLOOKUP(C5,ASTBase!E:S,13,FALSE) -> 222208 | B5: AJP | C5: 5490000718 | D5: 210 | E5: 150 | F5: 160 | G5: 150 | H5: 151 | I5: 151 | J5: 151 | K5: 151 | L5: 101 | M5: 120 | N5: 100 | O5: 100 | P5: 1209.6 | AB5: =IFERROR(IF(VLOOKUP($B5,Shortage!$A:$M,AB$2,FALSE)="Shortage",1,IFERROR(ROUND(P5/D5,4),0)),IFERROR(ROUND(P5/D5,4),0)) -> 5.76 | AC5: =IFERROR(IF(VLOOKUP($B5,Shortage!$A:$M,AC$2,FALSE)="Shortage",1,IFERROR(ROUND(Q5/E5,4),0)),IFERROR(ROUND(Q5/E5,4),0)) -> 0 | AD5: =IFERROR(IF(VLOOKUP($B5,Shortage!$A:$M,AD$2,FALSE)="Shortage",1,IFERROR(ROUND(R5/F5,4),0)),IFERROR(ROUND(R5/F5,4),0)) -> 0 | AE5: =IFERROR(IF(VLOOKUP($B5,Shortage!$A:$M,AE$2,FALSE)="Shortage",1,IFERROR(ROUND(S5/G5,4),0)),IFERROR(ROUND(S5/G5,4),0)) -> 0 | AF5: =IFERROR(IF(VLOOKUP($B5,Shortage!$A:$M,AF$2,FALSE)="Shortage",1,IFERROR(ROUND(T5/H5,4),0)),IFERROR(ROUND(T5/H5,4),0)) -> 0 | AG5: =IFERROR(IF(VLOOKUP($B5,Shortage!$A:$M,AG$2,FALSE)="Shortage",1,IFERROR(ROUND(U5/I5,4),0)),IFERROR(ROUND(U5/I5,4),0)) -> 0 | AH5: =IFERROR(IF(VLOOKUP($B5,Shortage!$A:$M,AH$2,FALSE)="Shortage",1,IFERROR(ROUND(V5/J5,4),0)),IFERROR(ROUND(V5/J5,4),0)) -> 0 | AI5: =IFERROR(IF(VLOOKUP($B5,Shortage!$A:$M,AI$2,FALSE)="Shortage",1,IFERROR(ROUND(W5/K5,4),0)),IFERROR(ROUND(W5/K5,4),0)) -> 0 | ... AM5: =IFERROR(IF(VLOOKUP($B5,Shortage!$A:$M,AM$2,FALSE)="Shortage",1,IFERROR(ROUND(AA5/O5,4),0)),IFERROR(ROUND(AA5/O5,4),0)) -> 0 | AN5: =IFERROR(_xlfn.XLOOKUP(AB5,'2) หลักการคำนวน Table'!$C$3:$K$3,'2) หลักการคำนวน Table'!$C$3:$K$3,,1),INDEX('2) หลักการคำนวน Table'!$C$3:$K$3,1)) -> 20 | AO5: =IFERROR( _xlfn.XLOOKUP(AC5,'2) หลักการคำนวน Table'!$C$3:$K$3,'2) หลักการคำนวน Table'!$C$3:$K$3,,1), IF(AC5<MIN('2) หลักการคำนวน Table'!$C$3:$K$3), MIN('2) หลักการคำนวน Table'!$C$3:$K$3), MAX('2) หลักการคำนวน Table'!$C$3:$K$3) ) ) -> 0.9 | AP5: =IFERROR( _xlfn.XLOOKUP(AD5,'2) หลักการคำนวน Table'!$C$3:$K$3,'2) หลักการคำนวน Table'!$C$3:$K$3,,1), IF(AD5<MIN('2) หลักการคำนวน Table'!$C$3:$K$3), MIN('2) หลักการคำนวน Table'!$C$3:$K$3), MAX('2) หลักการคำนวน Table'!$C$3:$K$3) ) ) -> 0.9 | AQ5: =IFERROR( _xlfn.XLOOKUP(AE5,'2) หลักการคำนวน Table'!$C$3:$K$3,'2) หลักการคำนวน Table'!$C$3:$K$3,,1), IF(AE5<MIN('2) หลักการคำนวน Table'!$C$3:$K$3), MIN('2) หลักการคำนวน Table'!$C$3:$K$3), MAX('2) หลักการคำนวน Table'!$C$3:$K$3) ) ) -> 0.9 | AR5: =IFERROR( _xlfn.XLOOKUP(AF5,'2) หลักการคำนวน Table'!$C$3:$K$3,'2) หลักการคำนวน Table'!$C$3:$K$3,,1), IF(AF5<MIN('2) หลักการคำนวน Table'!$C$3:$K$3), MIN('2) หลักการคำนวน Table'!$C$3:$K$3), MAX('2) หลักการคำนวน Table'!$C$3:$K$3) ) ) -> 0.9 | AS5: =IFERROR( _xlfn.XLOOKUP(AG5,'2) หลักการคำนวน Table'!$C$3:$K$3,'2) หลักการคำนวน Table'!$C$3:$K$3,,1), IF(AG5<MIN('2) หลักการคำนวน Table'!$C$3:$K$3), MIN('2) หลักการคำนวน Table'!$C$3:$K$3), MAX('2) หลักการคำนวน Table'!$C$3:$K$3) ) ) -> 0.9 | AT5: =IFERROR( _xlfn.XLOOKUP(AH5,'2) หลักการคำนวน Table'!$C$3:$K$3,'2) หลักการคำนวน Table'!$C$3:$K$3,,1), IF(AH5<MIN('2) หลักการคำนวน Table'!$C$3:$K$3), MIN('2) หลักการคำนวน Table'!$C$3:$K$3), MAX('2) หลักการคำนวน Table'!$C$3:$K$3) ) ) -> 0.9 | AU5: =IFERROR( _xlfn.XLOOKUP(AI5,'2) หลักการคำนวน Table'!$C$3:$K$3,'2) หลักการคำนวน Table'!$C$3:$K$3,,1), IF(AI5<MIN('2) หลักการคำนวน Table'!$C$3:$K$3), MIN('2) หลักการคำนวน Table'!$C$3:$K$3), MAX('2) หลักการคำนวน Table'!$C$3:$K$3) ) ) -> 0.9 | AV5: =IFERROR( _xlfn.XLOOKUP(AJ5,'2) หลักการคำนวน Table'!$C$3:$K$3,'2) หลักการคำนวน Table'!$C$3:$K$3,,1), IF(AJ5<MIN('2) หลักการคำนวน Table'!$C$3:$K$3), MIN('2) หลักการคำนวน Table'!$C$3:$K$3), MAX('2) หลักการคำนวน Table'!$C$3:$K$3) ) ) -> 0.9 | ... AY5: =IFERROR( _xlfn.XLOOKUP(AM5,'2) หลักการคำนวน Table'!$C$3:$K$3,'2) หลักการคำนวน Table'!$C$3:$K$3,,1), IF(AM5<MIN('2) หลักการคำนวน Table'!$C$3:$K$3), MIN('2) หลักการคำนวน Table'!$C$3:$K$3), MAX('2) หลักการคำนวน Table'!$C$3:$K$3) ) ) -> 0.9 | AZ5: {=ROUND((_xlfn.XLOOKUP($C5,'2) หลักการคำนวน Table'!$A$4:$A$36, _xlfn.XLOOKUP(AN5,'2) หลักการคำนวน Table'!$C$3:$K$3,'2) หลักการคำนวน Table'!$C$4:$K$36,,-1)))*(_xlfn.XLOOKUP($C5,'2) หลักการคำนวน Table'!$A$4:$A$36, _xlfn.XLOOKUP($B5,'2) หลักการคำนวน Table'!$L$3:$Z$3,'2) หลักการคำนวน Table'!$L$4:$Z$36))),0)} -> 289 | BA5: {=ROUND((_xlfn.XLOOKUP($C5,'2) หลักการคำนวน Table'!$A$4:$A$36, _xlfn.XLOOKUP(AO5,'2) หลักการคำนวน Table'!$C$3:$K$3,'2) หลักการคำนวน Table'!$C$4:$K$36,,-1)))*(_xlfn.XLOOKUP($C5,'2) หลักการคำนวน Table'!$A$4:$A$36, _xlfn.XLOOKUP($B5,'2) หลักการคำนวน Table'!$L$3:$Z$3,'2) หลักการคำนวน Table'!$L$4:$Z$36))),0)} -> 200 | BB5: {=ROUND((_xlfn.XLOOKUP($C5,'2) หลักการคำนวน Table'!$A$4:$A$36, _xlfn.XLOOKUP(AP5,'2) หลักการคำนวน Table'!$C$3:$K$3,'2) หลักการคำนวน Table'!$C$4:$K$36,,-1)))*(_xlfn.XLOOKUP($C5,'2) หลักการคำนวน Table'!$A$4:$A$36, _xlfn.XLOOKUP($B5,'2) หลักการคำนวน Table'!$L$3:$Z$3,'2) หลักการคำนวน Table'!$L$4:$Z$36))),0)} -> 200 | BC5: {=ROUND((_xlfn.XLOOKUP($C5,'2) หลักการคำนวน Table'!$A$4:$A$36, _xlfn.XLOOKUP(AQ5,'2) หลักการคำนวน Table'!$C$3:$K$3,'2) หลักการคำนวน Table'!$C$4:$K$36,,-1)))*(_xlfn.XLOOKUP($C5,'2) หลักการคำนวน Table'!$A$4:$A$36, _xlfn.XLOOKUP($B5,'2) หลักการคำนวน Table'!$L$3:$Z$3,'2) หลักการคำนวน Table'!$L$4:$Z$36))),0)} -> 200 | BD5: {=ROUND((_xlfn.XLOOKUP($C5,'2) หลักการคำนวน Table'!$A$4:$A$36, _xlfn.XLOOKUP(AR5,'2) หลักการคำนวน Table'!$C$3:$K$3,'2) หลักการคำนวน Table'!$C$4:$K$36,,-1)))*(_xlfn.XLOOKUP($C5,'2) หลักการคำนวน Table'!$A$4:$A$36, _xlfn.XLOOKUP($B5,'2) หลักการคำนวน Table'!$L$3:$Z$3,'2) หลักการคำนวน Table'!$L$4:$Z$36))),0)} -> 200 | BE5: {=ROUND((_xlfn.XLOOKUP($C5,'2) หลักการคำนวน Table'!$A$4:$A$36, _xlfn.XLOOKUP(AS5,'2) หลักการคำนวน Table'!$C$3:$K$3,'2) หลักการคำนวน Table'!$C$4:$K$36,,-1)))*(_xlfn.XLOOKUP($C5,'2) หลักการคำนวน Table'!$A$4:$A$36, _xlfn.XLOOKUP($B5,'2) หลักการคำนวน Table'!$L$3:$Z$3,'2) หลักการคำนวน Table'!$L$4:$Z$36))),0)} -> 200 | BF5: {=ROUND((_xlfn.XLOOKUP($C5,'2) หลักการคำนวน Table'!$A$4:$A$36, _xlfn.XLOOKUP(AT5,'2) หลักการคำนวน Table'!$C$3:$K$3,'2) หลักการคำนวน Table'!$C$4:$K$36,,-1)))*(_xlfn.XLOOKUP($C5,'2) หลักการคำนวน Table'!$A$4:$A$36, _xlfn.XLOOKUP($B5,'2) หลักการคำนวน Table'!$L$3:$Z$3,'2) หลักการคำนวน Table'!$L$4:$Z$36))),0)} -> 200 | BG5: {=ROUND((_xlfn.XLOOKUP($C5,'2) หลักการคำนวน Table'!$A$4:$A$36, _xlfn.XLOOKUP(AU5,'2) หลักการคำนวน Table'!$C$3:$K$3,'2) หลักการคำนวน Table'!$C$4:$K$36,,-1)))*(_xlfn.XLOOKUP($C5,'2) หลักการคำนวน Table'!$A$4:$A$36, _xlfn.XLOOKUP($B5,'2) หลักการคำนวน Table'!$L$3:$Z$3,'2) หลักการคำนวน Table'!$L$4:$Z$36))),0)} -> 200 | ... BK5: {=ROUND((_xlfn.XLOOKUP($C5,'2) หลักการคำนวน Table'!$A$4:$A$36, _xlfn.XLOOKUP(AY5,'2) หลักการคำนวน Table'!$C$3:$K$3,'2) หลักการคำนวน Table'!$C$4:$K$36,,-1)))*(_xlfn.XLOOKUP($C5,'2) หลักการคำนวน Table'!$A$4:$A$36, _xlfn.XLOOKUP($B5,'2) หลักการคำนวน Table'!$L$3:$Z$3,'2) หลักการคำนวน Table'!$L$4:$Z$36))),0)} -> 200 | BM5: 222209 | BN5: 289
A6: =VLOOKUP(C6,ASTBase!E:S,13,FALSE) -> 222208 | B6: AMV | C6: 5490000718 | D6: 70 | E6: 53 | F6: 50 | G6: 45 | H6: 63 | I6: 50 | J6: 55 | K6: 58 | L6: 60 | M6: 55 | N6: 55 | O6: 46 | P6: 214 | AB6: =IFERROR(IF(VLOOKUP($B6,Shortage!$A:$M,AB$2,FALSE)="Shortage",1,IFERROR(ROUND(P6/D6,4),0)),IFERROR(ROUND(P6/D6,4),0)) -> 3.0571 | AC6: =IFERROR(IF(VLOOKUP($B6,Shortage!$A:$M,AC$2,FALSE)="Shortage",1,IFERROR(ROUND(Q6/E6,4),0)),IFERROR(ROUND(Q6/E6,4),0)) -> 0 | AD6: =IFERROR(IF(VLOOKUP($B6,Shortage!$A:$M,AD$2,FALSE)="Shortage",1,IFERROR(ROUND(R6/F6,4),0)),IFERROR(ROUND(R6/F6,4),0)) -> 0 | AE6: =IFERROR(IF(VLOOKUP($B6,Shortage!$A:$M,AE$2,FALSE)="Shortage",1,IFERROR(ROUND(S6/G6,4),0)),IFERROR(ROUND(S6/G6,4),0)) -> 0 | AF6: =IFERROR(IF(VLOOKUP($B6,Shortage!$A:$M,AF$2,FALSE)="Shortage",1,IFERROR(ROUND(T6/H6,4),0)),IFERROR(ROUND(T6/H6,4),0)) -> 0 | AG6: =IFERROR(IF(VLOOKUP($B6,Shortage!$A:$M,AG$2,FALSE)="Shortage",1,IFERROR(ROUND(U6/I6,4),0)),IFERROR(ROUND(U6/I6,4),0)) -> 0 | AH6: =IFERROR(IF(VLOOKUP($B6,Shortage!$A:$M,AH$2,FALSE)="Shortage",1,IFERROR(ROUND(V6/J6,4),0)),IFERROR(ROUND(V6/J6,4),0)) -> 0 | AI6: =IFERROR(IF(VLOOKUP($B6,Shortage!$A:$M,AI$2,FALSE)="Shortage",1,IFERROR(ROUND(W6/K6,4),0)),IFERROR(ROUND(W6/K6,4),0)) -> 0 | ... AM6: =IFERROR(IF(VLOOKUP($B6,Shortage!$A:$M,AM$2,FALSE)="Shortage",1,IFERROR(ROUND(AA6/O6,4),0)),IFERROR(ROUND(AA6/O6,4),0)) -> 0 | AN6: =IFERROR(_xlfn.XLOOKUP(AB6,'2) หลักการคำนวน Table'!$C$3:$K$3,'2) หลักการคำนวน Table'!$C$3:$K$3,,1),INDEX('2) หลักการคำนวน Table'!$C$3:$K$3,1)) -> 20 | AO6: =IFERROR( _xlfn.XLOOKUP(AC6,'2) หลักการคำนวน Table'!$C$3:$K$3,'2) หลักการคำนวน Table'!$C$3:$K$3,,1), IF(AC6<MIN('2) หลักการคำนวน Table'!$C$3:$K$3), MIN('2) หลักการคำนวน Table'!$C$3:$K$3), MAX('2) หลักการคำนวน Table'!$C$3:$K$3) ) ) -> 0.9 | AP6: =IFERROR( _xlfn.XLOOKUP(AD6,'2) หลักการคำนวน Table'!$C$3:$K$3,'2) หลักการคำนวน Table'!$C$3:$K$3,,1), IF(AD6<MIN('2) หลักการคำนวน Table'!$C$3:$K$3), MIN('2) หลักการคำนวน Table'!$C$3:$K$3), MAX('2) หลักการคำนวน Table'!$C$3:$K$3) ) ) -> 0.9 | AQ6: =IFERROR( _xlfn.XLOOKUP(AE6,'2) หลักการคำนวน Table'!$C$3:$K$3,'2) หลักการคำนวน Table'!$C$3:$K$3,,1), IF(AE6<MIN('2) หลักการคำนวน Table'!$C$3:$K$3), MIN('2) หลักการคำนวน Table'!$C$3:$K$3), MAX('2) หลักการคำนวน Table'!$C$3:$K$3) ) ) -> 0.9 | AR6: =IFERROR( _xlfn.XLOOKUP(AF6,'2) หลักการคำนวน Table'!$C$3:$K$3,'2) หลักการคำนวน Table'!$C$3:$K$3,,1), IF(AF6<MIN('2) หลักการคำนวน Table'!$C$3:$K$3), MIN('2) หลักการคำนวน Table'!$C$3:$K$3), MAX('2) หลักการคำนวน Table'!$C$3:$K$3) ) ) -> 0.9 | AS6: =IFERROR( _xlfn.XLOOKUP(AG6,'2) หลักการคำนวน Table'!$C$3:$K$3,'2) หลักการคำนวน Table'!$C$3:$K$3,,1), IF(AG6<MIN('2) หลักการคำนวน Table'!$C$3:$K$3), MIN('2) หลักการคำนวน Table'!$C$3:$K$3), MAX('2) หลักการคำนวน Table'!$C$3:$K$3) ) ) -> 0.9 | AT6: =IFERROR( _xlfn.XLOOKUP(AH6,'2) หลักการคำนวน Table'!$C$3:$K$3,'2) หลักการคำนวน Table'!$C$3:$K$3,,1), IF(AH6<MIN('2) หลักการคำนวน Table'!$C$3:$K$3), MIN('2) หลักการคำนวน Table'!$C$3:$K$3), MAX('2) หลักการคำนวน Table'!$C$3:$K$3) ) ) -> 0.9 | AU6: =IFERROR( _xlfn.XLOOKUP(AI6,'2) หลักการคำนวน Table'!$C$3:$K$3,'2) หลักการคำนวน Table'!$C$3:$K$3,,1), IF(AI6<MIN('2) หลักการคำนวน Table'!$C$3:$K$3), MIN('2) หลักการคำนวน Table'!$C$3:$K$3), MAX('2) หลักการคำนวน Table'!$C$3:$K$3) ) ) -> 0.9 | AV6: =IFERROR( _xlfn.XLOOKUP(AJ6,'2) หลักการคำนวน Table'!$C$3:$K$3,'2) หลักการคำนวน Table'!$C$3:$K$3,,1), IF(AJ6<MIN('2) หลักการคำนวน Table'!$C$3:$K$3), MIN('2) หลักการคำนวน Table'!$C$3:$K$3), MAX('2) หลักการคำนวน Table'!$C$3:$K$3) ) ) -> 0.9 | ... AY6: =IFERROR( _xlfn.XLOOKUP(AM6,'2) หลักการคำนวน Table'!$C$3:$K$3,'2) หลักการคำนวน Table'!$C$3:$K$3,,1), IF(AM6<MIN('2) หลักการคำนวน Table'!$C$3:$K$3), MIN('2) หลักการคำนวน Table'!$C$3:$K$3), MAX('2) หลักการคำนวน Table'!$C$3:$K$3) ) ) -> 0.9 | AZ6: {=ROUND((_xlfn.XLOOKUP($C6,'2) หลักการคำนวน Table'!$A$4:$A$36, _xlfn.XLOOKUP(AN6,'2) หลักการคำนวน Table'!$C$3:$K$3,'2) หลักการคำนวน Table'!$C$4:$K$36,,-1)))*(_xlfn.XLOOKUP($C6,'2) หลักการคำนวน Table'!$A$4:$A$36, _xlfn.XLOOKUP($B6,'2) หลักการคำนวน Table'!$L$3:$Z$3,'2) หลักการคำนวน Table'!$L$4:$Z$36))),0)} -> 116 | BA6: {=ROUND((_xlfn.XLOOKUP($C6,'2) หลักการคำนวน Table'!$A$4:$A$36, _xlfn.XLOOKUP(AO6,'2) หลักการคำนวน Table'!$C$3:$K$3,'2) หลักการคำนวน Table'!$C$4:$K$36,,-1)))*(_xlfn.XLOOKUP($C6,'2) หลักการคำนวน Table'!$A$4:$A$36, _xlfn.XLOOKUP($B6,'2) หลักการคำนวน Table'!$L$3:$Z$3,'2) หลักการคำนวน Table'!$L$4:$Z$36))),0)} -> 80 | BB6: {=ROUND((_xlfn.XLOOKUP($C6,'2) หลักการคำนวน Table'!$A$4:$A$36, _xlfn.XLOOKUP(AP6,'2) หลักการคำนวน Table'!$C$3:$K$3,'2) หลักการคำนวน Table'!$C$4:$K$36,,-1)))*(_xlfn.XLOOKUP($C6,'2) หลักการคำนวน Table'!$A$4:$A$36, _xlfn.XLOOKUP($B6,'2) หลักการคำนวน Table'!$L$3:$Z$3,'2) หลักการคำนวน Table'!$L$4:$Z$36))),0)} -> 80 | BC6: {=ROUND((_xlfn.XLOOKUP($C6,'2) หลักการคำนวน Table'!$A$4:$A$36, _xlfn.XLOOKUP(AQ6,'2) หลักการคำนวน Table'!$C$3:$K$3,'2) หลักการคำนวน Table'!$C$4:$K$36,,-1)))*(_xlfn.XLOOKUP($C6,'2) หลักการคำนวน Table'!$A$4:$A$36, _xlfn.XLOOKUP($B6,'2) หลักการคำนวน Table'!$L$3:$Z$3,'2) หลักการคำนวน Table'!$L$4:$Z$36))),0)} -> 80 | BD6: {=ROUND((_xlfn.XLOOKUP($C6,'2) หลักการคำนวน Table'!$A$4:$A$36, _xlfn.XLOOKUP(AR6,'2) หลักการคำนวน Table'!$C$3:$K$3,'2) หลักการคำนวน Table'!$C$4:$K$36,,-1)))*(_xlfn.XLOOKUP($C6,'2) หลักการคำนวน Table'!$A$4:$A$36, _xlfn.XLOOKUP($B6,'2) หลักการคำนวน Table'!$L$3:$Z$3,'2) หลักการคำนวน Table'!$L$4:$Z$36))),0)} -> 80 | BE6: {=ROUND((_xlfn.XLOOKUP($C6,'2) หลักการคำนวน Table'!$A$4:$A$36, _xlfn.XLOOKUP(AS6,'2) หลักการคำนวน Table'!$C$3:$K$3,'2) หลักการคำนวน Table'!$C$4:$K$36,,-1)))*(_xlfn.XLOOKUP($C6,'2) หลักการคำนวน Table'!$A$4:$A$36, _xlfn.XLOOKUP($B6,'2) หลักการคำนวน Table'!$L$3:$Z$3,'2) หลักการคำนวน Table'!$L$4:$Z$36))),0)} -> 80 | BF6: {=ROUND((_xlfn.XLOOKUP($C6,'2) หลักการคำนวน Table'!$A$4:$A$36, _xlfn.XLOOKUP(AT6,'2) หลักการคำนวน Table'!$C$3:$K$3,'2) หลักการคำนวน Table'!$C$4:$K$36,,-1)))*(_xlfn.XLOOKUP($C6,'2) หลักการคำนวน Table'!$A$4:$A$36, _xlfn.XLOOKUP($B6,'2) หลักการคำนวน Table'!$L$3:$Z$3,'2) หลักการคำนวน Table'!$L$4:$Z$36))),0)} -> 80 | BG6: {=ROUND((_xlfn.XLOOKUP($C6,'2) หลักการคำนวน Table'!$A$4:$A$36, _xlfn.XLOOKUP(AU6,'2) หลักการคำนวน Table'!$C$3:$K$3,'2) หลักการคำนวน Table'!$C$4:$K$36,,-1)))*(_xlfn.XLOOKUP($C6,'2) หลักการคำนวน Table'!$A$4:$A$36, _xlfn.XLOOKUP($B6,'2) หลักการคำนวน Table'!$L$3:$Z$3,'2) หลักการคำนวน Table'!$L$4:$Z$36))),0)} -> 80 | ... BK6: {=ROUND((_xlfn.XLOOKUP($C6,'2) หลักการคำนวน Table'!$A$4:$A$36, _xlfn.XLOOKUP(AY6,'2) หลักการคำนวน Table'!$C$3:$K$3,'2) หลักการคำนวน Table'!$C$4:$K$36,,-1)))*(_xlfn.XLOOKUP($C6,'2) หลักการคำนวน Table'!$A$4:$A$36, _xlfn.XLOOKUP($B6,'2) หลักการคำนวน Table'!$L$3:$Z$3,'2) หลักการคำนวน Table'!$L$4:$Z$36))),0)} -> 80 | BM6: 222209 | BN6: 116
A7: =VLOOKUP(C7,ASTBase!E:S,13,FALSE) -> 222208 | B7: BD | C7: 5490000718 | D7: 1549 | E7: 1355 | F7: 1180 | G7: 1247 | H7: 2095 | I7: 1740 | J7: 1910 | K7: 1980 | L7: 1916 | M7: 2089 | N7: 1925 | O7: 1940 | P7: 622 | AB7: =IFERROR(IF(VLOOKUP($B7,Shortage!$A:$M,AB$2,FALSE)="Shortage",1,IFERROR(ROUND(P7/D7,4),0)),IFERROR(ROUND(P7/D7,4),0)) -> 0.4015 | AC7: =IFERROR(IF(VLOOKUP($B7,Shortage!$A:$M,AC$2,FALSE)="Shortage",1,IFERROR(ROUND(Q7/E7,4),0)),IFERROR(ROUND(Q7/E7,4),0)) -> 0 | AD7: =IFERROR(IF(VLOOKUP($B7,Shortage!$A:$M,AD$2,FALSE)="Shortage",1,IFERROR(ROUND(R7/F7,4),0)),IFERROR(ROUND(R7/F7,4),0)) -> 0 | AE7: =IFERROR(IF(VLOOKUP($B7,Shortage!$A:$M,AE$2,FALSE)="Shortage",1,IFERROR(ROUND(S7/G7,4),0)),IFERROR(ROUND(S7/G7,4),0)) -> 0 | AF7: =IFERROR(IF(VLOOKUP($B7,Shortage!$A:$M,AF$2,FALSE)="Shortage",1,IFERROR(ROUND(T7/H7,4),0)),IFERROR(ROUND(T7/H7,4),0)) -> 0 | AG7: =IFERROR(IF(VLOOKUP($B7,Shortage!$A:$M,AG$2,FALSE)="Shortage",1,IFERROR(ROUND(U7/I7,4),0)),IFERROR(ROUND(U7/I7,4),0)) -> 0 | AH7: =IFERROR(IF(VLOOKUP($B7,Shortage!$A:$M,AH$2,FALSE)="Shortage",1,IFERROR(ROUND(V7/J7,4),0)),IFERROR(ROUND(V7/J7,4),0)) -> 0 | AI7: =IFERROR(IF(VLOOKUP($B7,Shortage!$A:$M,AI$2,FALSE)="Shortage",1,IFERROR(ROUND(W7/K7,4),0)),IFERROR(ROUND(W7/K7,4),0)) -> 0 | ... AM7: =IFERROR(IF(VLOOKUP($B7,Shortage!$A:$M,AM$2,FALSE)="Shortage",1,IFERROR(ROUND(AA7/O7,4),0)),IFERROR(ROUND(AA7/O7,4),0)) -> 0 | AN7: =IFERROR(_xlfn.XLOOKUP(AB7,'2) หลักการคำนวน Table'!$C$3:$K$3,'2) หลักการคำนวน Table'!$C$3:$K$3,,1),INDEX('2) หลักการคำนวน Table'!$C$3:$K$3,1)) -> 0.9 | AO7: =IFERROR( _xlfn.XLOOKUP(AC7,'2) หลักการคำนวน Table'!$C$3:$K$3,'2) หลักการคำนวน Table'!$C$3:$K$3,,1), IF(AC7<MIN('2) หลักการคำนวน Table'!$C$3:$K$3), MIN('2) หลักการคำนวน Table'!$C$3:$K$3), MAX('2) หลักการคำนวน Table'!$C$3:$K$3) ) ) -> 0.9 | AP7: =IFERROR( _xlfn.XLOOKUP(AD7,'2) หลักการคำนวน Table'!$C$3:$K$3,'2) หลักการคำนวน Table'!$C$3:$K$3,,1), IF(AD7<MIN('2) หลักการคำนวน Table'!$C$3:$K$3), MIN('2) หลักการคำนวน Table'!$C$3:$K$3), MAX('2) หลักการคำนวน Table'!$C$3:$K$3) ) ) -> 0.9 | AQ7: =IFERROR( _xlfn.XLOOKUP(AE7,'2) หลักการคำนวน Table'!$C$3:$K$3,'2) หลักการคำนวน Table'!$C$3:$K$3,,1), IF(AE7<MIN('2) หลักการคำนวน Table'!$C$3:$K$3), MIN('2) หลักการคำนวน Table'!$C$3:$K$3), MAX('2) หลักการคำนวน Table'!$C$3:$K$3) ) ) -> 0.9 | AR7: =IFERROR( _xlfn.XLOOKUP(AF7,'2) หลักการคำนวน Table'!$C$3:$K$3,'2) หลักการคำนวน Table'!$C$3:$K$3,,1), IF(AF7<MIN('2) หลักการคำนวน Table'!$C$3:$K$3), MIN('2) หลักการคำนวน Table'!$C$3:$K$3), MAX('2) หลักการคำนวน Table'!$C$3:$K$3) ) ) -> 0.9 | AS7: =IFERROR( _xlfn.XLOOKUP(AG7,'2) หลักการคำนวน Table'!$C$3:$K$3,'2) หลักการคำนวน Table'!$C$3:$K$3,,1), IF(AG7<MIN('2) หลักการคำนวน Table'!$C$3:$K$3), MIN('2) หลักการคำนวน Table'!$C$3:$K$3), MAX('2) หลักการคำนวน Table'!$C$3:$K$3) ) ) -> 0.9 | AT7: =IFERROR( _xlfn.XLOOKUP(AH7,'2) หลักการคำนวน Table'!$C$3:$K$3,'2) หลักการคำนวน Table'!$C$3:$K$3,,1), IF(AH7<MIN('2) หลักการคำนวน Table'!$C$3:$K$3), MIN('2) หลักการคำนวน Table'!$C$3:$K$3), MAX('2) หลักการคำนวน Table'!$C$3:$K$3) ) ) -> 0.9 | AU7: =IFERROR( _xlfn.XLOOKUP(AI7,'2) หลักการคำนวน Table'!$C$3:$K$3,'2) หลักการคำนวน Table'!$C$3:$K$3,,1), IF(AI7<MIN('2) หลักการคำนวน Table'!$C$3:$K$3), MIN('2) หลักการคำนวน Table'!$C$3:$K$3), MAX('2) หลักการคำนวน Table'!$C$3:$K$3) ) ) -> 0.9 | AV7: =IFERROR( _xlfn.XLOOKUP(AJ7,'2) หลักการคำนวน Table'!$C$3:$K$3,'2) หลักการคำนวน Table'!$C$3:$K$3,,1), IF(AJ7<MIN('2) หลักการคำนวน Table'!$C$3:$K$3), MIN('2) หลักการคำนวน Table'!$C$3:$K$3), MAX('2) หลักการคำนวน Table'!$C$3:$K$3) ) ) -> 0.9 | ... AY7: =IFERROR( _xlfn.XLOOKUP(AM7,'2) หลักการคำนวน Table'!$C$3:$K$3,'2) หลักการคำนวน Table'!$C$3:$K$3,,1), IF(AM7<MIN('2) หลักการคำนวน Table'!$C$3:$K$3), MIN('2) หลักการคำนวน Table'!$C$3:$K$3), MAX('2) หลักการคำนวน Table'!$C$3:$K$3) ) ) -> 0.9 | AZ7: {=ROUND((_xlfn.XLOOKUP($C7,'2) หลักการคำนวน Table'!$A$4:$A$36, _xlfn.XLOOKUP(AN7,'2) หลักการคำนวน Table'!$C$3:$K$3,'2) หลักการคำนวน Table'!$C$4:$K$36,,-1)))*(_xlfn.XLOOKUP($C7,'2) หลักการคำนวน Table'!$A$4:$A$36, _xlfn.XLOOKUP($B7,'2) หลักการคำนวน Table'!$L$3:$Z$3,'2) หลักการคำนวน Table'!$L$4:$Z$36))),0)} -> 400 | BA7: {=ROUND((_xlfn.XLOOKUP($C7,'2) หลักการคำนวน Table'!$A$4:$A$36, _xlfn.XLOOKUP(AO7,'2) หลักการคำนวน Table'!$C$3:$K$3,'2) หลักการคำนวน Table'!$C$4:$K$36,,-1)))*(_xlfn.XLOOKUP($C7,'2) หลักการคำนวน Table'!$A$4:$A$36, _xlfn.XLOOKUP($B7,'2) หลักการคำนวน Table'!$L$3:$Z$3,'2) หลักการคำนวน Table'!$L$4:$Z$36))),0)} -> 400 | BB7: {=ROUND((_xlfn.XLOOKUP($C7,'2) หลักการคำนวน Table'!$A$4:$A$36, _xlfn.XLOOKUP(AP7,'2) หลักการคำนวน Table'!$C$3:$K$3,'2) หลักการคำนวน Table'!$C$4:$K$36,,-1)))*(_xlfn.XLOOKUP($C7,'2) หลักการคำนวน Table'!$A$4:$A$36, _xlfn.XLOOKUP($B7,'2) หลักการคำนวน Table'!$L$3:$Z$3,'2) หลักการคำนวน Table'!$L$4:$Z$36))),0)} -> 400 | BC7: {=ROUND((_xlfn.XLOOKUP($C7,'2) หลักการคำนวน Table'!$A$4:$A$36, _xlfn.XLOOKUP(AQ7,'2) หลักการคำนวน Table'!$C$3:$K$3,'2) หลักการคำนวน Table'!$C$4:$K$36,,-1)))*(_xlfn.XLOOKUP($C7,'2) หลักการคำนวน Table'!$A$4:$A$36, _xlfn.XLOOKUP($B7,'2) หลักการคำนวน Table'!$L$3:$Z$3,'2) หลักการคำนวน Table'!$L$4:$Z$36))),0)} -> 400 | BD7: {=ROUND((_xlfn.XLOOKUP($C7,'2) หลักการคำนวน Table'!$A$4:$A$36, _xlfn.XLOOKUP(AR7,'2) หลักการคำนวน Table'!$C$3:$K$3,'2) หลักการคำนวน Table'!$C$4:$K$36,,-1)))*(_xlfn.XLOOKUP($C7,'2) หลักการคำนวน Table'!$A$4:$A$36, _xlfn.XLOOKUP($B7,'2) หลักการคำนวน Table'!$L$3:$Z$3,'2) หลักการคำนวน Table'!$L$4:$Z$36))),0)} -> 400 | BE7: {=ROUND((_xlfn.XLOOKUP($C7,'2) หลักการคำนวน Table'!$A$4:$A$36, _xlfn.XLOOKUP(AS7,'2) หลักการคำนวน Table'!$C$3:$K$3,'2) หลักการคำนวน Table'!$C$4:$K$36,,-1)))*(_xlfn.XLOOKUP($C7,'2) หลักการคำนวน Table'!$A$4:$A$36, _xlfn.XLOOKUP($B7,'2) หลักการคำนวน Table'!$L$3:$Z$3,'2) หลักการคำนวน Table'!$L$4:$Z$36))),0)} -> 400 | BF7: {=ROUND((_xlfn.XLOOKUP($C7,'2) หลักการคำนวน Table'!$A$4:$A$36, _xlfn.XLOOKUP(AT7,'2) หลักการคำนวน Table'!$C$3:$K$3,'2) หลักการคำนวน Table'!$C$4:$K$36,,-1)))*(_xlfn.XLOOKUP($C7,'2) หลักการคำนวน Table'!$A$4:$A$36, _xlfn.XLOOKUP($B7,'2) หลักการคำนวน Table'!$L$3:$Z$3,'2) หลักการคำนวน Table'!$L$4:$Z$36))),0)} -> 400 | BG7: {=ROUND((_xlfn.XLOOKUP($C7,'2) หลักการคำนวน Table'!$A$4:$A$36, _xlfn.XLOOKUP(AU7,'2) หลักการคำนวน Table'!$C$3:$K$3,'2) หลักการคำนวน Table'!$C$4:$K$36,,-1)))*(_xlfn.XLOOKUP($C7,'2) หลักการคำนวน Table'!$A$4:$A$36, _xlfn.XLOOKUP($B7,'2) หลักการคำนวน Table'!$L$3:$Z$3,'2) หลักการคำนวน Table'!$L$4:$Z$36))),0)} -> 400 | ... BK7: {=ROUND((_xlfn.XLOOKUP($C7,'2) หลักการคำนวน Table'!$A$4:$A$36, _xlfn.XLOOKUP(AY7,'2) หลักการคำนวน Table'!$C$3:$K$3,'2) หลักการคำนวน Table'!$C$4:$K$36,,-1)))*(_xlfn.XLOOKUP($C7,'2) หลักการคำนวน Table'!$A$4:$A$36, _xlfn.XLOOKUP($B7,'2) หลักการคำนวน Table'!$L$3:$Z$3,'2) หลักการคำนวน Table'!$L$4:$Z$36))),0)} -> 400 | BM7: 222209 | BN7: 400
A8: =VLOOKUP(C8,ASTBase!E:S,13,FALSE) -> 222208 | B8: FP | C8: 5490000718 | D8: 455 | E8: 505 | F8: 355 | G8: 153 | H8: 303 | I8: 203 | J8: 205 | K8: 155 | L8: 255 | M8: 205 | N8: 203 | O8: 103 | P8: 367.2 | AB8: =IFERROR(IF(VLOOKUP($B8,Shortage!$A:$M,AB$2,FALSE)="Shortage",1,IFERROR(ROUND(P8/D8,4),0)),IFERROR(ROUND(P8/D8,4),0)) -> 0.807 | AC8: =IFERROR(IF(VLOOKUP($B8,Shortage!$A:$M,AC$2,FALSE)="Shortage",1,IFERROR(ROUND(Q8/E8,4),0)),IFERROR(ROUND(Q8/E8,4),0)) -> 0 | AD8: =IFERROR(IF(VLOOKUP($B8,Shortage!$A:$M,AD$2,FALSE)="Shortage",1,IFERROR(ROUND(R8/F8,4),0)),IFERROR(ROUND(R8/F8,4),0)) -> 0 | AE8: =IFERROR(IF(VLOOKUP($B8,Shortage!$A:$M,AE$2,FALSE)="Shortage",1,IFERROR(ROUND(S8/G8,4),0)),IFERROR(ROUND(S8/G8,4),0)) -> 0 | AF8: =IFERROR(IF(VLOOKUP($B8,Shortage!$A:$M,AF$2,FALSE)="Shortage",1,IFERROR(ROUND(T8/H8,4),0)),IFERROR(ROUND(T8/H8,4),0)) -> 0 | AG8: =IFERROR(IF(VLOOKUP($B8,Shortage!$A:$M,AG$2,FALSE)="Shortage",1,IFERROR(ROUND(U8/I8,4),0)),IFERROR(ROUND(U8/I8,4),0)) -> 0 | AH8: =IFERROR(IF(VLOOKUP($B8,Shortage!$A:$M,AH$2,FALSE)="Shortage",1,IFERROR(ROUND(V8/J8,4),0)),IFERROR(ROUND(V8/J8,4),0)) -> 0 | AI8: =IFERROR(IF(VLOOKUP($B8,Shortage!$A:$M,AI$2,FALSE)="Shortage",1,IFERROR(ROUND(W8/K8,4),0)),IFERROR(ROUND(W8/K8,4),0)) -> 0 | ... AM8: =IFERROR(IF(VLOOKUP($B8,Shortage!$A:$M,AM$2,FALSE)="Shortage",1,IFERROR(ROUND(AA8/O8,4),0)),IFERROR(ROUND(AA8/O8,4),0)) -> 0 | AN8: =IFERROR(_xlfn.XLOOKUP(AB8,'2) หลักการคำนวน Table'!$C$3:$K$3,'2) หลักการคำนวน Table'!$C$3:$K$3,,1),INDEX('2) หลักการคำนวน Table'!$C$3:$K$3,1)) -> 0.9 | AO8: =IFERROR( _xlfn.XLOOKUP(AC8,'2) หลักการคำนวน Table'!$C$3:$K$3,'2) หลักการคำนวน Table'!$C$3:$K$3,,1), IF(AC8<MIN('2) หลักการคำนวน Table'!$C$3:$K$3), MIN('2) หลักการคำนวน Table'!$C$3:$K$3), MAX('2) หลักการคำนวน Table'!$C$3:$K$3) ) ) -> 0.9 | AP8: =IFERROR( _xlfn.XLOOKUP(AD8,'2) หลักการคำนวน Table'!$C$3:$K$3,'2) หลักการคำนวน Table'!$C$3:$K$3,,1), IF(AD8<MIN('2) หลักการคำนวน Table'!$C$3:$K$3), MIN('2) หลักการคำนวน Table'!$C$3:$K$3), MAX('2) หลักการคำนวน Table'!$C$3:$K$3) ) ) -> 0.9 | AQ8: =IFERROR( _xlfn.XLOOKUP(AE8,'2) หลักการคำนวน Table'!$C$3:$K$3,'2) หลักการคำนวน Table'!$C$3:$K$3,,1), IF(AE8<MIN('2) หลักการคำนวน Table'!$C$3:$K$3), MIN('2) หลักการคำนวน Table'!$C$3:$K$3), MAX('2) หลักการคำนวน Table'!$C$3:$K$3) ) ) -> 0.9 | AR8: =IFERROR( _xlfn.XLOOKUP(AF8,'2) หลักการคำนวน Table'!$C$3:$K$3,'2) หลักการคำนวน Table'!$C$3:$K$3,,1), IF(AF8<MIN('2) หลักการคำนวน Table'!$C$3:$K$3), MIN('2) หลักการคำนวน Table'!$C$3:$K$3), MAX('2) หลักการคำนวน Table'!$C$3:$K$3) ) ) -> 0.9 | AS8: =IFERROR( _xlfn.XLOOKUP(AG8,'2) หลักการคำนวน Table'!$C$3:$K$3,'2) หลักการคำนวน Table'!$C$3:$K$3,,1), IF(AG8<MIN('2) หลักการคำนวน Table'!$C$3:$K$3), MIN('2) หลักการคำนวน Table'!$C$3:$K$3), MAX('2) หลักการคำนวน Table'!$C$3:$K$3) ) ) -> 0.9 | AT8: =IFERROR( _xlfn.XLOOKUP(AH8,'2) หลักการคำนวน Table'!$C$3:$K$3,'2) หลักการคำนวน Table'!$C$3:$K$3,,1), IF(AH8<MIN('2) หลักการคำนวน Table'!$C$3:$K$3), MIN('2) หลักการคำนวน Table'!$C$3:$K$3), MAX('2) หลักการคำนวน Table'!$C$3:$K$3) ) ) -> 0.9 | AU8: =IFERROR( _xlfn.XLOOKUP(AI8,'2) หลักการคำนวน Table'!$C$3:$K$3,'2) หลักการคำนวน Table'!$C$3:$K$3,,1), IF(AI8<MIN('2) หลักการคำนวน Table'!$C$3:$K$3), MIN('2) หลักการคำนวน Table'!$C$3:$K$3), MAX('2) หลักการคำนวน Table'!$C$3:$K$3) ) ) -> 0.9 | AV8: =IFERROR( _xlfn.XLOOKUP(AJ8,'2) หลักการคำนวน Table'!$C$3:$K$3,'2) หลักการคำนวน Table'!$C$3:$K$3,,1), IF(AJ8<MIN('2) หลักการคำนวน Table'!$C$3:$K$3), MIN('2) หลักการคำนวน Table'!$C$3:$K$3), MAX('2) หลักการคำนวน Table'!$C$3:$K$3) ) ) -> 0.9 | ... AY8: =IFERROR( _xlfn.XLOOKUP(AM8,'2) หลักการคำนวน Table'!$C$3:$K$3,'2) หลักการคำนวน Table'!$C$3:$K$3,,1), IF(AM8<MIN('2) หลักการคำนวน Table'!$C$3:$K$3), MIN('2) หลักการคำนวน Table'!$C$3:$K$3), MAX('2) หลักการคำนวน Table'!$C$3:$K$3) ) ) -> 0.9 | AZ8: {=ROUND((_xlfn.XLOOKUP($C8,'2) หลักการคำนวน Table'!$A$4:$A$36, _xlfn.XLOOKUP(AN8,'2) หลักการคำนวน Table'!$C$3:$K$3,'2) หลักการคำนวน Table'!$C$4:$K$36,,-1)))*(_xlfn.XLOOKUP($C8,'2) หลักการคำนวน Table'!$A$4:$A$36, _xlfn.XLOOKUP($B8,'2) หลักการคำนวน Table'!$L$3:$Z$3,'2) หลักการคำนวน Table'!$L$4:$Z$36))),0)} -> 400 | BA8: {=ROUND((_xlfn.XLOOKUP($C8,'2) หลักการคำนวน Table'!$A$4:$A$36, _xlfn.XLOOKUP(AO8,'2) หลักการคำนวน Table'!$C$3:$K$3,'2) หลักการคำนวน Table'!$C$4:$K$36,,-1)))*(_xlfn.XLOOKUP($C8,'2) หลักการคำนวน Table'!$A$4:$A$36, _xlfn.XLOOKUP($B8,'2) หลักการคำนวน Table'!$L$3:$Z$3,'2) หลักการคำนวน Table'!$L$4:$Z$36))),0)} -> 400 | BB8: {=ROUND((_xlfn.XLOOKUP($C8,'2) หลักการคำนวน Table'!$A$4:$A$36, _xlfn.XLOOKUP(AP8,'2) หลักการคำนวน Table'!$C$3:$K$3,'2) หลักการคำนวน Table'!$C$4:$K$36,,-1)))*(_xlfn.XLOOKUP($C8,'2) หลักการคำนวน Table'!$A$4:$A$36, _xlfn.XLOOKUP($B8,'2) หลักการคำนวน Table'!$L$3:$Z$3,'2) หลักการคำนวน Table'!$L$4:$Z$36))),0)} -> 400 | BC8: {=ROUND((_xlfn.XLOOKUP($C8,'2) หลักการคำนวน Table'!$A$4:$A$36, _xlfn.XLOOKUP(AQ8,'2) หลักการคำนวน Table'!$C$3:$K$3,'2) หลักการคำนวน Table'!$C$4:$K$36,,-1)))*(_xlfn.XLOOKUP($C8,'2) หลักการคำนวน Table'!$A$4:$A$36, _xlfn.XLOOKUP($B8,'2) หลักการคำนวน Table'!$L$3:$Z$3,'2) หลักการคำนวน Table'!$L$4:$Z$36))),0)} -> 400 | BD8: {=ROUND((_xlfn.XLOOKUP($C8,'2) หลักการคำนวน Table'!$A$4:$A$36, _xlfn.XLOOKUP(AR8,'2) หลักการคำนวน Table'!$C$3:$K$3,'2) หลักการคำนวน Table'!$C$4:$K$36,,-1)))*(_xlfn.XLOOKUP($C8,'2) หลักการคำนวน Table'!$A$4:$A$36, _xlfn.XLOOKUP($B8,'2) หลักการคำนวน Table'!$L$3:$Z$3,'2) หลักการคำนวน Table'!$L$4:$Z$36))),0)} -> 400 | BE8: {=ROUND((_xlfn.XLOOKUP($C8,'2) หลักการคำนวน Table'!$A$4:$A$36, _xlfn.XLOOKUP(AS8,'2) หลักการคำนวน Table'!$C$3:$K$3,'2) หลักการคำนวน Table'!$C$4:$K$36,,-1)))*(_xlfn.XLOOKUP($C8,'2) หลักการคำนวน Table'!$A$4:$A$36, _xlfn.XLOOKUP($B8,'2) หลักการคำนวน Table'!$L$3:$Z$3,'2) หลักการคำนวน Table'!$L$4:$Z$36))),0)} -> 400 | BF8: {=ROUND((_xlfn.XLOOKUP($C8,'2) หลักการคำนวน Table'!$A$4:$A$36, _xlfn.XLOOKUP(AT8,'2) หลักการคำนวน Table'!$C$3:$K$3,'2) หลักการคำนวน Table'!$C$4:$K$36,,-1)))*(_xlfn.XLOOKUP($C8,'2) หลักการคำนวน Table'!$A$4:$A$36, _xlfn.XLOOKUP($B8,'2) หลักการคำนวน Table'!$L$3:$Z$3,'2) หลักการคำนวน Table'!$L$4:$Z$36))),0)} -> 400 | BG8: {=ROUND((_xlfn.XLOOKUP($C8,'2) หลักการคำนวน Table'!$A$4:$A$36, _xlfn.XLOOKUP(AU8,'2) หลักการคำนวน Table'!$C$3:$K$3,'2) หลักการคำนวน Table'!$C$4:$K$36,,-1)))*(_xlfn.XLOOKUP($C8,'2) หลักการคำนวน Table'!$A$4:$A$36, _xlfn.XLOOKUP($B8,'2) หลักการคำนวน Table'!$L$3:$Z$3,'2) หลักการคำนวน Table'!$L$4:$Z$36))),0)} -> 400 | ... BK8: {=ROUND((_xlfn.XLOOKUP($C8,'2) หลักการคำนวน Table'!$A$4:$A$36, _xlfn.XLOOKUP(AY8,'2) หลักการคำนวน Table'!$C$3:$K$3,'2) หลักการคำนวน Table'!$C$4:$K$36,,-1)))*(_xlfn.XLOOKUP($C8,'2) หลักการคำนวน Table'!$A$4:$A$36, _xlfn.XLOOKUP($B8,'2) หลักการคำนวน Table'!$L$3:$Z$3,'2) หลักการคำนวน Table'!$L$4:$Z$36))),0)} -> 400 | BM8: 222209 | BN8: 400
A9: =VLOOKUP(C9,ASTBase!E:S,13,FALSE) -> 222208 | B9: PDC | C9: 5490000718 | D9: 298 | E9: 308 | F9: 234 | G9: 325 | H9: 250 | I9: 190 | J9: 230 | K9: 270 | L9: 220 | M9: 545 | N9: 250 | O9: 215 | P9: 210.591 | AB9: =IFERROR(IF(VLOOKUP($B9,Shortage!$A:$M,AB$2,FALSE)="Shortage",1,IFERROR(ROUND(P9/D9,4),0)),IFERROR(ROUND(P9/D9,4),0)) -> 0.7067 | AC9: =IFERROR(IF(VLOOKUP($B9,Shortage!$A:$M,AC$2,FALSE)="Shortage",1,IFERROR(ROUND(Q9/E9,4),0)),IFERROR(ROUND(Q9/E9,4),0)) -> 0 | AD9: =IFERROR(IF(VLOOKUP($B9,Shortage!$A:$M,AD$2,FALSE)="Shortage",1,IFERROR(ROUND(R9/F9,4),0)),IFERROR(ROUND(R9/F9,4),0)) -> 0 | AE9: =IFERROR(IF(VLOOKUP($B9,Shortage!$A:$M,AE$2,FALSE)="Shortage",1,IFERROR(ROUND(S9/G9,4),0)),IFERROR(ROUND(S9/G9,4),0)) -> 0 | AF9: =IFERROR(IF(VLOOKUP($B9,Shortage!$A:$M,AF$2,FALSE)="Shortage",1,IFERROR(ROUND(T9/H9,4),0)),IFERROR(ROUND(T9/H9,4),0)) -> 0 | AG9: =IFERROR(IF(VLOOKUP($B9,Shortage!$A:$M,AG$2,FALSE)="Shortage",1,IFERROR(ROUND(U9/I9,4),0)),IFERROR(ROUND(U9/I9,4),0)) -> 0 | AH9: =IFERROR(IF(VLOOKUP($B9,Shortage!$A:$M,AH$2,FALSE)="Shortage",1,IFERROR(ROUND(V9/J9,4),0)),IFERROR(ROUND(V9/J9,4),0)) -> 0 | AI9: =IFERROR(IF(VLOOKUP($B9,Shortage!$A:$M,AI$2,FALSE)="Shortage",1,IFERROR(ROUND(W9/K9,4),0)),IFERROR(ROUND(W9/K9,4),0)) -> 0 | ... AM9: =IFERROR(IF(VLOOKUP($B9,Shortage!$A:$M,AM$2,FALSE)="Shortage",1,IFERROR(ROUND(AA9/O9,4),0)),IFERROR(ROUND(AA9/O9,4),0)) -> 0 | AN9: =IFERROR(_xlfn.XLOOKUP(AB9,'2) หลักการคำนวน Table'!$C$3:$K$3,'2) หลักการคำนวน Table'!$C$3:$K$3,,1),INDEX('2) หลักการคำนวน Table'!$C$3:$K$3,1)) -> 0.9 | AO9: =IFERROR( _xlfn.XLOOKUP(AC9,'2) หลักการคำนวน Table'!$C$3:$K$3,'2) หลักการคำนวน Table'!$C$3:$K$3,,1), IF(AC9<MIN('2) หลักการคำนวน Table'!$C$3:$K$3), MIN('2) หลักการคำนวน Table'!$C$3:$K$3), MAX('2) หลักการคำนวน Table'!$C$3:$K$3) ) ) -> 0.9 | AP9: =IFERROR( _xlfn.XLOOKUP(AD9,'2) หลักการคำนวน Table'!$C$3:$K$3,'2) หลักการคำนวน Table'!$C$3:$K$3,,1), IF(AD9<MIN('2) หลักการคำนวน Table'!$C$3:$K$3), MIN('2) หลักการคำนวน Table'!$C$3:$K$3), MAX('2) หลักการคำนวน Table'!$C$3:$K$3) ) ) -> 0.9 | AQ9: =IFERROR( _xlfn.XLOOKUP(AE9,'2) หลักการคำนวน Table'!$C$3:$K$3,'2) หลักการคำนวน Table'!$C$3:$K$3,,1), IF(AE9<MIN('2) หลักการคำนวน Table'!$C$3:$K$3), MIN('2) หลักการคำนวน Table'!$C$3:$K$3), MAX('2) หลักการคำนวน Table'!$C$3:$K$3) ) ) -> 0.9 | AR9: =IFERROR( _xlfn.XLOOKUP(AF9,'2) หลักการคำนวน Table'!$C$3:$K$3,'2) หลักการคำนวน Table'!$C$3:$K$3,,1), IF(AF9<MIN('2) หลักการคำนวน Table'!$C$3:$K$3), MIN('2) หลักการคำนวน Table'!$C$3:$K$3), MAX('2) หลักการคำนวน Table'!$C$3:$K$3) ) ) -> 0.9 | AS9: =IFERROR( _xlfn.XLOOKUP(AG9,'2) หลักการคำนวน Table'!$C$3:$K$3,'2) หลักการคำนวน Table'!$C$3:$K$3,,1), IF(AG9<MIN('2) หลักการคำนวน Table'!$C$3:$K$3), MIN('2) หลักการคำนวน Table'!$C$3:$K$3), MAX('2) หลักการคำนวน Table'!$C$3:$K$3) ) ) -> 0.9 | AT9: =IFERROR( _xlfn.XLOOKUP(AH9,'2) หลักการคำนวน Table'!$C$3:$K$3,'2) หลักการคำนวน Table'!$C$3:$K$3,,1), IF(AH9<MIN('2) หลักการคำนวน Table'!$C$3:$K$3), MIN('2) หลักการคำนวน Table'!$C$3:$K$3), MAX('2) หลักการคำนวน Table'!$C$3:$K$3) ) ) -> 0.9 | AU9: =IFERROR( _xlfn.XLOOKUP(AI9,'2) หลักการคำนวน Table'!$C$3:$K$3,'2) หลักการคำนวน Table'!$C$3:$K$3,,1), IF(AI9<MIN('2) หลักการคำนวน Table'!$C$3:$K$3), MIN('2) หลักการคำนวน Table'!$C$3:$K$3), MAX('2) หลักการคำนวน Table'!$C$3:$K$3) ) ) -> 0.9 | AV9: =IFERROR( _xlfn.XLOOKUP(AJ9,'2) หลักการคำนวน Table'!$C$3:$K$3,'2) หลักการคำนวน Table'!$C$3:$K$3,,1), IF(AJ9<MIN('2) หลักการคำนวน Table'!$C$3:$K$3), MIN('2) หลักการคำนวน Table'!$C$3:$K$3), MAX('2) หลักการคำนวน Table'!$C$3:$K$3) ) ) -> 0.9 | ... AY9: =IFERROR( _xlfn.XLOOKUP(AM9,'2) หลักการคำนวน Table'!$C$3:$K$3,'2) หลักการคำนวน Table'!$C$3:$K$3,,1), IF(AM9<MIN('2) หลักการคำนวน Table'!$C$3:$K$3), MIN('2) หลักการคำนวน Table'!$C$3:$K$3), MAX('2) หลักการคำนวน Table'!$C$3:$K$3) ) ) -> 0.9 | AZ9: {=ROUND((_xlfn.XLOOKUP($C9,'2) หลักการคำนวน Table'!$A$4:$A$36, _xlfn.XLOOKUP(AN9,'2) หลักการคำนวน Table'!$C$3:$K$3,'2) หลักการคำนวน Table'!$C$4:$K$36,,-1)))*(_xlfn.XLOOKUP($C9,'2) หลักการคำนวน Table'!$A$4:$A$36, _xlfn.XLOOKUP($B9,'2) หลักการคำนวน Table'!$L$3:$Z$3,'2) หลักการคำนวน Table'!$L$4:$Z$36))),0)} -> 600 | BA9: {=ROUND((_xlfn.XLOOKUP($C9,'2) หลักการคำนวน Table'!$A$4:$A$36, _xlfn.XLOOKUP(AO9,'2) หลักการคำนวน Table'!$C$3:$K$3,'2) หลักการคำนวน Table'!$C$4:$K$36,,-1)))*(_xlfn.XLOOKUP($C9,'2) หลักการคำนวน Table'!$A$4:$A$36, _xlfn.XLOOKUP($B9,'2) หลักการคำนวน Table'!$L$3:$Z$3,'2) หลักการคำนวน Table'!$L$4:$Z$36))),0)} -> 600 | BB9: {=ROUND((_xlfn.XLOOKUP($C9,'2) หลักการคำนวน Table'!$A$4:$A$36, _xlfn.XLOOKUP(AP9,'2) หลักการคำนวน Table'!$C$3:$K$3,'2) หลักการคำนวน Table'!$C$4:$K$36,,-1)))*(_xlfn.XLOOKUP($C9,'2) หลักการคำนวน Table'!$A$4:$A$36, _xlfn.XLOOKUP($B9,'2) หลักการคำนวน Table'!$L$3:$Z$3,'2) หลักการคำนวน Table'!$L$4:$Z$36))),0)} -> 600 | BC9: {=ROUND((_xlfn.XLOOKUP($C9,'2) หลักการคำนวน Table'!$A$4:$A$36, _xlfn.XLOOKUP(AQ9,'2) หลักการคำนวน Table'!$C$3:$K$3,'2) หลักการคำนวน Table'!$C$4:$K$36,,-1)))*(_xlfn.XLOOKUP($C9,'2) หลักการคำนวน Table'!$A$4:$A$36, _xlfn.XLOOKUP($B9,'2) หลักการคำนวน Table'!$L$3:$Z$3,'2) หลักการคำนวน Table'!$L$4:$Z$36))),0)} -> 600 | BD9: {=ROUND((_xlfn.XLOOKUP($C9,'2) หลักการคำนวน Table'!$A$4:$A$36, _xlfn.XLOOKUP(AR9,'2) หลักการคำนวน Table'!$C$3:$K$3,'2) หลักการคำนวน Table'!$C$4:$K$36,,-1)))*(_xlfn.XLOOKUP($C9,'2) หลักการคำนวน Table'!$A$4:$A$36, _xlfn.XLOOKUP($B9,'2) หลักการคำนวน Table'!$L$3:$Z$3,'2) หลักการคำนวน Table'!$L$4:$Z$36))),0)} -> 600 | BE9: {=ROUND((_xlfn.XLOOKUP($C9,'2) หลักการคำนวน Table'!$A$4:$A$36, _xlfn.XLOOKUP(AS9,'2) หลักการคำนวน Table'!$C$3:$K$3,'2) หลักการคำนวน Table'!$C$4:$K$36,,-1)))*(_xlfn.XLOOKUP($C9,'2) หลักการคำนวน Table'!$A$4:$A$36, _xlfn.XLOOKUP($B9,'2) หลักการคำนวน Table'!$L$3:$Z$3,'2) หลักการคำนวน Table'!$L$4:$Z$36))),0)} -> 600 | BF9: {=ROUND((_xlfn.XLOOKUP($C9,'2) หลักการคำนวน Table'!$A$4:$A$36, _xlfn.XLOOKUP(AT9,'2) หลักการคำนวน Table'!$C$3:$K$3,'2) หลักการคำนวน Table'!$C$4:$K$36,,-1)))*(_xlfn.XLOOKUP($C9,'2) หลักการคำนวน Table'!$A$4:$A$36, _xlfn.XLOOKUP($B9,'2) หลักการคำนวน Table'!$L$3:$Z$3,'2) หลักการคำนวน Table'!$L$4:$Z$36))),0)} -> 600 | BG9: {=ROUND((_xlfn.XLOOKUP($C9,'2) หลักการคำนวน Table'!$A$4:$A$36, _xlfn.XLOOKUP(AU9,'2) หลักการคำนวน Table'!$C$3:$K$3,'2) หลักการคำนวน Table'!$C$4:$K$36,,-1)))*(_xlfn.XLOOKUP($C9,'2) หลักการคำนวน Table'!$A$4:$A$36, _xlfn.XLOOKUP($B9,'2) หลักการคำนวน Table'!$L$3:$Z$3,'2) หลักการคำนวน Table'!$L$4:$Z$36))),0)} -> 600 | ... BK9: {=ROUND((_xlfn.XLOOKUP($C9,'2) หลักการคำนวน Table'!$A$4:$A$36, _xlfn.XLOOKUP(AY9,'2) หลักการคำนวน Table'!$C$3:$K$3,'2) หลักการคำนวน Table'!$C$4:$K$36,,-1)))*(_xlfn.XLOOKUP($C9,'2) หลักการคำนวน Table'!$A$4:$A$36, _xlfn.XLOOKUP($B9,'2) หลักการคำนวน Table'!$L$3:$Z$3,'2) หลักการคำนวน Table'!$L$4:$Z$36))),0)} -> 600 | BM9: 222209 | BN9: 600
A10: =VLOOKUP(C10,ASTBase!E:S,13,FALSE) -> 222208 | B10: RD | C10: 5490000718 | D10: 1770 | E10: 1510 | F10: 1500 | G10: 1400 | H10: 1510 | I10: 1500 | J10: 1400 | K10: 1420 | L10: 1550 | M10: 1420 | N10: 1350 | O10: 1280 | P10: 1416.8 | AB10: =IFERROR(IF(VLOOKUP($B10,Shortage!$A:$M,AB$2,FALSE)="Shortage",1,IFERROR(ROUND(P10/D10,4),0)),IFERROR(ROUND(P10/D10,4),0)) -> 1 | AC10: =IFERROR(IF(VLOOKUP($B10,Shortage!$A:$M,AC$2,FALSE)="Shortage",1,IFERROR(ROUND(Q10/E10,4),0)),IFERROR(ROUND(Q10/E10,4),0)) -> 0 | AD10: =IFERROR(IF(VLOOKUP($B10,Shortage!$A:$M,AD$2,FALSE)="Shortage",1,IFERROR(ROUND(R10/F10,4),0)),IFERROR(ROUND(R10/F10,4),0)) -> 0 | AE10: =IFERROR(IF(VLOOKUP($B10,Shortage!$A:$M,AE$2,FALSE)="Shortage",1,IFERROR(ROUND(S10/G10,4),0)),IFERROR(ROUND(S10/G10,4),0)) -> 0 | AF10: =IFERROR(IF(VLOOKUP($B10,Shortage!$A:$M,AF$2,FALSE)="Shortage",1,IFERROR(ROUND(T10/H10,4),0)),IFERROR(ROUND(T10/H10,4),0)) -> 0 | AG10: =IFERROR(IF(VLOOKUP($B10,Shortage!$A:$M,AG$2,FALSE)="Shortage",1,IFERROR(ROUND(U10/I10,4),0)),IFERROR(ROUND(U10/I10,4),0)) -> 0 | AH10: =IFERROR(IF(VLOOKUP($B10,Shortage!$A:$M,AH$2,FALSE)="Shortage",1,IFERROR(ROUND(V10/J10,4),0)),IFERROR(ROUND(V10/J10,4),0)) -> 0 | AI10: =IFERROR(IF(VLOOKUP($B10,Shortage!$A:$M,AI$2,FALSE)="Shortage",1,IFERROR(ROUND(W10/K10,4),0)),IFERROR(ROUND(W10/K10,4),0)) -> 0 | ... AM10: =IFERROR(IF(VLOOKUP($B10,Shortage!$A:$M,AM$2,FALSE)="Shortage",1,IFERROR(ROUND(AA10/O10,4),0)),IFERROR(ROUND(AA10/O10,4),0)) -> 0 | AN10: =IFERROR(_xlfn.XLOOKUP(AB10,'2) หลักการคำนวน Table'!$C$3:$K$3,'2) หลักการคำนวน Table'!$C$3:$K$3,,1),INDEX('2) หลักการคำนวน Table'!$C$3:$K$3,1)) -> 1 | AO10: =IFERROR( _xlfn.XLOOKUP(AC10,'2) หลักการคำนวน Table'!$C$3:$K$3,'2) หลักการคำนวน Table'!$C$3:$K$3,,1), IF(AC10<MIN('2) หลักการคำนวน Table'!$C$3:$K$3), MIN('2) หลักการคำนวน Table'!$C$3:$K$3), MAX('2) หลักการคำนวน Table'!$C$3:$K$3) ) ) -> 0.9 | AP10: =IFERROR( _xlfn.XLOOKUP(AD10,'2) หลักการคำนวน Table'!$C$3:$K$3,'2) หลักการคำนวน Table'!$C$3:$K$3,,1), IF(AD10<MIN('2) หลักการคำนวน Table'!$C$3:$K$3), MIN('2) หลักการคำนวน Table'!$C$3:$K$3), MAX('2) หลักการคำนวน Table'!$C$3:$K$3) ) ) -> 0.9 | AQ10: =IFERROR( _xlfn.XLOOKUP(AE10,'2) หลักการคำนวน Table'!$C$3:$K$3,'2) หลักการคำนวน Table'!$C$3:$K$3,,1), IF(AE10<MIN('2) หลักการคำนวน Table'!$C$3:$K$3), MIN('2) หลักการคำนวน Table'!$C$3:$K$3), MAX('2) หลักการคำนวน Table'!$C$3:$K$3) ) ) -> 0.9 | AR10: =IFERROR( _xlfn.XLOOKUP(AF10,'2) หลักการคำนวน Table'!$C$3:$K$3,'2) หลักการคำนวน Table'!$C$3:$K$3,,1), IF(AF10<MIN('2) หลักการคำนวน Table'!$C$3:$K$3), MIN('2) หลักการคำนวน Table'!$C$3:$K$3), MAX('2) หลักการคำนวน Table'!$C$3:$K$3) ) ) -> 0.9 | AS10: =IFERROR( _xlfn.XLOOKUP(AG10,'2) หลักการคำนวน Table'!$C$3:$K$3,'2) หลักการคำนวน Table'!$C$3:$K$3,,1), IF(AG10<MIN('2) หลักการคำนวน Table'!$C$3:$K$3), MIN('2) หลักการคำนวน Table'!$C$3:$K$3), MAX('2) หลักการคำนวน Table'!$C$3:$K$3) ) ) -> 0.9 | AT10: =IFERROR( _xlfn.XLOOKUP(AH10,'2) หลักการคำนวน Table'!$C$3:$K$3,'2) หลักการคำนวน Table'!$C$3:$K$3,,1), IF(AH10<MIN('2) หลักการคำนวน Table'!$C$3:$K$3), MIN('2) หลักการคำนวน Table'!$C$3:$K$3), MAX('2) หลักการคำนวน Table'!$C$3:$K$3) ) ) -> 0.9 | AU10: =IFERROR( _xlfn.XLOOKUP(AI10,'2) หลักการคำนวน Table'!$C$3:$K$3,'2) หลักการคำนวน Table'!$C$3:$K$3,,1), IF(AI10<MIN('2) หลักการคำนวน Table'!$C$3:$K$3), MIN('2) หลักการคำนวน Table'!$C$3:$K$3), MAX('2) หลักการคำนวน Table'!$C$3:$K$3) ) ) -> 0.9 | AV10: =IFERROR( _xlfn.XLOOKUP(AJ10,'2) หลักการคำนวน Table'!$C$3:$K$3,'2) หลักการคำนวน Table'!$C$3:$K$3,,1), IF(AJ10<MIN('2) หลักการคำนวน Table'!$C$3:$K$3), MIN('2) หลักการคำนวน Table'!$C$3:$K$3), MAX('2) หลักการคำนวน Table'!$C$3:$K$3) ) ) -> 0.9 | ... AY10: =IFERROR( _xlfn.XLOOKUP(AM10,'2) หลักการคำนวน Table'!$C$3:$K$3,'2) หลักการคำนวน Table'!$C$3:$K$3,,1), IF(AM10<MIN('2) หลักการคำนวน Table'!$C$3:$K$3), MIN('2) หลักการคำนวน Table'!$C$3:$K$3), MAX('2) หลักการคำนวน Table'!$C$3:$K$3) ) ) -> 0.9 | AZ10: {=ROUND((_xlfn.XLOOKUP($C10,'2) หลักการคำนวน Table'!$A$4:$A$36, _xlfn.XLOOKUP(AN10,'2) หลักการคำนวน Table'!$C$3:$K$3,'2) หลักการคำนวน Table'!$C$4:$K$36,,-1)))*(_xlfn.XLOOKUP($C10,'2) หลักการคำนวน Table'!$A$4:$A$36, _xlfn.XLOOKUP($B10,'2) หลักการคำนวน Table'!$L$3:$Z$3,'2) หลักการคำนวน Table'!$L$4:$Z$36))),0)} -> 222 | BA10: {=ROUND((_xlfn.XLOOKUP($C10,'2) หลักการคำนวน Table'!$A$4:$A$36, _xlfn.XLOOKUP(AO10,'2) หลักการคำนวน Table'!$C$3:$K$3,'2) หลักการคำนวน Table'!$C$4:$K$36,,-1)))*(_xlfn.XLOOKUP($C10,'2) หลักการคำนวน Table'!$A$4:$A$36, _xlfn.XLOOKUP($B10,'2) หลักการคำนวน Table'!$L$3:$Z$3,'2) หลักการคำนวน Table'!$L$4:$Z$36))),0)} -> 200 | BB10: {=ROUND((_xlfn.XLOOKUP($C10,'2) หลักการคำนวน Table'!$A$4:$A$36, _xlfn.XLOOKUP(AP10,'2) หลักการคำนวน Table'!$C$3:$K$3,'2) หลักการคำนวน Table'!$C$4:$K$36,,-1)))*(_xlfn.XLOOKUP($C10,'2) หลักการคำนวน Table'!$A$4:$A$36, _xlfn.XLOOKUP($B10,'2) หลักการคำนวน Table'!$L$3:$Z$3,'2) หลักการคำนวน Table'!$L$4:$Z$36))),0)} -> 200 | BC10: {=ROUND((_xlfn.XLOOKUP($C10,'2) หลักการคำนวน Table'!$A$4:$A$36, _xlfn.XLOOKUP(AQ10,'2) หลักการคำนวน Table'!$C$3:$K$3,'2) หลักการคำนวน Table'!$C$4:$K$36,,-1)))*(_xlfn.XLOOKUP($C10,'2) หลักการคำนวน Table'!$A$4:$A$36, _xlfn.XLOOKUP($B10,'2) หลักการคำนวน Table'!$L$3:$Z$3,'2) หลักการคำนวน Table'!$L$4:$Z$36))),0)} -> 200 | BD10: {=ROUND((_xlfn.XLOOKUP($C10,'2) หลักการคำนวน Table'!$A$4:$A$36, _xlfn.XLOOKUP(AR10,'2) หลักการคำนวน Table'!$C$3:$K$3,'2) หลักการคำนวน Table'!$C$4:$K$36,,-1)))*(_xlfn.XLOOKUP($C10,'2) หลักการคำนวน Table'!$A$4:$A$36, _xlfn.XLOOKUP($B10,'2) หลักการคำนวน Table'!$L$3:$Z$3,'2) หลักการคำนวน Table'!$L$4:$Z$36))),0)} -> 200 | BE10: {=ROUND((_xlfn.XLOOKUP($C10,'2) หลักการคำนวน Table'!$A$4:$A$36, _xlfn.XLOOKUP(AS10,'2) หลักการคำนวน Table'!$C$3:$K$3,'2) หลักการคำนวน Table'!$C$4:$K$36,,-1)))*(_xlfn.XLOOKUP($C10,'2) หลักการคำนวน Table'!$A$4:$A$36, _xlfn.XLOOKUP($B10,'2) หลักการคำนวน Table'!$L$3:$Z$3,'2) หลักการคำนวน Table'!$L$4:$Z$36))),0)} -> 200 | BF10: {=ROUND((_xlfn.XLOOKUP($C10,'2) หลักการคำนวน Table'!$A$4:$A$36, _xlfn.XLOOKUP(AT10,'2) หลักการคำนวน Table'!$C$3:$K$3,'2) หลักการคำนวน Table'!$C$4:$K$36,,-1)))*(_xlfn.XLOOKUP($C10,'2) หลักการคำนวน Table'!$A$4:$A$36, _xlfn.XLOOKUP($B10,'2) หลักการคำนวน Table'!$L$3:$Z$3,'2) หลักการคำนวน Table'!$L$4:$Z$36))),0)} -> 200 | BG10: {=ROUND((_xlfn.XLOOKUP($C10,'2) หลักการคำนวน Table'!$A$4:$A$36, _xlfn.XLOOKUP(AU10,'2) หลักการคำนวน Table'!$C$3:$K$3,'2) หลักการคำนวน Table'!$C$4:$K$36,,-1)))*(_xlfn.XLOOKUP($C10,'2) หลักการคำนวน Table'!$A$4:$A$36, _xlfn.XLOOKUP($B10,'2) หลักการคำนวน Table'!$L$3:$Z$3,'2) หลักการคำนวน Table'!$L$4:$Z$36))),0)} -> 200 | ... BK10: {=ROUND((_xlfn.XLOOKUP($C10,'2) หลักการคำนวน Table'!$A$4:$A$36, _xlfn.XLOOKUP(AY10,'2) หลักการคำนวน Table'!$C$3:$K$3,'2) หลักการคำนวน Table'!$C$4:$K$36,,-1)))*(_xlfn.XLOOKUP($C10,'2) หลักการคำนวน Table'!$A$4:$A$36, _xlfn.XLOOKUP($B10,'2) หลักการคำนวน Table'!$L$3:$Z$3,'2) หลักการคำนวน Table'!$L$4:$Z$36))),0)} -> 200 | BM10: 222209 | BN10: 222
A11: =VLOOKUP(C11,ASTBase!E:S,13,FALSE) -> 222208 | B11: RDC | C11: 5490000718 | D11: 300 | E11: 245 | F11: 250 | G11: 284 | H11: 285 | I11: 260 | J11: 330 | K11: 215 | L11: 230 | M11: 380 | N11: 290 | O11: 215 | P11: 455.04 | AB11: =IFERROR(IF(VLOOKUP($B11,Shortage!$A:$M,AB$2,FALSE)="Shortage",1,IFERROR(ROUND(P11/D11,4),0)),IFERROR(ROUND(P11/D11,4),0)) -> 1.5168 | AC11: =IFERROR(IF(VLOOKUP($B11,Shortage!$A:$M,AC$2,FALSE)="Shortage",1,IFERROR(ROUND(Q11/E11,4),0)),IFERROR(ROUND(Q11/E11,4),0)) -> 0 | AD11: =IFERROR(IF(VLOOKUP($B11,Shortage!$A:$M,AD$2,FALSE)="Shortage",1,IFERROR(ROUND(R11/F11,4),0)),IFERROR(ROUND(R11/F11,4),0)) -> 0 | AE11: =IFERROR(IF(VLOOKUP($B11,Shortage!$A:$M,AE$2,FALSE)="Shortage",1,IFERROR(ROUND(S11/G11,4),0)),IFERROR(ROUND(S11/G11,4),0)) -> 0 | AF11: =IFERROR(IF(VLOOKUP($B11,Shortage!$A:$M,AF$2,FALSE)="Shortage",1,IFERROR(ROUND(T11/H11,4),0)),IFERROR(ROUND(T11/H11,4),0)) -> 0 | AG11: =IFERROR(IF(VLOOKUP($B11,Shortage!$A:$M,AG$2,FALSE)="Shortage",1,IFERROR(ROUND(U11/I11,4),0)),IFERROR(ROUND(U11/I11,4),0)) -> 0 | AH11: =IFERROR(IF(VLOOKUP($B11,Shortage!$A:$M,AH$2,FALSE)="Shortage",1,IFERROR(ROUND(V11/J11,4),0)),IFERROR(ROUND(V11/J11,4),0)) -> 0 | AI11: =IFERROR(IF(VLOOKUP($B11,Shortage!$A:$M,AI$2,FALSE)="Shortage",1,IFERROR(ROUND(W11/K11,4),0)),IFERROR(ROUND(W11/K11,4),0)) -> 0 | ... AM11: =IFERROR(IF(VLOOKUP($B11,Shortage!$A:$M,AM$2,FALSE)="Shortage",1,IFERROR(ROUND(AA11/O11,4),0)),IFERROR(ROUND(AA11/O11,4),0)) -> 0 | AN11: =IFERROR(_xlfn.XLOOKUP(AB11,'2) หลักการคำนวน Table'!$C$3:$K$3,'2) หลักการคำนวน Table'!$C$3:$K$3,,1),INDEX('2) หลักการคำนวน Table'!$C$3:$K$3,1)) -> 20 | AO11: =IFERROR( _xlfn.XLOOKUP(AC11,'2) หลักการคำนวน Table'!$C$3:$K$3,'2) หลักการคำนวน Table'!$C$3:$K$3,,1), IF(AC11<MIN('2) หลักการคำนวน Table'!$C$3:$K$3), MIN('2) หลักการคำนวน Table'!$C$3:$K$3), MAX('2) หลักการคำนวน Table'!$C$3:$K$3) ) ) -> 0.9 | AP11: =IFERROR( _xlfn.XLOOKUP(AD11,'2) หลักการคำนวน Table'!$C$3:$K$3,'2) หลักการคำนวน Table'!$C$3:$K$3,,1), IF(AD11<MIN('2) หลักการคำนวน Table'!$C$3:$K$3), MIN('2) หลักการคำนวน Table'!$C$3:$K$3), MAX('2) หลักการคำนวน Table'!$C$3:$K$3) ) ) -> 0.9 | AQ11: =IFERROR( _xlfn.XLOOKUP(AE11,'2) หลักการคำนวน Table'!$C$3:$K$3,'2) หลักการคำนวน Table'!$C$3:$K$3,,1), IF(AE11<MIN('2) หลักการคำนวน Table'!$C$3:$K$3), MIN('2) หลักการคำนวน Table'!$C$3:$K$3), MAX('2) หลักการคำนวน Table'!$C$3:$K$3) ) ) -> 0.9 | AR11: =IFERROR( _xlfn.XLOOKUP(AF11,'2) หลักการคำนวน Table'!$C$3:$K$3,'2) หลักการคำนวน Table'!$C$3:$K$3,,1), IF(AF11<MIN('2) หลักการคำนวน Table'!$C$3:$K$3), MIN('2) หลักการคำนวน Table'!$C$3:$K$3), MAX('2) หลักการคำนวน Table'!$C$3:$K$3) ) ) -> 0.9 | AS11: =IFERROR( _xlfn.XLOOKUP(AG11,'2) หลักการคำนวน Table'!$C$3:$K$3,'2) หลักการคำนวน Table'!$C$3:$K$3,,1), IF(AG11<MIN('2) หลักการคำนวน Table'!$C$3:$K$3), MIN('2) หลักการคำนวน Table'!$C$3:$K$3), MAX('2) หลักการคำนวน Table'!$C$3:$K$3) ) ) -> 0.9 | AT11: =IFERROR( _xlfn.XLOOKUP(AH11,'2) หลักการคำนวน Table'!$C$3:$K$3,'2) หลักการคำนวน Table'!$C$3:$K$3,,1), IF(AH11<MIN('2) หลักการคำนวน Table'!$C$3:$K$3), MIN('2) หลักการคำนวน Table'!$C$3:$K$3), MAX('2) หลักการคำนวน Table'!$C$3:$K$3) ) ) -> 0.9 | AU11: =IFERROR( _xlfn.XLOOKUP(AI11,'2) หลักการคำนวน Table'!$C$3:$K$3,'2) หลักการคำนวน Table'!$C$3:$K$3,,1), IF(AI11<MIN('2) หลักการคำนวน Table'!$C$3:$K$3), MIN('2) หลักการคำนวน Table'!$C$3:$K$3), MAX('2) หลักการคำนวน Table'!$C$3:$K$3) ) ) -> 0.9 | AV11: =IFERROR( _xlfn.XLOOKUP(AJ11,'2) หลักการคำนวน Table'!$C$3:$K$3,'2) หลักการคำนวน Table'!$C$3:$K$3,,1), IF(AJ11<MIN('2) หลักการคำนวน Table'!$C$3:$K$3), MIN('2) หลักการคำนวน Table'!$C$3:$K$3), MAX('2) หลักการคำนวน Table'!$C$3:$K$3) ) ) -> 0.9 | ... AY11: =IFERROR( _xlfn.XLOOKUP(AM11,'2) หลักการคำนวน Table'!$C$3:$K$3,'2) หลักการคำนวน Table'!$C$3:$K$3,,1), IF(AM11<MIN('2) หลักการคำนวน Table'!$C$3:$K$3), MIN('2) หลักการคำนวน Table'!$C$3:$K$3), MAX('2) หลักการคำนวน Table'!$C$3:$K$3) ) ) -> 0.9 | AZ11: {=ROUND((_xlfn.XLOOKUP($C11,'2) หลักการคำนวน Table'!$A$4:$A$36, _xlfn.XLOOKUP(AN11,'2) หลักการคำนวน Table'!$C$3:$K$3,'2) หลักการคำนวน Table'!$C$4:$K$36,,-1)))*(_xlfn.XLOOKUP($C11,'2) หลักการคำนวน Table'!$A$4:$A$36, _xlfn.XLOOKUP($B11,'2) หลักการคำนวน Table'!$L$3:$Z$3,'2) หลักการคำนวน Table'!$L$4:$Z$36))),0)} -> 578 | BA11: {=ROUND((_xlfn.XLOOKUP($C11,'2) หลักการคำนวน Table'!$A$4:$A$36, _xlfn.XLOOKUP(AO11,'2) หลักการคำนวน Table'!$C$3:$K$3,'2) หลักการคำนวน Table'!$C$4:$K$36,,-1)))*(_xlfn.XLOOKUP($C11,'2) หลักการคำนวน Table'!$A$4:$A$36, _xlfn.XLOOKUP($B11,'2) หลักการคำนวน Table'!$L$3:$Z$3,'2) หลักการคำนวน Table'!$L$4:$Z$36))),0)} -> 400 | BB11: {=ROUND((_xlfn.XLOOKUP($C11,'2) หลักการคำนวน Table'!$A$4:$A$36, _xlfn.XLOOKUP(AP11,'2) หลักการคำนวน Table'!$C$3:$K$3,'2) หลักการคำนวน Table'!$C$4:$K$36,,-1)))*(_xlfn.XLOOKUP($C11,'2) หลักการคำนวน Table'!$A$4:$A$36, _xlfn.XLOOKUP($B11,'2) หลักการคำนวน Table'!$L$3:$Z$3,'2) หลักการคำนวน Table'!$L$4:$Z$36))),0)} -> 400 | BC11: {=ROUND((_xlfn.XLOOKUP($C11,'2) หลักการคำนวน Table'!$A$4:$A$36, _xlfn.XLOOKUP(AQ11,'2) หลักการคำนวน Table'!$C$3:$K$3,'2) หลักการคำนวน Table'!$C$4:$K$36,,-1)))*(_xlfn.XLOOKUP($C11,'2) หลักการคำนวน Table'!$A$4:$A$36, _xlfn.XLOOKUP($B11,'2) หลักการคำนวน Table'!$L$3:$Z$3,'2) หลักการคำนวน Table'!$L$4:$Z$36))),0)} -> 400 | BD11: {=ROUND((_xlfn.XLOOKUP($C11,'2) หลักการคำนวน Table'!$A$4:$A$36, _xlfn.XLOOKUP(AR11,'2) หลักการคำนวน Table'!$C$3:$K$3,'2) หลักการคำนวน Table'!$C$4:$K$36,,-1)))*(_xlfn.XLOOKUP($C11,'2) หลักการคำนวน Table'!$A$4:$A$36, _xlfn.XLOOKUP($B11,'2) หลักการคำนวน Table'!$L$3:$Z$3,'2) หลักการคำนวน Table'!$L$4:$Z$36))),0)} -> 400 | BE11: {=ROUND((_xlfn.XLOOKUP($C11,'2) หลักการคำนวน Table'!$A$4:$A$36, _xlfn.XLOOKUP(AS11,'2) หลักการคำนวน Table'!$C$3:$K$3,'2) หลักการคำนวน Table'!$C$4:$K$36,,-1)))*(_xlfn.XLOOKUP($C11,'2) หลักการคำนวน Table'!$A$4:$A$36, _xlfn.XLOOKUP($B11,'2) หลักการคำนวน Table'!$L$3:$Z$3,'2) หลักการคำนวน Table'!$L$4:$Z$36))),0)} -> 400 | BF11: {=ROUND((_xlfn.XLOOKUP($C11,'2) หลักการคำนวน Table'!$A$4:$A$36, _xlfn.XLOOKUP(AT11,'2) หลักการคำนวน Table'!$C$3:$K$3,'2) หลักการคำนวน Table'!$C$4:$K$36,,-1)))*(_xlfn.XLOOKUP($C11,'2) หลักการคำนวน Table'!$A$4:$A$36, _xlfn.XLOOKUP($B11,'2) หลักการคำนวน Table'!$L$3:$Z$3,'2) หลักการคำนวน Table'!$L$4:$Z$36))),0)} -> 400 | BG11: {=ROUND((_xlfn.XLOOKUP($C11,'2) หลักการคำนวน Table'!$A$4:$A$36, _xlfn.XLOOKUP(AU11,'2) หลักการคำนวน Table'!$C$3:$K$3,'2) หลักการคำนวน Table'!$C$4:$K$36,,-1)))*(_xlfn.XLOOKUP($C11,'2) หลักการคำนวน Table'!$A$4:$A$36, _xlfn.XLOOKUP($B11,'2) หลักการคำนวน Table'!$L$3:$Z$3,'2) หลักการคำนวน Table'!$L$4:$Z$36))),0)} -> 400 | ... BK11: {=ROUND((_xlfn.XLOOKUP($C11,'2) หลักการคำนวน Table'!$A$4:$A$36, _xlfn.XLOOKUP(AY11,'2) หลักการคำนวน Table'!$C$3:$K$3,'2) หลักการคำนวน Table'!$C$4:$K$36,,-1)))*(_xlfn.XLOOKUP($C11,'2) หลักการคำนวน Table'!$A$4:$A$36, _xlfn.XLOOKUP($B11,'2) หลักการคำนวน Table'!$L$3:$Z$3,'2) หลักการคำนวน Table'!$L$4:$Z$36))),0)} -> 400 | BM11: 222209 | BN11: 578
A12: =VLOOKUP(C12,ASTBase!E:S,13,FALSE) -> 222208 | B12: RM | C12: 5490000718 | D12: 303 | E12: 165 | F12: 249 | G12: 229 | H12: 160 | I12: 250 | J12: 230 | K12: 180 | L12: 270 | M12: 205 | N12: 190 | O12: 230 | P12: 221 | AB12: =IFERROR(IF(VLOOKUP($B12,Shortage!$A:$M,AB$2,FALSE)="Shortage",1,IFERROR(ROUND(P12/D12,4),0)),IFERROR(ROUND(P12/D12,4),0)) -> 0.7294 | AC12: =IFERROR(IF(VLOOKUP($B12,Shortage!$A:$M,AC$2,FALSE)="Shortage",1,IFERROR(ROUND(Q12/E12,4),0)),IFERROR(ROUND(Q12/E12,4),0)) -> 0 | AD12: =IFERROR(IF(VLOOKUP($B12,Shortage!$A:$M,AD$2,FALSE)="Shortage",1,IFERROR(ROUND(R12/F12,4),0)),IFERROR(ROUND(R12/F12,4),0)) -> 0 | AE12: =IFERROR(IF(VLOOKUP($B12,Shortage!$A:$M,AE$2,FALSE)="Shortage",1,IFERROR(ROUND(S12/G12,4),0)),IFERROR(ROUND(S12/G12,4),0)) -> 0 | AF12: =IFERROR(IF(VLOOKUP($B12,Shortage!$A:$M,AF$2,FALSE)="Shortage",1,IFERROR(ROUND(T12/H12,4),0)),IFERROR(ROUND(T12/H12,4),0)) -> 0 | AG12: =IFERROR(IF(VLOOKUP($B12,Shortage!$A:$M,AG$2,FALSE)="Shortage",1,IFERROR(ROUND(U12/I12,4),0)),IFERROR(ROUND(U12/I12,4),0)) -> 0 | AH12: =IFERROR(IF(VLOOKUP($B12,Shortage!$A:$M,AH$2,FALSE)="Shortage",1,IFERROR(ROUND(V12/J12,4),0)),IFERROR(ROUND(V12/J12,4),0)) -> 0 | AI12: =IFERROR(IF(VLOOKUP($B12,Shortage!$A:$M,AI$2,FALSE)="Shortage",1,IFERROR(ROUND(W12/K12,4),0)),IFERROR(ROUND(W12/K12,4),0)) -> 0 | ... AM12: =IFERROR(IF(VLOOKUP($B12,Shortage!$A:$M,AM$2,FALSE)="Shortage",1,IFERROR(ROUND(AA12/O12,4),0)),IFERROR(ROUND(AA12/O12,4),0)) -> 0 | AN12: =IFERROR(_xlfn.XLOOKUP(AB12,'2) หลักการคำนวน Table'!$C$3:$K$3,'2) หลักการคำนวน Table'!$C$3:$K$3,,1),INDEX('2) หลักการคำนวน Table'!$C$3:$K$3,1)) -> 0.9 | AO12: =IFERROR( _xlfn.XLOOKUP(AC12,'2) หลักการคำนวน Table'!$C$3:$K$3,'2) หลักการคำนวน Table'!$C$3:$K$3,,1), IF(AC12<MIN('2) หลักการคำนวน Table'!$C$3:$K$3), MIN('2) หลักการคำนวน Table'!$C$3:$K$3), MAX('2) หลักการคำนวน Table'!$C$3:$K$3) ) ) -> 0.9 | AP12: =IFERROR( _xlfn.XLOOKUP(AD12,'2) หลักการคำนวน Table'!$C$3:$K$3,'2) หลักการคำนวน Table'!$C$3:$K$3,,1), IF(AD12<MIN('2) หลักการคำนวน Table'!$C$3:$K$3), MIN('2) หลักการคำนวน Table'!$C$3:$K$3), MAX('2) หลักการคำนวน Table'!$C$3:$K$3) ) ) -> 0.9 | AQ12: =IFERROR( _xlfn.XLOOKUP(AE12,'2) หลักการคำนวน Table'!$C$3:$K$3,'2) หลักการคำนวน Table'!$C$3:$K$3,,1), IF(AE12<MIN('2) หลักการคำนวน Table'!$C$3:$K$3), MIN('2) หลักการคำนวน Table'!$C$3:$K$3), MAX('2) หลักการคำนวน Table'!$C$3:$K$3) ) ) -> 0.9 | AR12: =IFERROR( _xlfn.XLOOKUP(AF12,'2) หลักการคำนวน Table'!$C$3:$K$3,'2) หลักการคำนวน Table'!$C$3:$K$3,,1), IF(AF12<MIN('2) หลักการคำนวน Table'!$C$3:$K$3), MIN('2) หลักการคำนวน Table'!$C$3:$K$3), MAX('2) หลักการคำนวน Table'!$C$3:$K$3) ) ) -> 0.9 | AS12: =IFERROR( _xlfn.XLOOKUP(AG12,'2) หลักการคำนวน Table'!$C$3:$K$3,'2) หลักการคำนวน Table'!$C$3:$K$3,,1), IF(AG12<MIN('2) หลักการคำนวน Table'!$C$3:$K$3), MIN('2) หลักการคำนวน Table'!$C$3:$K$3), MAX('2) หลักการคำนวน Table'!$C$3:$K$3) ) ) -> 0.9 | AT12: =IFERROR( _xlfn.XLOOKUP(AH12,'2) หลักการคำนวน Table'!$C$3:$K$3,'2) หลักการคำนวน Table'!$C$3:$K$3,,1), IF(AH12<MIN('2) หลักการคำนวน Table'!$C$3:$K$3), MIN('2) หลักการคำนวน Table'!$C$3:$K$3), MAX('2) หลักการคำนวน Table'!$C$3:$K$3) ) ) -> 0.9 | AU12: =IFERROR( _xlfn.XLOOKUP(AI12,'2) หลักการคำนวน Table'!$C$3:$K$3,'2) หลักการคำนวน Table'!$C$3:$K$3,,1), IF(AI12<MIN('2) หลักการคำนวน Table'!$C$3:$K$3), MIN('2) หลักการคำนวน Table'!$C$3:$K$3), MAX('2) หลักการคำนวน Table'!$C$3:$K$3) ) ) -> 0.9 | AV12: =IFERROR( _xlfn.XLOOKUP(AJ12,'2) หลักการคำนวน Table'!$C$3:$K$3,'2) หลักการคำนวน Table'!$C$3:$K$3,,1), IF(AJ12<MIN('2) หลักการคำนวน Table'!$C$3:$K$3), MIN('2) หลักการคำนวน Table'!$C$3:$K$3), MAX('2) หลักการคำนวน Table'!$C$3:$K$3) ) ) -> 0.9 | ... AY12: =IFERROR( _xlfn.XLOOKUP(AM12,'2) หลักการคำนวน Table'!$C$3:$K$3,'2) หลักการคำนวน Table'!$C$3:$K$3,,1), IF(AM12<MIN('2) หลักการคำนวน Table'!$C$3:$K$3), MIN('2) หลักการคำนวน Table'!$C$3:$K$3), MAX('2) หลักการคำนวน Table'!$C$3:$K$3) ) ) -> 0.9 | AZ12: {=ROUND((_xlfn.XLOOKUP($C12,'2) หลักการคำนวน Table'!$A$4:$A$36, _xlfn.XLOOKUP(AN12,'2) หลักการคำนวน Table'!$C$3:$K$3,'2) หลักการคำนวน Table'!$C$4:$K$36,,-1)))*(_xlfn.XLOOKUP($C12,'2) หลักการคำนวน Table'!$A$4:$A$36, _xlfn.XLOOKUP($B12,'2) หลักการคำนวน Table'!$L$3:$Z$3,'2) หลักการคำนวน Table'!$L$4:$Z$36))),0)} -> 400 | BA12: {=ROUND((_xlfn.XLOOKUP($C12,'2) หลักการคำนวน Table'!$A$4:$A$36, _xlfn.XLOOKUP(AO12,'2) หลักการคำนวน Table'!$C$3:$K$3,'2) หลักการคำนวน Table'!$C$4:$K$36,,-1)))*(_xlfn.XLOOKUP($C12,'2) หลักการคำนวน Table'!$A$4:$A$36, _xlfn.XLOOKUP($B12,'2) หลักการคำนวน Table'!$L$3:$Z$3,'2) หลักการคำนวน Table'!$L$4:$Z$36))),0)} -> 400 | BB12: {=ROUND((_xlfn.XLOOKUP($C12,'2) หลักการคำนวน Table'!$A$4:$A$36, _xlfn.XLOOKUP(AP12,'2) หลักการคำนวน Table'!$C$3:$K$3,'2) หลักการคำนวน Table'!$C$4:$K$36,,-1)))*(_xlfn.XLOOKUP($C12,'2) หลักการคำนวน Table'!$A$4:$A$36, _xlfn.XLOOKUP($B12,'2) หลักการคำนวน Table'!$L$3:$Z$3,'2) หลักการคำนวน Table'!$L$4:$Z$36))),0)} -> 400 | BC12: {=ROUND((_xlfn.XLOOKUP($C12,'2) หลักการคำนวน Table'!$A$4:$A$36, _xlfn.XLOOKUP(AQ12,'2) หลักการคำนวน Table'!$C$3:$K$3,'2) หลักการคำนวน Table'!$C$4:$K$36,,-1)))*(_xlfn.XLOOKUP($C12,'2) หลักการคำนวน Table'!$A$4:$A$36, _xlfn.XLOOKUP($B12,'2) หลักการคำนวน Table'!$L$3:$Z$3,'2) หลักการคำนวน Table'!$L$4:$Z$36))),0)} -> 400 | BD12: {=ROUND((_xlfn.XLOOKUP($C12,'2) หลักการคำนวน Table'!$A$4:$A$36, _xlfn.XLOOKUP(AR12,'2) หลักการคำนวน Table'!$C$3:$K$3,'2) หลักการคำนวน Table'!$C$4:$K$36,,-1)))*(_xlfn.XLOOKUP($C12,'2) หลักการคำนวน Table'!$A$4:$A$36, _xlfn.XLOOKUP($B12,'2) หลักการคำนวน Table'!$L$3:$Z$3,'2) หลักการคำนวน Table'!$L$4:$Z$36))),0)} -> 400 | BE12: {=ROUND((_xlfn.XLOOKUP($C12,'2) หลักการคำนวน Table'!$A$4:$A$36, _xlfn.XLOOKUP(AS12,'2) หลักการคำนวน Table'!$C$3:$K$3,'2) หลักการคำนวน Table'!$C$4:$K$36,,-1)))*(_xlfn.XLOOKUP($C12,'2) หลักการคำนวน Table'!$A$4:$A$36, _xlfn.XLOOKUP($B12,'2) หลักการคำนวน Table'!$L$3:$Z$3,'2) หลักการคำนวน Table'!$L$4:$Z$36))),0)} -> 400 | BF12: {=ROUND((_xlfn.XLOOKUP($C12,'2) หลักการคำนวน Table'!$A$4:$A$36, _xlfn.XLOOKUP(AT12,'2) หลักการคำนวน Table'!$C$3:$K$3,'2) หลักการคำนวน Table'!$C$4:$K$36,,-1)))*(_xlfn.XLOOKUP($C12,'2) หลักการคำนวน Table'!$A$4:$A$36, _xlfn.XLOOKUP($B12,'2) หลักการคำนวน Table'!$L$3:$Z$3,'2) หลักการคำนวน Table'!$L$4:$Z$36))),0)} -> 400 | BG12: {=ROUND((_xlfn.XLOOKUP($C12,'2) หลักการคำนวน Table'!$A$4:$A$36, _xlfn.XLOOKUP(AU12,'2) หลักการคำนวน Table'!$C$3:$K$3,'2) หลักการคำนวน Table'!$C$4:$K$36,,-1)))*(_xlfn.XLOOKUP($C12,'2) หลักการคำนวน Table'!$A$4:$A$36, _xlfn.XLOOKUP($B12,'2) หลักการคำนวน Table'!$L$3:$Z$3,'2) หลักการคำนวน Table'!$L$4:$Z$36))),0)} -> 400 | ... BK12: {=ROUND((_xlfn.XLOOKUP($C12,'2) หลักการคำนวน Table'!$A$4:$A$36, _xlfn.XLOOKUP(AY12,'2) หลักการคำนวน Table'!$C$3:$K$3,'2) หลักการคำนวน Table'!$C$4:$K$36,,-1)))*(_xlfn.XLOOKUP($C12,'2) หลักการคำนวน Table'!$A$4:$A$36, _xlfn.XLOOKUP($B12,'2) หลักการคำนวน Table'!$L$3:$Z$3,'2) หลักการคำนวน Table'!$L$4:$Z$36))),0)} -> 400 | BM12: 222209 | BN12: 400
A13: =VLOOKUP(C13,ASTBase!E:S,13,FALSE) -> 222208 | B13: RKR | C13: 5490000718 | D13: 150 | E13: 175 | F13: 104 | G13: 104 | H13: 130 | I13: 120 | J13: 100 | K13: 130 | L13: 130 | M13: 650 | N13: 120 | O13: 110 | P13: 118.8 | AB13: =IFERROR(IF(VLOOKUP($B13,Shortage!$A:$M,AB$2,FALSE)="Shortage",1,IFERROR(ROUND(P13/D13,4),0)),IFERROR(ROUND(P13/D13,4),0)) -> 0.792 | AC13: =IFERROR(IF(VLOOKUP($B13,Shortage!$A:$M,AC$2,FALSE)="Shortage",1,IFERROR(ROUND(Q13/E13,4),0)),IFERROR(ROUND(Q13/E13,4),0)) -> 0 | AD13: =IFERROR(IF(VLOOKUP($B13,Shortage!$A:$M,AD$2,FALSE)="Shortage",1,IFERROR(ROUND(R13/F13,4),0)),IFERROR(ROUND(R13/F13,4),0)) -> 0 | AE13: =IFERROR(IF(VLOOKUP($B13,Shortage!$A:$M,AE$2,FALSE)="Shortage",1,IFERROR(ROUND(S13/G13,4),0)),IFERROR(ROUND(S13/G13,4),0)) -> 0 | AF13: =IFERROR(IF(VLOOKUP($B13,Shortage!$A:$M,AF$2,FALSE)="Shortage",1,IFERROR(ROUND(T13/H13,4),0)),IFERROR(ROUND(T13/H13,4),0)) -> 0 | AG13: =IFERROR(IF(VLOOKUP($B13,Shortage!$A:$M,AG$2,FALSE)="Shortage",1,IFERROR(ROUND(U13/I13,4),0)),IFERROR(ROUND(U13/I13,4),0)) -> 0 | AH13: =IFERROR(IF(VLOOKUP($B13,Shortage!$A:$M,AH$2,FALSE)="Shortage",1,IFERROR(ROUND(V13/J13,4),0)),IFERROR(ROUND(V13/J13,4),0)) -> 0 | AI13: =IFERROR(IF(VLOOKUP($B13,Shortage!$A:$M,AI$2,FALSE)="Shortage",1,IFERROR(ROUND(W13/K13,4),0)),IFERROR(ROUND(W13/K13,4),0)) -> 0 | ... AM13: =IFERROR(IF(VLOOKUP($B13,Shortage!$A:$M,AM$2,FALSE)="Shortage",1,IFERROR(ROUND(AA13/O13,4),0)),IFERROR(ROUND(AA13/O13,4),0)) -> 0 | AN13: =IFERROR(_xlfn.XLOOKUP(AB13,'2) หลักการคำนวน Table'!$C$3:$K$3,'2) หลักการคำนวน Table'!$C$3:$K$3,,1),INDEX('2) หลักการคำนวน Table'!$C$3:$K$3,1)) -> 0.9 | AO13: =IFERROR( _xlfn.XLOOKUP(AC13,'2) หลักการคำนวน Table'!$C$3:$K$3,'2) หลักการคำนวน Table'!$C$3:$K$3,,1), IF(AC13<MIN('2) หลักการคำนวน Table'!$C$3:$K$3), MIN('2) หลักการคำนวน Table'!$C$3:$K$3), MAX('2) หลักการคำนวน Table'!$C$3:$K$3) ) ) -> 0.9 | AP13: =IFERROR( _xlfn.XLOOKUP(AD13,'2) หลักการคำนวน Table'!$C$3:$K$3,'2) หลักการคำนวน Table'!$C$3:$K$3,,1), IF(AD13<MIN('2) หลักการคำนวน Table'!$C$3:$K$3), MIN('2) หลักการคำนวน Table'!$C$3:$K$3), MAX('2) หลักการคำนวน Table'!$C$3:$K$3) ) ) -> 0.9 | AQ13: =IFERROR( _xlfn.XLOOKUP(AE13,'2) หลักการคำนวน Table'!$C$3:$K$3,'2) หลักการคำนวน Table'!$C$3:$K$3,,1), IF(AE13<MIN('2) หลักการคำนวน Table'!$C$3:$K$3), MIN('2) หลักการคำนวน Table'!$C$3:$K$3), MAX('2) หลักการคำนวน Table'!$C$3:$K$3) ) ) -> 0.9 | AR13: =IFERROR( _xlfn.XLOOKUP(AF13,'2) หลักการคำนวน Table'!$C$3:$K$3,'2) หลักการคำนวน Table'!$C$3:$K$3,,1), IF(AF13<MIN('2) หลักการคำนวน Table'!$C$3:$K$3), MIN('2) หลักการคำนวน Table'!$C$3:$K$3), MAX('2) หลักการคำนวน Table'!$C$3:$K$3) ) ) -> 0.9 | AS13: =IFERROR( _xlfn.XLOOKUP(AG13,'2) หลักการคำนวน Table'!$C$3:$K$3,'2) หลักการคำนวน Table'!$C$3:$K$3,,1), IF(AG13<MIN('2) หลักการคำนวน Table'!$C$3:$K$3), MIN('2) หลักการคำนวน Table'!$C$3:$K$3), MAX('2) หลักการคำนวน Table'!$C$3:$K$3) ) ) -> 0.9 | AT13: =IFERROR( _xlfn.XLOOKUP(AH13,'2) หลักการคำนวน Table'!$C$3:$K$3,'2) หลักการคำนวน Table'!$C$3:$K$3,,1), IF(AH13<MIN('2) หลักการคำนวน Table'!$C$3:$K$3), MIN('2) หลักการคำนวน Table'!$C$3:$K$3), MAX('2) หลักการคำนวน Table'!$C$3:$K$3) ) ) -> 0.9 | AU13: =IFERROR( _xlfn.XLOOKUP(AI13,'2) หลักการคำนวน Table'!$C$3:$K$3,'2) หลักการคำนวน Table'!$C$3:$K$3,,1), IF(AI13<MIN('2) หลักการคำนวน Table'!$C$3:$K$3), MIN('2) หลักการคำนวน Table'!$C$3:$K$3), MAX('2) หลักการคำนวน Table'!$C$3:$K$3) ) ) -> 0.9 | AV13: =IFERROR( _xlfn.XLOOKUP(AJ13,'2) หลักการคำนวน Table'!$C$3:$K$3,'2) หลักการคำนวน Table'!$C$3:$K$3,,1), IF(AJ13<MIN('2) หลักการคำนวน Table'!$C$3:$K$3), MIN('2) หลักการคำนวน Table'!$C$3:$K$3), MAX('2) หลักการคำนวน Table'!$C$3:$K$3) ) ) -> 0.9 | ... AY13: =IFERROR( _xlfn.XLOOKUP(AM13,'2) หลักการคำนวน Table'!$C$3:$K$3,'2) หลักการคำนวน Table'!$C$3:$K$3,,1), IF(AM13<MIN('2) หลักการคำนวน Table'!$C$3:$K$3), MIN('2) หลักการคำนวน Table'!$C$3:$K$3), MAX('2) หลักการคำนวน Table'!$C$3:$K$3) ) ) -> 0.9 | AZ13: {=ROUND((_xlfn.XLOOKUP($C13,'2) หลักการคำนวน Table'!$A$4:$A$36, _xlfn.XLOOKUP(AN13,'2) หลักการคำนวน Table'!$C$3:$K$3,'2) หลักการคำนวน Table'!$C$4:$K$36,,-1)))*(_xlfn.XLOOKUP($C13,'2) หลักการคำนวน Table'!$A$4:$A$36, _xlfn.XLOOKUP($B13,'2) หลักการคำนวน Table'!$L$3:$Z$3,'2) หลักการคำนวน Table'!$L$4:$Z$36))),0)} -> 160 | BA13: {=ROUND((_xlfn.XLOOKUP($C13,'2) หลักการคำนวน Table'!$A$4:$A$36, _xlfn.XLOOKUP(AO13,'2) หลักการคำนวน Table'!$C$3:$K$3,'2) หลักการคำนวน Table'!$C$4:$K$36,,-1)))*(_xlfn.XLOOKUP($C13,'2) หลักการคำนวน Table'!$A$4:$A$36, _xlfn.XLOOKUP($B13,'2) หลักการคำนวน Table'!$L$3:$Z$3,'2) หลักการคำนวน Table'!$L$4:$Z$36))),0)} -> 160 | BB13: {=ROUND((_xlfn.XLOOKUP($C13,'2) หลักการคำนวน Table'!$A$4:$A$36, _xlfn.XLOOKUP(AP13,'2) หลักการคำนวน Table'!$C$3:$K$3,'2) หลักการคำนวน Table'!$C$4:$K$36,,-1)))*(_xlfn.XLOOKUP($C13,'2) หลักการคำนวน Table'!$A$4:$A$36, _xlfn.XLOOKUP($B13,'2) หลักการคำนวน Table'!$L$3:$Z$3,'2) หลักการคำนวน Table'!$L$4:$Z$36))),0)} -> 160 | BC13: {=ROUND((_xlfn.XLOOKUP($C13,'2) หลักการคำนวน Table'!$A$4:$A$36, _xlfn.XLOOKUP(AQ13,'2) หลักการคำนวน Table'!$C$3:$K$3,'2) หลักการคำนวน Table'!$C$4:$K$36,,-1)))*(_xlfn.XLOOKUP($C13,'2) หลักการคำนวน Table'!$A$4:$A$36, _xlfn.XLOOKUP($B13,'2) หลักการคำนวน Table'!$L$3:$Z$3,'2) หลักการคำนวน Table'!$L$4:$Z$36))),0)} -> 160 | BD13: {=ROUND((_xlfn.XLOOKUP($C13,'2) หลักการคำนวน Table'!$A$4:$A$36, _xlfn.XLOOKUP(AR13,'2) หลักการคำนวน Table'!$C$3:$K$3,'2) หลักการคำนวน Table'!$C$4:$K$36,,-1)))*(_xlfn.XLOOKUP($C13,'2) หลักการคำนวน Table'!$A$4:$A$36, _xlfn.XLOOKUP($B13,'2) หลักการคำนวน Table'!$L$3:$Z$3,'2) หลักการคำนวน Table'!$L$4:$Z$36))),0)} -> 160 | BE13: {=ROUND((_xlfn.XLOOKUP($C13,'2) หลักการคำนวน Table'!$A$4:$A$36, _xlfn.XLOOKUP(AS13,'2) หลักการคำนวน Table'!$C$3:$K$3,'2) หลักการคำนวน Table'!$C$4:$K$36,,-1)))*(_xlfn.XLOOKUP($C13,'2) หลักการคำนวน Table'!$A$4:$A$36, _xlfn.XLOOKUP($B13,'2) หลักการคำนวน Table'!$L$3:$Z$3,'2) หลักการคำนวน Table'!$L$4:$Z$36))),0)} -> 160 | BF13: {=ROUND((_xlfn.XLOOKUP($C13,'2) หลักการคำนวน Table'!$A$4:$A$36, _xlfn.XLOOKUP(AT13,'2) หลักการคำนวน Table'!$C$3:$K$3,'2) หลักการคำนวน Table'!$C$4:$K$36,,-1)))*(_xlfn.XLOOKUP($C13,'2) หลักการคำนวน Table'!$A$4:$A$36, _xlfn.XLOOKUP($B13,'2) หลักการคำนวน Table'!$L$3:$Z$3,'2) หลักการคำนวน Table'!$L$4:$Z$36))),0)} -> 160 | BG13: {=ROUND((_xlfn.XLOOKUP($C13,'2) หลักการคำนวน Table'!$A$4:$A$36, _xlfn.XLOOKUP(AU13,'2) หลักการคำนวน Table'!$C$3:$K$3,'2) หลักการคำนวน Table'!$C$4:$K$36,,-1)))*(_xlfn.XLOOKUP($C13,'2) หลักการคำนวน Table'!$A$4:$A$36, _xlfn.XLOOKUP($B13,'2) หลักการคำนวน Table'!$L$3:$Z$3,'2) หลักการคำนวน Table'!$L$4:$Z$36))),0)} -> 160 | ... BK13: {=ROUND((_xlfn.XLOOKUP($C13,'2) หลักการคำนวน Table'!$A$4:$A$36, _xlfn.XLOOKUP(AY13,'2) หลักการคำนวน Table'!$C$3:$K$3,'2) หลักการคำนวน Table'!$C$4:$K$36,,-1)))*(_xlfn.XLOOKUP($C13,'2) หลักการคำนวน Table'!$A$4:$A$36, _xlfn.XLOOKUP($B13,'2) หลักการคำนวน Table'!$L$3:$Z$3,'2) หลักการคำนวน Table'!$L$4:$Z$36))),0)} -> 160 | BM13: 222209 | BN13: 160
A14: =VLOOKUP(C14,ASTBase!E:S,13,FALSE) -> 222208 | B14: TKM | C14: 5490000718 | D14: 1380 | E14: 1124 | F14: 1024 | G14: 944 | H14: 924 | I14: 924 | J14: 844 | K14: 874 | L14: 970 | M14: 894 | N14: 924 | O14: 894 | P14: 1785.6 | AB14: =IFERROR(IF(VLOOKUP($B14,Shortage!$A:$M,AB$2,FALSE)="Shortage",1,IFERROR(ROUND(P14/D14,4),0)),IFERROR(ROUND(P14/D14,4),0)) -> 1.2939 | AC14: =IFERROR(IF(VLOOKUP($B14,Shortage!$A:$M,AC$2,FALSE)="Shortage",1,IFERROR(ROUND(Q14/E14,4),0)),IFERROR(ROUND(Q14/E14,4),0)) -> 0 | AD14: =IFERROR(IF(VLOOKUP($B14,Shortage!$A:$M,AD$2,FALSE)="Shortage",1,IFERROR(ROUND(R14/F14,4),0)),IFERROR(ROUND(R14/F14,4),0)) -> 0 | AE14: =IFERROR(IF(VLOOKUP($B14,Shortage!$A:$M,AE$2,FALSE)="Shortage",1,IFERROR(ROUND(S14/G14,4),0)),IFERROR(ROUND(S14/G14,4),0)) -> 0 | AF14: =IFERROR(IF(VLOOKUP($B14,Shortage!$A:$M,AF$2,FALSE)="Shortage",1,IFERROR(ROUND(T14/H14,4),0)),IFERROR(ROUND(T14/H14,4),0)) -> 0 | AG14: =IFERROR(IF(VLOOKUP($B14,Shortage!$A:$M,AG$2,FALSE)="Shortage",1,IFERROR(ROUND(U14/I14,4),0)),IFERROR(ROUND(U14/I14,4),0)) -> 0 | AH14: =IFERROR(IF(VLOOKUP($B14,Shortage!$A:$M,AH$2,FALSE)="Shortage",1,IFERROR(ROUND(V14/J14,4),0)),IFERROR(ROUND(V14/J14,4),0)) -> 0 | AI14: =IFERROR(IF(VLOOKUP($B14,Shortage!$A:$M,AI$2,FALSE)="Shortage",1,IFERROR(ROUND(W14/K14,4),0)),IFERROR(ROUND(W14/K14,4),0)) -> 0 | ... AM14: =IFERROR(IF(VLOOKUP($B14,Shortage!$A:$M,AM$2,FALSE)="Shortage",1,IFERROR(ROUND(AA14/O14,4),0)),IFERROR(ROUND(AA14/O14,4),0)) -> 0 | AN14: =IFERROR(_xlfn.XLOOKUP(AB14,'2) หลักการคำนวน Table'!$C$3:$K$3,'2) หลักการคำนวน Table'!$C$3:$K$3,,1),INDEX('2) หลักการคำนวน Table'!$C$3:$K$3,1)) -> 20 | AO14: =IFERROR( _xlfn.XLOOKUP(AC14,'2) หลักการคำนวน Table'!$C$3:$K$3,'2) หลักการคำนวน Table'!$C$3:$K$3,,1), IF(AC14<MIN('2) หลักการคำนวน Table'!$C$3:$K$3), MIN('2) หลักการคำนวน Table'!$C$3:$K$3), MAX('2) หลักการคำนวน Table'!$C$3:$K$3) ) ) -> 0.9 | AP14: =IFERROR( _xlfn.XLOOKUP(AD14,'2) หลักการคำนวน Table'!$C$3:$K$3,'2) หลักการคำนวน Table'!$C$3:$K$3,,1), IF(AD14<MIN('2) หลักการคำนวน Table'!$C$3:$K$3), MIN('2) หลักการคำนวน Table'!$C$3:$K$3), MAX('2) หลักการคำนวน Table'!$C$3:$K$3) ) ) -> 0.9 | AQ14: =IFERROR( _xlfn.XLOOKUP(AE14,'2) หลักการคำนวน Table'!$C$3:$K$3,'2) หลักการคำนวน Table'!$C$3:$K$3,,1), IF(AE14<MIN('2) หลักการคำนวน Table'!$C$3:$K$3), MIN('2) หลักการคำนวน Table'!$C$3:$K$3), MAX('2) หลักการคำนวน Table'!$C$3:$K$3) ) ) -> 0.9 | AR14: =IFERROR( _xlfn.XLOOKUP(AF14,'2) หลักการคำนวน Table'!$C$3:$K$3,'2) หลักการคำนวน Table'!$C$3:$K$3,,1), IF(AF14<MIN('2) หลักการคำนวน Table'!$C$3:$K$3), MIN('2) หลักการคำนวน Table'!$C$3:$K$3), MAX('2) หลักการคำนวน Table'!$C$3:$K$3) ) ) -> 0.9 | AS14: =IFERROR( _xlfn.XLOOKUP(AG14,'2) หลักการคำนวน Table'!$C$3:$K$3,'2) หลักการคำนวน Table'!$C$3:$K$3,,1), IF(AG14<MIN('2) หลักการคำนวน Table'!$C$3:$K$3), MIN('2) หลักการคำนวน Table'!$C$3:$K$3), MAX('2) หลักการคำนวน Table'!$C$3:$K$3) ) ) -> 0.9 | AT14: =IFERROR( _xlfn.XLOOKUP(AH14,'2) หลักการคำนวน Table'!$C$3:$K$3,'2) หลักการคำนวน Table'!$C$3:$K$3,,1), IF(AH14<MIN('2) หลักการคำนวน Table'!$C$3:$K$3), MIN('2) หลักการคำนวน Table'!$C$3:$K$3), MAX('2) หลักการคำนวน Table'!$C$3:$K$3) ) ) -> 0.9 | AU14: =IFERROR( _xlfn.XLOOKUP(AI14,'2) หลักการคำนวน Table'!$C$3:$K$3,'2) หลักการคำนวน Table'!$C$3:$K$3,,1), IF(AI14<MIN('2) หลักการคำนวน Table'!$C$3:$K$3), MIN('2) หลักการคำนวน Table'!$C$3:$K$3), MAX('2) หลักการคำนวน Table'!$C$3:$K$3) ) ) -> 0.9 | AV14: =IFERROR( _xlfn.XLOOKUP(AJ14,'2) หลักการคำนวน Table'!$C$3:$K$3,'2) หลักการคำนวน Table'!$C$3:$K$3,,1), IF(AJ14<MIN('2) หลักการคำนวน Table'!$C$3:$K$3), MIN('2) หลักการคำนวน Table'!$C$3:$K$3), MAX('2) หลักการคำนวน Table'!$C$3:$K$3) ) ) -> 0.9 | ... AY14: =IFERROR( _xlfn.XLOOKUP(AM14,'2) หลักการคำนวน Table'!$C$3:$K$3,'2) หลักการคำนวน Table'!$C$3:$K$3,,1), IF(AM14<MIN('2) หลักการคำนวน Table'!$C$3:$K$3), MIN('2) หลักการคำนวน Table'!$C$3:$K$3), MAX('2) หลักการคำนวน Table'!$C$3:$K$3) ) ) -> 0.9 | AZ14: {=ROUND((_xlfn.XLOOKUP($C14,'2) หลักการคำนวน Table'!$A$4:$A$36, _xlfn.XLOOKUP(AN14,'2) หลักการคำนวน Table'!$C$3:$K$3,'2) หลักการคำนวน Table'!$C$4:$K$36,,-1)))*(_xlfn.XLOOKUP($C14,'2) หลักการคำนวน Table'!$A$4:$A$36, _xlfn.XLOOKUP($B14,'2) หลักการคำนวน Table'!$L$3:$Z$3,'2) หลักการคำนวน Table'!$L$4:$Z$36))),0)} -> 231 | BA14: {=ROUND((_xlfn.XLOOKUP($C14,'2) หลักการคำนวน Table'!$A$4:$A$36, _xlfn.XLOOKUP(AO14,'2) หลักการคำนวน Table'!$C$3:$K$3,'2) หลักการคำนวน Table'!$C$4:$K$36,,-1)))*(_xlfn.XLOOKUP($C14,'2) หลักการคำนวน Table'!$A$4:$A$36, _xlfn.XLOOKUP($B14,'2) หลักการคำนวน Table'!$L$3:$Z$3,'2) หลักการคำนวน Table'!$L$4:$Z$36))),0)} -> 160 | BB14: {=ROUND((_xlfn.XLOOKUP($C14,'2) หลักการคำนวน Table'!$A$4:$A$36, _xlfn.XLOOKUP(AP14,'2) หลักการคำนวน Table'!$C$3:$K$3,'2) หลักการคำนวน Table'!$C$4:$K$36,,-1)))*(_xlfn.XLOOKUP($C14,'2) หลักการคำนวน Table'!$A$4:$A$36, _xlfn.XLOOKUP($B14,'2) หลักการคำนวน Table'!$L$3:$Z$3,'2) หลักการคำนวน Table'!$L$4:$Z$36))),0)} -> 160 | BC14: {=ROUND((_xlfn.XLOOKUP($C14,'2) หลักการคำนวน Table'!$A$4:$A$36, _xlfn.XLOOKUP(AQ14,'2) หลักการคำนวน Table'!$C$3:$K$3,'2) หลักการคำนวน Table'!$C$4:$K$36,,-1)))*(_xlfn.XLOOKUP($C14,'2) หลักการคำนวน Table'!$A$4:$A$36, _xlfn.XLOOKUP($B14,'2) หลักการคำนวน Table'!$L$3:$Z$3,'2) หลักการคำนวน Table'!$L$4:$Z$36))),0)} -> 160 | BD14: {=ROUND((_xlfn.XLOOKUP($C14,'2) หลักการคำนวน Table'!$A$4:$A$36, _xlfn.XLOOKUP(AR14,'2) หลักการคำนวน Table'!$C$3:$K$3,'2) หลักการคำนวน Table'!$C$4:$K$36,,-1)))*(_xlfn.XLOOKUP($C14,'2) หลักการคำนวน Table'!$A$4:$A$36, _xlfn.XLOOKUP($B14,'2) หลักการคำนวน Table'!$L$3:$Z$3,'2) หลักการคำนวน Table'!$L$4:$Z$36))),0)} -> 160 | BE14: {=ROUND((_xlfn.XLOOKUP($C14,'2) หลักการคำนวน Table'!$A$4:$A$36, _xlfn.XLOOKUP(AS14,'2) หลักการคำนวน Table'!$C$3:$K$3,'2) หลักการคำนวน Table'!$C$4:$K$36,,-1)))*(_xlfn.XLOOKUP($C14,'2) หลักการคำนวน Table'!$A$4:$A$36, _xlfn.XLOOKUP($B14,'2) หลักการคำนวน Table'!$L$3:$Z$3,'2) หลักการคำนวน Table'!$L$4:$Z$36))),0)} -> 160 | BF14: {=ROUND((_xlfn.XLOOKUP($C14,'2) หลักการคำนวน Table'!$A$4:$A$36, _xlfn.XLOOKUP(AT14,'2) หลักการคำนวน Table'!$C$3:$K$3,'2) หลักการคำนวน Table'!$C$4:$K$36,,-1)))*(_xlfn.XLOOKUP($C14,'2) หลักการคำนวน Table'!$A$4:$A$36, _xlfn.XLOOKUP($B14,'2) หลักการคำนวน Table'!$L$3:$Z$3,'2) หลักการคำนวน Table'!$L$4:$Z$36))),0)} -> 160 | BG14: {=ROUND((_xlfn.XLOOKUP($C14,'2) หลักการคำนวน Table'!$A$4:$A$36, _xlfn.XLOOKUP(AU14,'2) หลักการคำนวน Table'!$C$3:$K$3,'2) หลักการคำนวน Table'!$C$4:$K$36,,-1)))*(_xlfn.XLOOKUP($C14,'2) หลักการคำนวน Table'!$A$4:$A$36, _xlfn.XLOOKUP($B14,'2) หลักการคำนวน Table'!$L$3:$Z$3,'2) หลักการคำนวน Table'!$L$4:$Z$36))),0)} -> 160 | ... BK14: {=ROUND((_xlfn.XLOOKUP($C14,'2) หลักการคำนวน Table'!$A$4:$A$36, _xlfn.XLOOKUP(AY14,'2) หลักการคำนวน Table'!$C$3:$K$3,'2) หลักการคำนวน Table'!$C$4:$K$36,,-1)))*(_xlfn.XLOOKUP($C14,'2) หลักการคำนวน Table'!$A$4:$A$36, _xlfn.XLOOKUP($B14,'2) หลักการคำนวน Table'!$L$3:$Z$3,'2) หลักการคำนวน Table'!$L$4:$Z$36))),0)} -> 160 | BM14: 222209 | BN14: 231
A15: =VLOOKUP(C15,ASTBase!E:S,13,FALSE) -> 222208 | B15: YY | C15: 5490000718 | D15: 4426 | E15: 5546 | F15: 4840 | G15: 5143 | H15: 4320 | I15: 3530 | J15: 5120 | K15: 3735 | L15: 4420 | M15: 5325 | N15: 6120 | O15: 5335 | P15: 3374 | AB15: =IFERROR(IF(VLOOKUP($B15,Shortage!$A:$M,AB$2,FALSE)="Shortage",1,IFERROR(ROUND(P15/D15,4),0)),IFERROR(ROUND(P15/D15,4),0)) -> 1 | AC15: =IFERROR(IF(VLOOKUP($B15,Shortage!$A:$M,AC$2,FALSE)="Shortage",1,IFERROR(ROUND(Q15/E15,4),0)),IFERROR(ROUND(Q15/E15,4),0)) -> 0 | AD15: =IFERROR(IF(VLOOKUP($B15,Shortage!$A:$M,AD$2,FALSE)="Shortage",1,IFERROR(ROUND(R15/F15,4),0)),IFERROR(ROUND(R15/F15,4),0)) -> 0 | AE15: =IFERROR(IF(VLOOKUP($B15,Shortage!$A:$M,AE$2,FALSE)="Shortage",1,IFERROR(ROUND(S15/G15,4),0)),IFERROR(ROUND(S15/G15,4),0)) -> 0 | AF15: =IFERROR(IF(VLOOKUP($B15,Shortage!$A:$M,AF$2,FALSE)="Shortage",1,IFERROR(ROUND(T15/H15,4),0)),IFERROR(ROUND(T15/H15,4),0)) -> 0 | AG15: =IFERROR(IF(VLOOKUP($B15,Shortage!$A:$M,AG$2,FALSE)="Shortage",1,IFERROR(ROUND(U15/I15,4),0)),IFERROR(ROUND(U15/I15,4),0)) -> 0 | AH15: =IFERROR(IF(VLOOKUP($B15,Shortage!$A:$M,AH$2,FALSE)="Shortage",1,IFERROR(ROUND(V15/J15,4),0)),IFERROR(ROUND(V15/J15,4),0)) -> 0 | AI15: =IFERROR(IF(VLOOKUP($B15,Shortage!$A:$M,AI$2,FALSE)="Shortage",1,IFERROR(ROUND(W15/K15,4),0)),IFERROR(ROUND(W15/K15,4),0)) -> 0 | ... AM15: =IFERROR(IF(VLOOKUP($B15,Shortage!$A:$M,AM$2,FALSE)="Shortage",1,IFERROR(ROUND(AA15/O15,4),0)),IFERROR(ROUND(AA15/O15,4),0)) -> 0 | AN15: =IFERROR(_xlfn.XLOOKUP(AB15,'2) หลักการคำนวน Table'!$C$3:$K$3,'2) หลักการคำนวน Table'!$C$3:$K$3,,1),INDEX('2) หลักการคำนวน Table'!$C$3:$K$3,1)) -> 1 | AO15: =IFERROR( _xlfn.XLOOKUP(AC15,'2) หลักการคำนวน Table'!$C$3:$K$3,'2) หลักการคำนวน Table'!$C$3:$K$3,,1), IF(AC15<MIN('2) หลักการคำนวน Table'!$C$3:$K$3), MIN('2) หลักการคำนวน Table'!$C$3:$K$3), MAX('2) หลักการคำนวน Table'!$C$3:$K$3) ) ) -> 0.9 | AP15: =IFERROR( _xlfn.XLOOKUP(AD15,'2) หลักการคำนวน Table'!$C$3:$K$3,'2) หลักการคำนวน Table'!$C$3:$K$3,,1), IF(AD15<MIN('2) หลักการคำนวน Table'!$C$3:$K$3), MIN('2) หลักการคำนวน Table'!$C$3:$K$3), MAX('2) หลักการคำนวน Table'!$C$3:$K$3) ) ) -> 0.9 | AQ15: =IFERROR( _xlfn.XLOOKUP(AE15,'2) หลักการคำนวน Table'!$C$3:$K$3,'2) หลักการคำนวน Table'!$C$3:$K$3,,1), IF(AE15<MIN('2) หลักการคำนวน Table'!$C$3:$K$3), MIN('2) หลักการคำนวน Table'!$C$3:$K$3), MAX('2) หลักการคำนวน Table'!$C$3:$K$3) ) ) -> 0.9 | AR15: =IFERROR( _xlfn.XLOOKUP(AF15,'2) หลักการคำนวน Table'!$C$3:$K$3,'2) หลักการคำนวน Table'!$C$3:$K$3,,1), IF(AF15<MIN('2) หลักการคำนวน Table'!$C$3:$K$3), MIN('2) หลักการคำนวน Table'!$C$3:$K$3), MAX('2) หลักการคำนวน Table'!$C$3:$K$3) ) ) -> 0.9 | AS15: =IFERROR( _xlfn.XLOOKUP(AG15,'2) หลักการคำนวน Table'!$C$3:$K$3,'2) หลักการคำนวน Table'!$C$3:$K$3,,1), IF(AG15<MIN('2) หลักการคำนวน Table'!$C$3:$K$3), MIN('2) หลักการคำนวน Table'!$C$3:$K$3), MAX('2) หลักการคำนวน Table'!$C$3:$K$3) ) ) -> 0.9 | AT15: =IFERROR( _xlfn.XLOOKUP(AH15,'2) หลักการคำนวน Table'!$C$3:$K$3,'2) หลักการคำนวน Table'!$C$3:$K$3,,1), IF(AH15<MIN('2) หลักการคำนวน Table'!$C$3:$K$3), MIN('2) หลักการคำนวน Table'!$C$3:$K$3), MAX('2) หลักการคำนวน Table'!$C$3:$K$3) ) ) -> 0.9 | AU15: =IFERROR( _xlfn.XLOOKUP(AI15,'2) หลักการคำนวน Table'!$C$3:$K$3,'2) หลักการคำนวน Table'!$C$3:$K$3,,1), IF(AI15<MIN('2) หลักการคำนวน Table'!$C$3:$K$3), MIN('2) หลักการคำนวน Table'!$C$3:$K$3), MAX('2) หลักการคำนวน Table'!$C$3:$K$3) ) ) -> 0.9 | AV15: =IFERROR( _xlfn.XLOOKUP(AJ15,'2) หลักการคำนวน Table'!$C$3:$K$3,'2) หลักการคำนวน Table'!$C$3:$K$3,,1), IF(AJ15<MIN('2) หลักการคำนวน Table'!$C$3:$K$3), MIN('2) หลักการคำนวน Table'!$C$3:$K$3), MAX('2) หลักการคำนวน Table'!$C$3:$K$3) ) ) -> 0.9 | ... AY15: =IFERROR( _xlfn.XLOOKUP(AM15,'2) หลักการคำนวน Table'!$C$3:$K$3,'2) หลักการคำนวน Table'!$C$3:$K$3,,1), IF(AM15<MIN('2) หลักการคำนวน Table'!$C$3:$K$3), MIN('2) หลักการคำนวน Table'!$C$3:$K$3), MAX('2) หลักการคำนวน Table'!$C$3:$K$3) ) ) -> 0.9 | AZ15: {=ROUND((_xlfn.XLOOKUP($C15,'2) หลักการคำนวน Table'!$A$4:$A$36, _xlfn.XLOOKUP(AN15,'2) หลักการคำนวน Table'!$C$3:$K$3,'2) หลักการคำนวน Table'!$C$4:$K$36,,-1)))*(_xlfn.XLOOKUP($C15,'2) หลักการคำนวน Table'!$A$4:$A$36, _xlfn.XLOOKUP($B15,'2) หลักการคำนวน Table'!$L$3:$Z$3,'2) หลักการคำนวน Table'!$L$4:$Z$36))),0)} -> 444 | BA15: {=ROUND((_xlfn.XLOOKUP($C15,'2) หลักการคำนวน Table'!$A$4:$A$36, _xlfn.XLOOKUP(AO15,'2) หลักการคำนวน Table'!$C$3:$K$3,'2) หลักการคำนวน Table'!$C$4:$K$36,,-1)))*(_xlfn.XLOOKUP($C15,'2) หลักการคำนวน Table'!$A$4:$A$36, _xlfn.XLOOKUP($B15,'2) หลักการคำนวน Table'!$L$3:$Z$3,'2) หลักการคำนวน Table'!$L$4:$Z$36))),0)} -> 400 | BB15: {=ROUND((_xlfn.XLOOKUP($C15,'2) หลักการคำนวน Table'!$A$4:$A$36, _xlfn.XLOOKUP(AP15,'2) หลักการคำนวน Table'!$C$3:$K$3,'2) หลักการคำนวน Table'!$C$4:$K$36,,-1)))*(_xlfn.XLOOKUP($C15,'2) หลักการคำนวน Table'!$A$4:$A$36, _xlfn.XLOOKUP($B15,'2) หลักการคำนวน Table'!$L$3:$Z$3,'2) หลักการคำนวน Table'!$L$4:$Z$36))),0)} -> 400 | BC15: {=ROUND((_xlfn.XLOOKUP($C15,'2) หลักการคำนวน Table'!$A$4:$A$36, _xlfn.XLOOKUP(AQ15,'2) หลักการคำนวน Table'!$C$3:$K$3,'2) หลักการคำนวน Table'!$C$4:$K$36,,-1)))*(_xlfn.XLOOKUP($C15,'2) หลักการคำนวน Table'!$A$4:$A$36, _xlfn.XLOOKUP($B15,'2) หลักการคำนวน Table'!$L$3:$Z$3,'2) หลักการคำนวน Table'!$L$4:$Z$36))),0)} -> 400 | BD15: {=ROUND((_xlfn.XLOOKUP($C15,'2) หลักการคำนวน Table'!$A$4:$A$36, _xlfn.XLOOKUP(AR15,'2) หลักการคำนวน Table'!$C$3:$K$3,'2) หลักการคำนวน Table'!$C$4:$K$36,,-1)))*(_xlfn.XLOOKUP($C15,'2) หลักการคำนวน Table'!$A$4:$A$36, _xlfn.XLOOKUP($B15,'2) หลักการคำนวน Table'!$L$3:$Z$3,'2) หลักการคำนวน Table'!$L$4:$Z$36))),0)} -> 400 | BE15: {=ROUND((_xlfn.XLOOKUP($C15,'2) หลักการคำนวน Table'!$A$4:$A$36, _xlfn.XLOOKUP(AS15,'2) หลักการคำนวน Table'!$C$3:$K$3,'2) หลักการคำนวน Table'!$C$4:$K$36,,-1)))*(_xlfn.XLOOKUP($C15,'2) หลักการคำนวน Table'!$A$4:$A$36, _xlfn.XLOOKUP($B15,'2) หลักการคำนวน Table'!$L$3:$Z$3,'2) หลักการคำนวน Table'!$L$4:$Z$36))),0)} -> 400 | BF15: {=ROUND((_xlfn.XLOOKUP($C15,'2) หลักการคำนวน Table'!$A$4:$A$36, _xlfn.XLOOKUP(AT15,'2) หลักการคำนวน Table'!$C$3:$K$3,'2) หลักการคำนวน Table'!$C$4:$K$36,,-1)))*(_xlfn.XLOOKUP($C15,'2) หลักการคำนวน Table'!$A$4:$A$36, _xlfn.XLOOKUP($B15,'2) หลักการคำนวน Table'!$L$3:$Z$3,'2) หลักการคำนวน Table'!$L$4:$Z$36))),0)} -> 400 | BG15: {=ROUND((_xlfn.XLOOKUP($C15,'2) หลักการคำนวน Table'!$A$4:$A$36, _xlfn.XLOOKUP(AU15,'2) หลักการคำนวน Table'!$C$3:$K$3,'2) หลักการคำนวน Table'!$C$4:$K$36,,-1)))*(_xlfn.XLOOKUP($C15,'2) หลักการคำนวน Table'!$A$4:$A$36, _xlfn.XLOOKUP($B15,'2) หลักการคำนวน Table'!$L$3:$Z$3,'2) หลักการคำนวน Table'!$L$4:$Z$36))),0)} -> 400 | ... BK15: {=ROUND((_xlfn.XLOOKUP($C15,'2) หลักการคำนวน Table'!$A$4:$A$36, _xlfn.XLOOKUP(AY15,'2) หลักการคำนวน Table'!$C$3:$K$3,'2) หลักการคำนวน Table'!$C$4:$K$36,,-1)))*(_xlfn.XLOOKUP($C15,'2) หลักการคำนวน Table'!$A$4:$A$36, _xlfn.XLOOKUP($B15,'2) หลักการคำนวน Table'!$L$3:$Z$3,'2) หลักการคำนวน Table'!$L$4:$Z$36))),0)} -> 400 | BM15: 222209 | BN15: 444
... A61: =VLOOKUP(C61,ASTBase!E:S,13,FALSE) -> #N/A | B61: AJ | C61: 5490000721 | D61: 364.4 | E61: 1189.4 | F61: 553.2 | G61: 1280 | H61: 1042 | I61: 712.4 | J61: 875.2 | K61: 2202.8 | L61: 2359.2 | M61: 894.8 | N61: 1688.2 | O61: 1538 | P61: 2033.2 | AB61: =IFERROR(IF(VLOOKUP($B61,Shortage!$A:$M,AB$2,FALSE)="Shortage",1,IFERROR(ROUND(P61/D61,4),0)),IFERROR(ROUND(P61/D61,4),0)) -> 1 | AC61: =IFERROR(IF(VLOOKUP($B61,Shortage!$A:$M,AC$2,FALSE)="Shortage",1,IFERROR(ROUND(Q61/E61,4),0)),IFERROR(ROUND(Q61/E61,4),0)) -> 0 | AD61: =IFERROR(IF(VLOOKUP($B61,Shortage!$A:$M,AD$2,FALSE)="Shortage",1,IFERROR(ROUND(R61/F61,4),0)),IFERROR(ROUND(R61/F61,4),0)) -> 0 | AE61: =IFERROR(IF(VLOOKUP($B61,Shortage!$A:$M,AE$2,FALSE)="Shortage",1,IFERROR(ROUND(S61/G61,4),0)),IFERROR(ROUND(S61/G61,4),0)) -> 0 | AF61: =IFERROR(IF(VLOOKUP($B61,Shortage!$A:$M,AF$2,FALSE)="Shortage",1,IFERROR(ROUND(T61/H61,4),0)),IFERROR(ROUND(T61/H61,4),0)) -> 0 | AG61: =IFERROR(IF(VLOOKUP($B61,Shortage!$A:$M,AG$2,FALSE)="Shortage",1,IFERROR(ROUND(U61/I61,4),0)),IFERROR(ROUND(U61/I61,4),0)) -> 0 | AH61: =IFERROR(IF(VLOOKUP($B61,Shortage!$A:$M,AH$2,FALSE)="Shortage",1,IFERROR(ROUND(V61/J61,4),0)),IFERROR(ROUND(V61/J61,4),0)) -> 0 | AI61: =IFERROR(IF(VLOOKUP($B61,Shortage!$A:$M,AI$2,FALSE)="Shortage",1,IFERROR(ROUND(W61/K61,4),0)),IFERROR(ROUND(W61/K61,4),0)) -> 0 | ... AM61: =IFERROR(IF(VLOOKUP($B61,Shortage!$A:$M,AM$2,FALSE)="Shortage",1,IFERROR(ROUND(AA61/O61,4),0)),IFERROR(ROUND(AA61/O61,4),0)) -> 0 | AN61: =IFERROR(_xlfn.XLOOKUP(AB61,'2) หลักการคำนวน Table'!$C$3:$K$3,'2) หลักการคำนวน Table'!$C$3:$K$3,,1),INDEX('2) หลักการคำนวน Table'!$C$3:$K$3,1)) -> 1 | AO61: =IFERROR( _xlfn.XLOOKUP(AC61,'2) หลักการคำนวน Table'!$C$3:$K$3,'2) หลักการคำนวน Table'!$C$3:$K$3,,1), IF(AC61<MIN('2) หลักการคำนวน Table'!$C$3:$K$3), MIN('2) หลักการคำนวน Table'!$C$3:$K$3), MAX('2) หลักการคำนวน Table'!$C$3:$K$3) ) ) -> 0.9 | AP61: =IFERROR( _xlfn.XLOOKUP(AD61,'2) หลักการคำนวน Table'!$C$3:$K$3,'2) หลักการคำนวน Table'!$C$3:$K$3,,1), IF(AD61<MIN('2) หลักการคำนวน Table'!$C$3:$K$3), MIN('2) หลักการคำนวน Table'!$C$3:$K$3), MAX('2) หลักการคำนวน Table'!$C$3:$K$3) ) ) -> 0.9 | AQ61: =IFERROR( _xlfn.XLOOKUP(AE61,'2) หลักการคำนวน Table'!$C$3:$K$3,'2) หลักการคำนวน Table'!$C$3:$K$3,,1), IF(AE61<MIN('2) หลักการคำนวน Table'!$C$3:$K$3), MIN('2) หลักการคำนวน Table'!$C$3:$K$3), MAX('2) หลักการคำนวน Table'!$C$3:$K$3) ) ) -> 0.9 | AR61: =IFERROR( _xlfn.XLOOKUP(AF61,'2) หลักการคำนวน Table'!$C$3:$K$3,'2) หลักการคำนวน Table'!$C$3:$K$3,,1), IF(AF61<MIN('2) หลักการคำนวน Table'!$C$3:$K$3), MIN('2) หลักการคำนวน Table'!$C$3:$K$3), MAX('2) หลักการคำนวน Table'!$C$3:$K$3) ) ) -> 0.9 | AS61: =IFERROR( _xlfn.XLOOKUP(AG61,'2) หลักการคำนวน Table'!$C$3:$K$3,'2) หลักการคำนวน Table'!$C$3:$K$3,,1), IF(AG61<MIN('2) หลักการคำนวน Table'!$C$3:$K$3), MIN('2) หลักการคำนวน Table'!$C$3:$K$3), MAX('2) หลักการคำนวน Table'!$C$3:$K$3) ) ) -> 0.9 | AT61: =IFERROR( _xlfn.XLOOKUP(AH61,'2) หลักการคำนวน Table'!$C$3:$K$3,'2) หลักการคำนวน Table'!$C$3:$K$3,,1), IF(AH61<MIN('2) หลักการคำนวน Table'!$C$3:$K$3), MIN('2) หลักการคำนวน Table'!$C$3:$K$3), MAX('2) หลักการคำนวน Table'!$C$3:$K$3) ) ) -> 0.9 | AU61: =IFERROR( _xlfn.XLOOKUP(AI61,'2) หลักการคำนวน Table'!$C$3:$K$3,'2) หลักการคำนวน Table'!$C$3:$K$3,,1), IF(AI61<MIN('2) หลักการคำนวน Table'!$C$3:$K$3), MIN('2) หลักการคำนวน Table'!$C$3:$K$3), MAX('2) หลักการคำนวน Table'!$C$3:$K$3) ) ) -> 0.9 | AV61: =IFERROR( _xlfn.XLOOKUP(AJ61,'2) หลักการคำนวน Table'!$C$3:$K$3,'2) หลักการคำนวน Table'!$C$3:$K$3,,1), IF(AJ61<MIN('2) หลักการคำนวน Table'!$C$3:$K$3), MIN('2) หลักการคำนวน Table'!$C$3:$K$3), MAX('2) หลักการคำนวน Table'!$C$3:$K$3) ) ) -> 0.9 | ... AY61: =IFERROR( _xlfn.XLOOKUP(AM61,'2) หลักการคำนวน Table'!$C$3:$K$3,'2) หลักการคำนวน Table'!$C$3:$K$3,,1), IF(AM61<MIN('2) หลักการคำนวน Table'!$C$3:$K$3), MIN('2) หลักการคำนวน Table'!$C$3:$K$3), MAX('2) หลักการคำนวน Table'!$C$3:$K$3) ) ) -> 0.9 | AZ61: {=ROUND((_xlfn.XLOOKUP($C61,'2) หลักการคำนวน Table'!$A$4:$A$36, _xlfn.XLOOKUP(AN61,'2) หลักการคำนวน Table'!$C$3:$K$3,'2) หลักการคำนวน Table'!$C$4:$K$36,,-1)))*(_xlfn.XLOOKUP($C61,'2) หลักการคำนวน Table'!$A$4:$A$36, _xlfn.XLOOKUP($B61,'2) หลักการคำนวน Table'!$L$3:$Z$3,'2) หลักการคำนวน Table'!$L$4:$Z$36))),0)} -> #N/A | BA61: {=ROUND((_xlfn.XLOOKUP($C61,'2) หลักการคำนวน Table'!$A$4:$A$36, _xlfn.XLOOKUP(AO61,'2) หลักการคำนวน Table'!$C$3:$K$3,'2) หลักการคำนวน Table'!$C$4:$K$36,,-1)))*(_xlfn.XLOOKUP($C61,'2) หลักการคำนวน Table'!$A$4:$A$36, _xlfn.XLOOKUP($B61,'2) หลักการคำนวน Table'!$L$3:$Z$3,'2) หลักการคำนวน Table'!$L$4:$Z$36))),0)} -> #N/A | BB61: {=ROUND((_xlfn.XLOOKUP($C61,'2) หลักการคำนวน Table'!$A$4:$A$36, _xlfn.XLOOKUP(AP61,'2) หลักการคำนวน Table'!$C$3:$K$3,'2) หลักการคำนวน Table'!$C$4:$K$36,,-1)))*(_xlfn.XLOOKUP($C61,'2) หลักการคำนวน Table'!$A$4:$A$36, _xlfn.XLOOKUP($B61,'2) หลักการคำนวน Table'!$L$3:$Z$3,'2) หลักการคำนวน Table'!$L$4:$Z$36))),0)} -> #N/A | BC61: {=ROUND((_xlfn.XLOOKUP($C61,'2) หลักการคำนวน Table'!$A$4:$A$36, _xlfn.XLOOKUP(AQ61,'2) หลักการคำนวน Table'!$C$3:$K$3,'2) หลักการคำนวน Table'!$C$4:$K$36,,-1)))*(_xlfn.XLOOKUP($C61,'2) หลักการคำนวน Table'!$A$4:$A$36, _xlfn.XLOOKUP($B61,'2) หลักการคำนวน Table'!$L$3:$Z$3,'2) หลักการคำนวน Table'!$L$4:$Z$36))),0)} -> #N/A | BD61: {=ROUND((_xlfn.XLOOKUP($C61,'2) หลักการคำนวน Table'!$A$4:$A$36, _xlfn.XLOOKUP(AR61,'2) หลักการคำนวน Table'!$C$3:$K$3,'2) หลักการคำนวน Table'!$C$4:$K$36,,-1)))*(_xlfn.XLOOKUP($C61,'2) หลักการคำนวน Table'!$A$4:$A$36, _xlfn.XLOOKUP($B61,'2) หลักการคำนวน Table'!$L$3:$Z$3,'2) หลักการคำนวน Table'!$L$4:$Z$36))),0)} -> #N/A | BE61: {=ROUND((_xlfn.XLOOKUP($C61,'2) หลักการคำนวน Table'!$A$4:$A$36, _xlfn.XLOOKUP(AS61,'2) หลักการคำนวน Table'!$C$3:$K$3,'2) หลักการคำนวน Table'!$C$4:$K$36,,-1)))*(_xlfn.XLOOKUP($C61,'2) หลักการคำนวน Table'!$A$4:$A$36, _xlfn.XLOOKUP($B61,'2) หลักการคำนวน Table'!$L$3:$Z$3,'2) หลักการคำนวน Table'!$L$4:$Z$36))),0)} -> #N/A | BF61: {=ROUND((_xlfn.XLOOKUP($C61,'2) หลักการคำนวน Table'!$A$4:$A$36, _xlfn.XLOOKUP(AT61,'2) หลักการคำนวน Table'!$C$3:$K$3,'2) หลักการคำนวน Table'!$C$4:$K$36,,-1)))*(_xlfn.XLOOKUP($C61,'2) หลักการคำนวน Table'!$A$4:$A$36, _xlfn.XLOOKUP($B61,'2) หลักการคำนวน Table'!$L$3:$Z$3,'2) หลักการคำนวน Table'!$L$4:$Z$36))),0)} -> #N/A | BG61: {=ROUND((_xlfn.XLOOKUP($C61,'2) หลักการคำนวน Table'!$A$4:$A$36, _xlfn.XLOOKUP(AU61,'2) หลักการคำนวน Table'!$C$3:$K$3,'2) หลักการคำนวน Table'!$C$4:$K$36,,-1)))*(_xlfn.XLOOKUP($C61,'2) หลักการคำนวน Table'!$A$4:$A$36, _xlfn.XLOOKUP($B61,'2) หลักการคำนวน Table'!$L$3:$Z$3,'2) หลักการคำนวน Table'!$L$4:$Z$36))),0)} -> #N/A | ... BK61: {=ROUND((_xlfn.XLOOKUP($C61,'2) หลักการคำนวน Table'!$A$4:$A$36, _xlfn.XLOOKUP(AY61,'2) หลักการคำนวน Table'!$C$3:$K$3,'2) หลักการคำนวน Table'!$C$4:$K$36,,-1)))*(_xlfn.XLOOKUP($C61,'2) หลักการคำนวน Table'!$A$4:$A$36, _xlfn.XLOOKUP($B61,'2) หลักการคำนวน Table'!$L$3:$Z$3,'2) หลักการคำนวน Table'!$L$4:$Z$36))),0)} -> #N/A | BM61: 222218 | BN61: 167
A62: =VLOOKUP(C62,ASTBase!E:S,13,FALSE) -> #N/A | B62: AJP | C62: 5490000721 | D62: 10.08 | E62: 0 | F62: 10.08 | G62: 0 | H62: 20.16 | I62: 10.08 | J62: 10 | K62: 0 | L62: 10 | M62: 0 | N62: 0 | O62: 10.08 | AB62: =IFERROR(IF(VLOOKUP($B62,Shortage!$A:$M,AB$2,FALSE)="Shortage",1,IFERROR(ROUND(P62/D62,4),0)),IFERROR(ROUND(P62/D62,4),0)) -> 0 | AC62: =IFERROR(IF(VLOOKUP($B62,Shortage!$A:$M,AC$2,FALSE)="Shortage",1,IFERROR(ROUND(Q62/E62,4),0)),IFERROR(ROUND(Q62/E62,4),0)) -> 0 | AD62: =IFERROR(IF(VLOOKUP($B62,Shortage!$A:$M,AD$2,FALSE)="Shortage",1,IFERROR(ROUND(R62/F62,4),0)),IFERROR(ROUND(R62/F62,4),0)) -> 0 | AE62: =IFERROR(IF(VLOOKUP($B62,Shortage!$A:$M,AE$2,FALSE)="Shortage",1,IFERROR(ROUND(S62/G62,4),0)),IFERROR(ROUND(S62/G62,4),0)) -> 0 | AF62: =IFERROR(IF(VLOOKUP($B62,Shortage!$A:$M,AF$2,FALSE)="Shortage",1,IFERROR(ROUND(T62/H62,4),0)),IFERROR(ROUND(T62/H62,4),0)) -> 0 | AG62: =IFERROR(IF(VLOOKUP($B62,Shortage!$A:$M,AG$2,FALSE)="Shortage",1,IFERROR(ROUND(U62/I62,4),0)),IFERROR(ROUND(U62/I62,4),0)) -> 0 | AH62: =IFERROR(IF(VLOOKUP($B62,Shortage!$A:$M,AH$2,FALSE)="Shortage",1,IFERROR(ROUND(V62/J62,4),0)),IFERROR(ROUND(V62/J62,4),0)) -> 0 | AI62: =IFERROR(IF(VLOOKUP($B62,Shortage!$A:$M,AI$2,FALSE)="Shortage",1,IFERROR(ROUND(W62/K62,4),0)),IFERROR(ROUND(W62/K62,4),0)) -> 0 | ... AM62: =IFERROR(IF(VLOOKUP($B62,Shortage!$A:$M,AM$2,FALSE)="Shortage",1,IFERROR(ROUND(AA62/O62,4),0)),IFERROR(ROUND(AA62/O62,4),0)) -> 0 | AN62: =IFERROR(_xlfn.XLOOKUP(AB62,'2) หลักการคำนวน Table'!$C$3:$K$3,'2) หลักการคำนวน Table'!$C$3:$K$3,,1),INDEX('2) หลักการคำนวน Table'!$C$3:$K$3,1)) -> 0.9 | AO62: =IFERROR( _xlfn.XLOOKUP(AC62,'2) หลักการคำนวน Table'!$C$3:$K$3,'2) หลักการคำนวน Table'!$C$3:$K$3,,1), IF(AC62<MIN('2) หลักการคำนวน Table'!$C$3:$K$3), MIN('2) หลักการคำนวน Table'!$C$3:$K$3), MAX('2) หลักการคำนวน Table'!$C$3:$K$3) ) ) -> 0.9 | AP62: =IFERROR( _xlfn.XLOOKUP(AD62,'2) หลักการคำนวน Table'!$C$3:$K$3,'2) หลักการคำนวน Table'!$C$3:$K$3,,1), IF(AD62<MIN('2) หลักการคำนวน Table'!$C$3:$K$3), MIN('2) หลักการคำนวน Table'!$C$3:$K$3), MAX('2) หลักการคำนวน Table'!$C$3:$K$3) ) ) -> 0.9 | AQ62: =IFERROR( _xlfn.XLOOKUP(AE62,'2) หลักการคำนวน Table'!$C$3:$K$3,'2) หลักการคำนวน Table'!$C$3:$K$3,,1), IF(AE62<MIN('2) หลักการคำนวน Table'!$C$3:$K$3), MIN('2) หลักการคำนวน Table'!$C$3:$K$3), MAX('2) หลักการคำนวน Table'!$C$3:$K$3) ) ) -> 0.9 | AR62: =IFERROR( _xlfn.XLOOKUP(AF62,'2) หลักการคำนวน Table'!$C$3:$K$3,'2) หลักการคำนวน Table'!$C$3:$K$3,,1), IF(AF62<MIN('2) หลักการคำนวน Table'!$C$3:$K$3), MIN('2) หลักการคำนวน Table'!$C$3:$K$3), MAX('2) หลักการคำนวน Table'!$C$3:$K$3) ) ) -> 0.9 | AS62: =IFERROR( _xlfn.XLOOKUP(AG62,'2) หลักการคำนวน Table'!$C$3:$K$3,'2) หลักการคำนวน Table'!$C$3:$K$3,,1), IF(AG62<MIN('2) หลักการคำนวน Table'!$C$3:$K$3), MIN('2) หลักการคำนวน Table'!$C$3:$K$3), MAX('2) หลักการคำนวน Table'!$C$3:$K$3) ) ) -> 0.9 | AT62: =IFERROR( _xlfn.XLOOKUP(AH62,'2) หลักการคำนวน Table'!$C$3:$K$3,'2) หลักการคำนวน Table'!$C$3:$K$3,,1), IF(AH62<MIN('2) หลักการคำนวน Table'!$C$3:$K$3), MIN('2) หลักการคำนวน Table'!$C$3:$K$3), MAX('2) หลักการคำนวน Table'!$C$3:$K$3) ) ) -> 0.9 | AU62: =IFERROR( _xlfn.XLOOKUP(AI62,'2) หลักการคำนวน Table'!$C$3:$K$3,'2) หลักการคำนวน Table'!$C$3:$K$3,,1), IF(AI62<MIN('2) หลักการคำนวน Table'!$C$3:$K$3), MIN('2) หลักการคำนวน Table'!$C$3:$K$3), MAX('2) หลักการคำนวน Table'!$C$3:$K$3) ) ) -> 0.9 | AV62: =IFERROR( _xlfn.XLOOKUP(AJ62,'2) หลักการคำนวน Table'!$C$3:$K$3,'2) หลักการคำนวน Table'!$C$3:$K$3,,1), IF(AJ62<MIN('2) หลักการคำนวน Table'!$C$3:$K$3), MIN('2) หลักการคำนวน Table'!$C$3:$K$3), MAX('2) หลักการคำนวน Table'!$C$3:$K$3) ) ) -> 0.9 | ... AY62: =IFERROR( _xlfn.XLOOKUP(AM62,'2) หลักการคำนวน Table'!$C$3:$K$3,'2) หลักการคำนวน Table'!$C$3:$K$3,,1), IF(AM62<MIN('2) หลักการคำนวน Table'!$C$3:$K$3), MIN('2) หลักการคำนวน Table'!$C$3:$K$3), MAX('2) หลักการคำนวน Table'!$C$3:$K$3) ) ) -> 0.9 | AZ62: {=ROUND((_xlfn.XLOOKUP($C62,'2) หลักการคำนวน Table'!$A$4:$A$36, _xlfn.XLOOKUP(AN62,'2) หลักการคำนวน Table'!$C$3:$K$3,'2) หลักการคำนวน Table'!$C$4:$K$36,,-1)))*(_xlfn.XLOOKUP($C62,'2) หลักการคำนวน Table'!$A$4:$A$36, _xlfn.XLOOKUP($B62,'2) หลักการคำนวน Table'!$L$3:$Z$3,'2) หลักการคำนวน Table'!$L$4:$Z$36))),0)} -> #N/A | BA62: {=ROUND((_xlfn.XLOOKUP($C62,'2) หลักการคำนวน Table'!$A$4:$A$36, _xlfn.XLOOKUP(AO62,'2) หลักการคำนวน Table'!$C$3:$K$3,'2) หลักการคำนวน Table'!$C$4:$K$36,,-1)))*(_xlfn.XLOOKUP($C62,'2) หลักการคำนวน Table'!$A$4:$A$36, _xlfn.XLOOKUP($B62,'2) หลักการคำนวน Table'!$L$3:$Z$3,'2) หลักการคำนวน Table'!$L$4:$Z$36))),0)} -> #N/A | BB62: {=ROUND((_xlfn.XLOOKUP($C62,'2) หลักการคำนวน Table'!$A$4:$A$36, _xlfn.XLOOKUP(AP62,'2) หลักการคำนวน Table'!$C$3:$K$3,'2) หลักการคำนวน Table'!$C$4:$K$36,,-1)))*(_xlfn.XLOOKUP($C62,'2) หลักการคำนวน Table'!$A$4:$A$36, _xlfn.XLOOKUP($B62,'2) หลักการคำนวน Table'!$L$3:$Z$3,'2) หลักการคำนวน Table'!$L$4:$Z$36))),0)} -> #N/A | BC62: {=ROUND((_xlfn.XLOOKUP($C62,'2) หลักการคำนวน Table'!$A$4:$A$36, _xlfn.XLOOKUP(AQ62,'2) หลักการคำนวน Table'!$C$3:$K$3,'2) หลักการคำนวน Table'!$C$4:$K$36,,-1)))*(_xlfn.XLOOKUP($C62,'2) หลักการคำนวน Table'!$A$4:$A$36, _xlfn.XLOOKUP($B62,'2) หลักการคำนวน Table'!$L$3:$Z$3,'2) หลักการคำนวน Table'!$L$4:$Z$36))),0)} -> #N/A | BD62: {=ROUND((_xlfn.XLOOKUP($C62,'2) หลักการคำนวน Table'!$A$4:$A$36, _xlfn.XLOOKUP(AR62,'2) หลักการคำนวน Table'!$C$3:$K$3,'2) หลักการคำนวน Table'!$C$4:$K$36,,-1)))*(_xlfn.XLOOKUP($C62,'2) หลักการคำนวน Table'!$A$4:$A$36, _xlfn.XLOOKUP($B62,'2) หลักการคำนวน Table'!$L$3:$Z$3,'2) หลักการคำนวน Table'!$L$4:$Z$36))),0)} -> #N/A | BE62: {=ROUND((_xlfn.XLOOKUP($C62,'2) หลักการคำนวน Table'!$A$4:$A$36, _xlfn.XLOOKUP(AS62,'2) หลักการคำนวน Table'!$C$3:$K$3,'2) หลักการคำนวน Table'!$C$4:$K$36,,-1)))*(_xlfn.XLOOKUP($C62,'2) หลักการคำนวน Table'!$A$4:$A$36, _xlfn.XLOOKUP($B62,'2) หลักการคำนวน Table'!$L$3:$Z$3,'2) หลักการคำนวน Table'!$L$4:$Z$36))),0)} -> #N/A | BF62: {=ROUND((_xlfn.XLOOKUP($C62,'2) หลักการคำนวน Table'!$A$4:$A$36, _xlfn.XLOOKUP(AT62,'2) หลักการคำนวน Table'!$C$3:$K$3,'2) หลักการคำนวน Table'!$C$4:$K$36,,-1)))*(_xlfn.XLOOKUP($C62,'2) หลักการคำนวน Table'!$A$4:$A$36, _xlfn.XLOOKUP($B62,'2) หลักการคำนวน Table'!$L$3:$Z$3,'2) หลักการคำนวน Table'!$L$4:$Z$36))),0)} -> #N/A | BG62: {=ROUND((_xlfn.XLOOKUP($C62,'2) หลักการคำนวน Table'!$A$4:$A$36, _xlfn.XLOOKUP(AU62,'2) หลักการคำนวน Table'!$C$3:$K$3,'2) หลักการคำนวน Table'!$C$4:$K$36,,-1)))*(_xlfn.XLOOKUP($C62,'2) หลักการคำนวน Table'!$A$4:$A$36, _xlfn.XLOOKUP($B62,'2) หลักการคำนวน Table'!$L$3:$Z$3,'2) หลักการคำนวน Table'!$L$4:$Z$36))),0)} -> #N/A | ... BK62: {=ROUND((_xlfn.XLOOKUP($C62,'2) หลักการคำนวน Table'!$A$4:$A$36, _xlfn.XLOOKUP(AY62,'2) หลักการคำนวน Table'!$C$3:$K$3,'2) หลักการคำนวน Table'!$C$4:$K$36,,-1)))*(_xlfn.XLOOKUP($C62,'2) หลักการคำนวน Table'!$A$4:$A$36, _xlfn.XLOOKUP($B62,'2) หลักการคำนวน Table'!$L$3:$Z$3,'2) หลักการคำนวน Table'!$L$4:$Z$36))),0)} -> #N/A | BM62: 222218 | BN62: 250
A63: =VLOOKUP(C63,ASTBase!E:S,13,FALSE) -> #N/A | B63: AMV | C63: 5490000721 | D63: 30 | E63: 30 | F63: 30 | G63: 30 | H63: 35 | I63: 35 | J63: 35 | K63: 35 | L63: 35 | M63: 35 | N63: 35 | O63: 35 | P63: 26 | AB63: =IFERROR(IF(VLOOKUP($B63,Shortage!$A:$M,AB$2,FALSE)="Shortage",1,IFERROR(ROUND(P63/D63,4),0)),IFERROR(ROUND(P63/D63,4),0)) -> 0.8667 | AC63: =IFERROR(IF(VLOOKUP($B63,Shortage!$A:$M,AC$2,FALSE)="Shortage",1,IFERROR(ROUND(Q63/E63,4),0)),IFERROR(ROUND(Q63/E63,4),0)) -> 0 | AD63: =IFERROR(IF(VLOOKUP($B63,Shortage!$A:$M,AD$2,FALSE)="Shortage",1,IFERROR(ROUND(R63/F63,4),0)),IFERROR(ROUND(R63/F63,4),0)) -> 0 | AE63: =IFERROR(IF(VLOOKUP($B63,Shortage!$A:$M,AE$2,FALSE)="Shortage",1,IFERROR(ROUND(S63/G63,4),0)),IFERROR(ROUND(S63/G63,4),0)) -> 0 | AF63: =IFERROR(IF(VLOOKUP($B63,Shortage!$A:$M,AF$2,FALSE)="Shortage",1,IFERROR(ROUND(T63/H63,4),0)),IFERROR(ROUND(T63/H63,4),0)) -> 0 | AG63: =IFERROR(IF(VLOOKUP($B63,Shortage!$A:$M,AG$2,FALSE)="Shortage",1,IFERROR(ROUND(U63/I63,4),0)),IFERROR(ROUND(U63/I63,4),0)) -> 0 | AH63: =IFERROR(IF(VLOOKUP($B63,Shortage!$A:$M,AH$2,FALSE)="Shortage",1,IFERROR(ROUND(V63/J63,4),0)),IFERROR(ROUND(V63/J63,4),0)) -> 0 | AI63: =IFERROR(IF(VLOOKUP($B63,Shortage!$A:$M,AI$2,FALSE)="Shortage",1,IFERROR(ROUND(W63/K63,4),0)),IFERROR(ROUND(W63/K63,4),0)) -> 0 | ... AM63: =IFERROR(IF(VLOOKUP($B63,Shortage!$A:$M,AM$2,FALSE)="Shortage",1,IFERROR(ROUND(AA63/O63,4),0)),IFERROR(ROUND(AA63/O63,4),0)) -> 0 | AN63: =IFERROR(_xlfn.XLOOKUP(AB63,'2) หลักการคำนวน Table'!$C$3:$K$3,'2) หลักการคำนวน Table'!$C$3:$K$3,,1),INDEX('2) หลักการคำนวน Table'!$C$3:$K$3,1)) -> 0.9 | AO63: =IFERROR( _xlfn.XLOOKUP(AC63,'2) หลักการคำนวน Table'!$C$3:$K$3,'2) หลักการคำนวน Table'!$C$3:$K$3,,1), IF(AC63<MIN('2) หลักการคำนวน Table'!$C$3:$K$3), MIN('2) หลักการคำนวน Table'!$C$3:$K$3), MAX('2) หลักการคำนวน Table'!$C$3:$K$3) ) ) -> 0.9 | AP63: =IFERROR( _xlfn.XLOOKUP(AD63,'2) หลักการคำนวน Table'!$C$3:$K$3,'2) หลักการคำนวน Table'!$C$3:$K$3,,1), IF(AD63<MIN('2) หลักการคำนวน Table'!$C$3:$K$3), MIN('2) หลักการคำนวน Table'!$C$3:$K$3), MAX('2) หลักการคำนวน Table'!$C$3:$K$3) ) ) -> 0.9 | AQ63: =IFERROR( _xlfn.XLOOKUP(AE63,'2) หลักการคำนวน Table'!$C$3:$K$3,'2) หลักการคำนวน Table'!$C$3:$K$3,,1), IF(AE63<MIN('2) หลักการคำนวน Table'!$C$3:$K$3), MIN('2) หลักการคำนวน Table'!$C$3:$K$3), MAX('2) หลักการคำนวน Table'!$C$3:$K$3) ) ) -> 0.9 | AR63: =IFERROR( _xlfn.XLOOKUP(AF63,'2) หลักการคำนวน Table'!$C$3:$K$3,'2) หลักการคำนวน Table'!$C$3:$K$3,,1), IF(AF63<MIN('2) หลักการคำนวน Table'!$C$3:$K$3), MIN('2) หลักการคำนวน Table'!$C$3:$K$3), MAX('2) หลักการคำนวน Table'!$C$3:$K$3) ) ) -> 0.9 | AS63: =IFERROR( _xlfn.XLOOKUP(AG63,'2) หลักการคำนวน Table'!$C$3:$K$3,'2) หลักการคำนวน Table'!$C$3:$K$3,,1), IF(AG63<MIN('2) หลักการคำนวน Table'!$C$3:$K$3), MIN('2) หลักการคำนวน Table'!$C$3:$K$3), MAX('2) หลักการคำนวน Table'!$C$3:$K$3) ) ) -> 0.9 | AT63: =IFERROR( _xlfn.XLOOKUP(AH63,'2) หลักการคำนวน Table'!$C$3:$K$3,'2) หลักการคำนวน Table'!$C$3:$K$3,,1), IF(AH63<MIN('2) หลักการคำนวน Table'!$C$3:$K$3), MIN('2) หลักการคำนวน Table'!$C$3:$K$3), MAX('2) หลักการคำนวน Table'!$C$3:$K$3) ) ) -> 0.9 | AU63: =IFERROR( _xlfn.XLOOKUP(AI63,'2) หลักการคำนวน Table'!$C$3:$K$3,'2) หลักการคำนวน Table'!$C$3:$K$3,,1), IF(AI63<MIN('2) หลักการคำนวน Table'!$C$3:$K$3), MIN('2) หลักการคำนวน Table'!$C$3:$K$3), MAX('2) หลักการคำนวน Table'!$C$3:$K$3) ) ) -> 0.9 | AV63: =IFERROR( _xlfn.XLOOKUP(AJ63,'2) หลักการคำนวน Table'!$C$3:$K$3,'2) หลักการคำนวน Table'!$C$3:$K$3,,1), IF(AJ63<MIN('2) หลักการคำนวน Table'!$C$3:$K$3), MIN('2) หลักการคำนวน Table'!$C$3:$K$3), MAX('2) หลักการคำนวน Table'!$C$3:$K$3) ) ) -> 0.9 | ... AY63: =IFERROR( _xlfn.XLOOKUP(AM63,'2) หลักการคำนวน Table'!$C$3:$K$3,'2) หลักการคำนวน Table'!$C$3:$K$3,,1), IF(AM63<MIN('2) หลักการคำนวน Table'!$C$3:$K$3), MIN('2) หลักการคำนวน Table'!$C$3:$K$3), MAX('2) หลักการคำนวน Table'!$C$3:$K$3) ) ) -> 0.9 | AZ63: {=ROUND((_xlfn.XLOOKUP($C63,'2) หลักการคำนวน Table'!$A$4:$A$36, _xlfn.XLOOKUP(AN63,'2) หลักการคำนวน Table'!$C$3:$K$3,'2) หลักการคำนวน Table'!$C$4:$K$36,,-1)))*(_xlfn.XLOOKUP($C63,'2) หลักการคำนวน Table'!$A$4:$A$36, _xlfn.XLOOKUP($B63,'2) หลักการคำนวน Table'!$L$3:$Z$3,'2) หลักการคำนวน Table'!$L$4:$Z$36))),0)} -> #N/A | BA63: {=ROUND((_xlfn.XLOOKUP($C63,'2) หลักการคำนวน Table'!$A$4:$A$36, _xlfn.XLOOKUP(AO63,'2) หลักการคำนวน Table'!$C$3:$K$3,'2) หลักการคำนวน Table'!$C$4:$K$36,,-1)))*(_xlfn.XLOOKUP($C63,'2) หลักการคำนวน Table'!$A$4:$A$36, _xlfn.XLOOKUP($B63,'2) หลักการคำนวน Table'!$L$3:$Z$3,'2) หลักการคำนวน Table'!$L$4:$Z$36))),0)} -> #N/A | BB63: {=ROUND((_xlfn.XLOOKUP($C63,'2) หลักการคำนวน Table'!$A$4:$A$36, _xlfn.XLOOKUP(AP63,'2) หลักการคำนวน Table'!$C$3:$K$3,'2) หลักการคำนวน Table'!$C$4:$K$36,,-1)))*(_xlfn.XLOOKUP($C63,'2) หลักการคำนวน Table'!$A$4:$A$36, _xlfn.XLOOKUP($B63,'2) หลักการคำนวน Table'!$L$3:$Z$3,'2) หลักการคำนวน Table'!$L$4:$Z$36))),0)} -> #N/A | BC63: {=ROUND((_xlfn.XLOOKUP($C63,'2) หลักการคำนวน Table'!$A$4:$A$36, _xlfn.XLOOKUP(AQ63,'2) หลักการคำนวน Table'!$C$3:$K$3,'2) หลักการคำนวน Table'!$C$4:$K$36,,-1)))*(_xlfn.XLOOKUP($C63,'2) หลักการคำนวน Table'!$A$4:$A$36, _xlfn.XLOOKUP($B63,'2) หลักการคำนวน Table'!$L$3:$Z$3,'2) หลักการคำนวน Table'!$L$4:$Z$36))),0)} -> #N/A | BD63: {=ROUND((_xlfn.XLOOKUP($C63,'2) หลักการคำนวน Table'!$A$4:$A$36, _xlfn.XLOOKUP(AR63,'2) หลักการคำนวน Table'!$C$3:$K$3,'2) หลักการคำนวน Table'!$C$4:$K$36,,-1)))*(_xlfn.XLOOKUP($C63,'2) หลักการคำนวน Table'!$A$4:$A$36, _xlfn.XLOOKUP($B63,'2) หลักการคำนวน Table'!$L$3:$Z$3,'2) หลักการคำนวน Table'!$L$4:$Z$36))),0)} -> #N/A | BE63: {=ROUND((_xlfn.XLOOKUP($C63,'2) หลักการคำนวน Table'!$A$4:$A$36, _xlfn.XLOOKUP(AS63,'2) หลักการคำนวน Table'!$C$3:$K$3,'2) หลักการคำนวน Table'!$C$4:$K$36,,-1)))*(_xlfn.XLOOKUP($C63,'2) หลักการคำนวน Table'!$A$4:$A$36, _xlfn.XLOOKUP($B63,'2) หลักการคำนวน Table'!$L$3:$Z$3,'2) หลักการคำนวน Table'!$L$4:$Z$36))),0)} -> #N/A | BF63: {=ROUND((_xlfn.XLOOKUP($C63,'2) หลักการคำนวน Table'!$A$4:$A$36, _xlfn.XLOOKUP(AT63,'2) หลักการคำนวน Table'!$C$3:$K$3,'2) หลักการคำนวน Table'!$C$4:$K$36,,-1)))*(_xlfn.XLOOKUP($C63,'2) หลักการคำนวน Table'!$A$4:$A$36, _xlfn.XLOOKUP($B63,'2) หลักการคำนวน Table'!$L$3:$Z$3,'2) หลักการคำนวน Table'!$L$4:$Z$36))),0)} -> #N/A | BG63: {=ROUND((_xlfn.XLOOKUP($C63,'2) หลักการคำนวน Table'!$A$4:$A$36, _xlfn.XLOOKUP(AU63,'2) หลักการคำนวน Table'!$C$3:$K$3,'2) หลักการคำนวน Table'!$C$4:$K$36,,-1)))*(_xlfn.XLOOKUP($C63,'2) หลักการคำนวน Table'!$A$4:$A$36, _xlfn.XLOOKUP($B63,'2) หลักการคำนวน Table'!$L$3:$Z$3,'2) หลักการคำนวน Table'!$L$4:$Z$36))),0)} -> #N/A | ... BK63: {=ROUND((_xlfn.XLOOKUP($C63,'2) หลักการคำนวน Table'!$A$4:$A$36, _xlfn.XLOOKUP(AY63,'2) หลักการคำนวน Table'!$C$3:$K$3,'2) หลักการคำนวน Table'!$C$4:$K$36,,-1)))*(_xlfn.XLOOKUP($C63,'2) หลักการคำนวน Table'!$A$4:$A$36, _xlfn.XLOOKUP($B63,'2) หลักการคำนวน Table'!$L$3:$Z$3,'2) หลักการคำนวน Table'!$L$4:$Z$36))),0)} -> #N/A | BM63: 222218 | BN63: 100
A64: =VLOOKUP(C64,ASTBase!E:S,13,FALSE) -> #N/A | B64: BD | C64: 5490000721 | D64: 130 | E64: 140 | F64: 153 | G64: 144 | H64: 121 | I64: 130 | J64: 156 | K64: 152 | L64: 164 | M64: 94 | N64: 152 | O64: 156 | P64: 167 | AB64: =IFERROR(IF(VLOOKUP($B64,Shortage!$A:$M,AB$2,FALSE)="Shortage",1,IFERROR(ROUND(P64/D64,4),0)),IFERROR(ROUND(P64/D64,4),0)) -> 1.2846 | AC64: =IFERROR(IF(VLOOKUP($B64,Shortage!$A:$M,AC$2,FALSE)="Shortage",1,IFERROR(ROUND(Q64/E64,4),0)),IFERROR(ROUND(Q64/E64,4),0)) -> 0 | AD64: =IFERROR(IF(VLOOKUP($B64,Shortage!$A:$M,AD$2,FALSE)="Shortage",1,IFERROR(ROUND(R64/F64,4),0)),IFERROR(ROUND(R64/F64,4),0)) -> 0 | AE64: =IFERROR(IF(VLOOKUP($B64,Shortage!$A:$M,AE$2,FALSE)="Shortage",1,IFERROR(ROUND(S64/G64,4),0)),IFERROR(ROUND(S64/G64,4),0)) -> 0 | AF64: =IFERROR(IF(VLOOKUP($B64,Shortage!$A:$M,AF$2,FALSE)="Shortage",1,IFERROR(ROUND(T64/H64,4),0)),IFERROR(ROUND(T64/H64,4),0)) -> 0 | AG64: =IFERROR(IF(VLOOKUP($B64,Shortage!$A:$M,AG$2,FALSE)="Shortage",1,IFERROR(ROUND(U64/I64,4),0)),IFERROR(ROUND(U64/I64,4),0)) -> 0 | AH64: =IFERROR(IF(VLOOKUP($B64,Shortage!$A:$M,AH$2,FALSE)="Shortage",1,IFERROR(ROUND(V64/J64,4),0)),IFERROR(ROUND(V64/J64,4),0)) -> 0 | AI64: =IFERROR(IF(VLOOKUP($B64,Shortage!$A:$M,AI$2,FALSE)="Shortage",1,IFERROR(ROUND(W64/K64,4),0)),IFERROR(ROUND(W64/K64,4),0)) -> 0 | ... AM64: =IFERROR(IF(VLOOKUP($B64,Shortage!$A:$M,AM$2,FALSE)="Shortage",1,IFERROR(ROUND(AA64/O64,4),0)),IFERROR(ROUND(AA64/O64,4),0)) -> 0 | AN64: =IFERROR(_xlfn.XLOOKUP(AB64,'2) หลักการคำนวน Table'!$C$3:$K$3,'2) หลักการคำนวน Table'!$C$3:$K$3,,1),INDEX('2) หลักการคำนวน Table'!$C$3:$K$3,1)) -> 20 | AO64: =IFERROR( _xlfn.XLOOKUP(AC64,'2) หลักการคำนวน Table'!$C$3:$K$3,'2) หลักการคำนวน Table'!$C$3:$K$3,,1), IF(AC64<MIN('2) หลักการคำนวน Table'!$C$3:$K$3), MIN('2) หลักการคำนวน Table'!$C$3:$K$3), MAX('2) หลักการคำนวน Table'!$C$3:$K$3) ) ) -> 0.9 | AP64: =IFERROR( _xlfn.XLOOKUP(AD64,'2) หลักการคำนวน Table'!$C$3:$K$3,'2) หลักการคำนวน Table'!$C$3:$K$3,,1), IF(AD64<MIN('2) หลักการคำนวน Table'!$C$3:$K$3), MIN('2) หลักการคำนวน Table'!$C$3:$K$3), MAX('2) หลักการคำนวน Table'!$C$3:$K$3) ) ) -> 0.9 | AQ64: =IFERROR( _xlfn.XLOOKUP(AE64,'2) หลักการคำนวน Table'!$C$3:$K$3,'2) หลักการคำนวน Table'!$C$3:$K$3,,1), IF(AE64<MIN('2) หลักการคำนวน Table'!$C$3:$K$3), MIN('2) หลักการคำนวน Table'!$C$3:$K$3), MAX('2) หลักการคำนวน Table'!$C$3:$K$3) ) ) -> 0.9 | AR64: =IFERROR( _xlfn.XLOOKUP(AF64,'2) หลักการคำนวน Table'!$C$3:$K$3,'2) หลักการคำนวน Table'!$C$3:$K$3,,1), IF(AF64<MIN('2) หลักการคำนวน Table'!$C$3:$K$3), MIN('2) หลักการคำนวน Table'!$C$3:$K$3), MAX('2) หลักการคำนวน Table'!$C$3:$K$3) ) ) -> 0.9 | AS64: =IFERROR( _xlfn.XLOOKUP(AG64,'2) หลักการคำนวน Table'!$C$3:$K$3,'2) หลักการคำนวน Table'!$C$3:$K$3,,1), IF(AG64<MIN('2) หลักการคำนวน Table'!$C$3:$K$3), MIN('2) หลักการคำนวน Table'!$C$3:$K$3), MAX('2) หลักการคำนวน Table'!$C$3:$K$3) ) ) -> 0.9 | AT64: =IFERROR( _xlfn.XLOOKUP(AH64,'2) หลักการคำนวน Table'!$C$3:$K$3,'2) หลักการคำนวน Table'!$C$3:$K$3,,1), IF(AH64<MIN('2) หลักการคำนวน Table'!$C$3:$K$3), MIN('2) หลักการคำนวน Table'!$C$3:$K$3), MAX('2) หลักการคำนวน Table'!$C$3:$K$3) ) ) -> 0.9 | AU64: =IFERROR( _xlfn.XLOOKUP(AI64,'2) หลักการคำนวน Table'!$C$3:$K$3,'2) หลักการคำนวน Table'!$C$3:$K$3,,1), IF(AI64<MIN('2) หลักการคำนวน Table'!$C$3:$K$3), MIN('2) หลักการคำนวน Table'!$C$3:$K$3), MAX('2) หลักการคำนวน Table'!$C$3:$K$3) ) ) -> 0.9 | AV64: =IFERROR( _xlfn.XLOOKUP(AJ64,'2) หลักการคำนวน Table'!$C$3:$K$3,'2) หลักการคำนวน Table'!$C$3:$K$3,,1), IF(AJ64<MIN('2) หลักการคำนวน Table'!$C$3:$K$3), MIN('2) หลักการคำนวน Table'!$C$3:$K$3), MAX('2) หลักการคำนวน Table'!$C$3:$K$3) ) ) -> 0.9 | ... AY64: =IFERROR( _xlfn.XLOOKUP(AM64,'2) หลักการคำนวน Table'!$C$3:$K$3,'2) หลักการคำนวน Table'!$C$3:$K$3,,1), IF(AM64<MIN('2) หลักการคำนวน Table'!$C$3:$K$3), MIN('2) หลักการคำนวน Table'!$C$3:$K$3), MAX('2) หลักการคำนวน Table'!$C$3:$K$3) ) ) -> 0.9 | AZ64: {=ROUND((_xlfn.XLOOKUP($C64,'2) หลักการคำนวน Table'!$A$4:$A$36, _xlfn.XLOOKUP(AN64,'2) หลักการคำนวน Table'!$C$3:$K$3,'2) หลักการคำนวน Table'!$C$4:$K$36,,-1)))*(_xlfn.XLOOKUP($C64,'2) หลักการคำนวน Table'!$A$4:$A$36, _xlfn.XLOOKUP($B64,'2) หลักการคำนวน Table'!$L$3:$Z$3,'2) หลักการคำนวน Table'!$L$4:$Z$36))),0)} -> #N/A | BA64: {=ROUND((_xlfn.XLOOKUP($C64,'2) หลักการคำนวน Table'!$A$4:$A$36, _xlfn.XLOOKUP(AO64,'2) หลักการคำนวน Table'!$C$3:$K$3,'2) หลักการคำนวน Table'!$C$4:$K$36,,-1)))*(_xlfn.XLOOKUP($C64,'2) หลักการคำนวน Table'!$A$4:$A$36, _xlfn.XLOOKUP($B64,'2) หลักการคำนวน Table'!$L$3:$Z$3,'2) หลักการคำนวน Table'!$L$4:$Z$36))),0)} -> #N/A | BB64: {=ROUND((_xlfn.XLOOKUP($C64,'2) หลักการคำนวน Table'!$A$4:$A$36, _xlfn.XLOOKUP(AP64,'2) หลักการคำนวน Table'!$C$3:$K$3,'2) หลักการคำนวน Table'!$C$4:$K$36,,-1)))*(_xlfn.XLOOKUP($C64,'2) หลักการคำนวน Table'!$A$4:$A$36, _xlfn.XLOOKUP($B64,'2) หลักการคำนวน Table'!$L$3:$Z$3,'2) หลักการคำนวน Table'!$L$4:$Z$36))),0)} -> #N/A | BC64: {=ROUND((_xlfn.XLOOKUP($C64,'2) หลักการคำนวน Table'!$A$4:$A$36, _xlfn.XLOOKUP(AQ64,'2) หลักการคำนวน Table'!$C$3:$K$3,'2) หลักการคำนวน Table'!$C$4:$K$36,,-1)))*(_xlfn.XLOOKUP($C64,'2) หลักการคำนวน Table'!$A$4:$A$36, _xlfn.XLOOKUP($B64,'2) หลักการคำนวน Table'!$L$3:$Z$3,'2) หลักการคำนวน Table'!$L$4:$Z$36))),0)} -> #N/A | BD64: {=ROUND((_xlfn.XLOOKUP($C64,'2) หลักการคำนวน Table'!$A$4:$A$36, _xlfn.XLOOKUP(AR64,'2) หลักการคำนวน Table'!$C$3:$K$3,'2) หลักการคำนวน Table'!$C$4:$K$36,,-1)))*(_xlfn.XLOOKUP($C64,'2) หลักการคำนวน Table'!$A$4:$A$36, _xlfn.XLOOKUP($B64,'2) หลักการคำนวน Table'!$L$3:$Z$3,'2) หลักการคำนวน Table'!$L$4:$Z$36))),0)} -> #N/A | BE64: {=ROUND((_xlfn.XLOOKUP($C64,'2) หลักการคำนวน Table'!$A$4:$A$36, _xlfn.XLOOKUP(AS64,'2) หลักการคำนวน Table'!$C$3:$K$3,'2) หลักการคำนวน Table'!$C$4:$K$36,,-1)))*(_xlfn.XLOOKUP($C64,'2) หลักการคำนวน Table'!$A$4:$A$36, _xlfn.XLOOKUP($B64,'2) หลักการคำนวน Table'!$L$3:$Z$3,'2) หลักการคำนวน Table'!$L$4:$Z$36))),0)} -> #N/A | BF64: {=ROUND((_xlfn.XLOOKUP($C64,'2) หลักการคำนวน Table'!$A$4:$A$36, _xlfn.XLOOKUP(AT64,'2) หลักการคำนวน Table'!$C$3:$K$3,'2) หลักการคำนวน Table'!$C$4:$K$36,,-1)))*(_xlfn.XLOOKUP($C64,'2) หลักการคำนวน Table'!$A$4:$A$36, _xlfn.XLOOKUP($B64,'2) หลักการคำนวน Table'!$L$3:$Z$3,'2) หลักการคำนวน Table'!$L$4:$Z$36))),0)} -> #N/A | BG64: {=ROUND((_xlfn.XLOOKUP($C64,'2) หลักการคำนวน Table'!$A$4:$A$36, _xlfn.XLOOKUP(AU64,'2) หลักการคำนวน Table'!$C$3:$K$3,'2) หลักการคำนวน Table'!$C$4:$K$36,,-1)))*(_xlfn.XLOOKUP($C64,'2) หลักการคำนวน Table'!$A$4:$A$36, _xlfn.XLOOKUP($B64,'2) หลักการคำนวน Table'!$L$3:$Z$3,'2) หลักการคำนวน Table'!$L$4:$Z$36))),0)} -> #N/A | ... BK64: {=ROUND((_xlfn.XLOOKUP($C64,'2) หลักการคำนวน Table'!$A$4:$A$36, _xlfn.XLOOKUP(AY64,'2) หลักการคำนวน Table'!$C$3:$K$3,'2) หลักการคำนวน Table'!$C$4:$K$36,,-1)))*(_xlfn.XLOOKUP($C64,'2) หลักการคำนวน Table'!$A$4:$A$36, _xlfn.XLOOKUP($B64,'2) หลักการคำนวน Table'!$L$3:$Z$3,'2) หลักการคำนวน Table'!$L$4:$Z$36))),0)} -> #N/A | BM64: 222218 | BN64: 722
A65: =VLOOKUP(C65,ASTBase!E:S,13,FALSE) -> #N/A | B65: FP | C65: 5490000721 | D65: 400 | E65: 400 | F65: 420 | G65: 420 | H65: 420 | I65: 420 | J65: 420 | K65: 420 | L65: 420 | M65: 420 | N65: 420 | O65: 420 | P65: 417.096 | AB65: =IFERROR(IF(VLOOKUP($B65,Shortage!$A:$M,AB$2,FALSE)="Shortage",1,IFERROR(ROUND(P65/D65,4),0)),IFERROR(ROUND(P65/D65,4),0)) -> 1.0427 | AC65: =IFERROR(IF(VLOOKUP($B65,Shortage!$A:$M,AC$2,FALSE)="Shortage",1,IFERROR(ROUND(Q65/E65,4),0)),IFERROR(ROUND(Q65/E65,4),0)) -> 0 | AD65: =IFERROR(IF(VLOOKUP($B65,Shortage!$A:$M,AD$2,FALSE)="Shortage",1,IFERROR(ROUND(R65/F65,4),0)),IFERROR(ROUND(R65/F65,4),0)) -> 0 | AE65: =IFERROR(IF(VLOOKUP($B65,Shortage!$A:$M,AE$2,FALSE)="Shortage",1,IFERROR(ROUND(S65/G65,4),0)),IFERROR(ROUND(S65/G65,4),0)) -> 0 | AF65: =IFERROR(IF(VLOOKUP($B65,Shortage!$A:$M,AF$2,FALSE)="Shortage",1,IFERROR(ROUND(T65/H65,4),0)),IFERROR(ROUND(T65/H65,4),0)) -> 0 | AG65: =IFERROR(IF(VLOOKUP($B65,Shortage!$A:$M,AG$2,FALSE)="Shortage",1,IFERROR(ROUND(U65/I65,4),0)),IFERROR(ROUND(U65/I65,4),0)) -> 0 | AH65: =IFERROR(IF(VLOOKUP($B65,Shortage!$A:$M,AH$2,FALSE)="Shortage",1,IFERROR(ROUND(V65/J65,4),0)),IFERROR(ROUND(V65/J65,4),0)) -> 0 | AI65: =IFERROR(IF(VLOOKUP($B65,Shortage!$A:$M,AI$2,FALSE)="Shortage",1,IFERROR(ROUND(W65/K65,4),0)),IFERROR(ROUND(W65/K65,4),0)) -> 0 | ... AM65: =IFERROR(IF(VLOOKUP($B65,Shortage!$A:$M,AM$2,FALSE)="Shortage",1,IFERROR(ROUND(AA65/O65,4),0)),IFERROR(ROUND(AA65/O65,4),0)) -> 0 | AN65: =IFERROR(_xlfn.XLOOKUP(AB65,'2) หลักการคำนวน Table'!$C$3:$K$3,'2) หลักการคำนวน Table'!$C$3:$K$3,,1),INDEX('2) หลักการคำนวน Table'!$C$3:$K$3,1)) -> 1.06 | AO65: =IFERROR( _xlfn.XLOOKUP(AC65,'2) หลักการคำนวน Table'!$C$3:$K$3,'2) หลักการคำนวน Table'!$C$3:$K$3,,1), IF(AC65<MIN('2) หลักการคำนวน Table'!$C$3:$K$3), MIN('2) หลักการคำนวน Table'!$C$3:$K$3), MAX('2) หลักการคำนวน Table'!$C$3:$K$3) ) ) -> 0.9 | AP65: =IFERROR( _xlfn.XLOOKUP(AD65,'2) หลักการคำนวน Table'!$C$3:$K$3,'2) หลักการคำนวน Table'!$C$3:$K$3,,1), IF(AD65<MIN('2) หลักการคำนวน Table'!$C$3:$K$3), MIN('2) หลักการคำนวน Table'!$C$3:$K$3), MAX('2) หลักการคำนวน Table'!$C$3:$K$3) ) ) -> 0.9 | AQ65: =IFERROR( _xlfn.XLOOKUP(AE65,'2) หลักการคำนวน Table'!$C$3:$K$3,'2) หลักการคำนวน Table'!$C$3:$K$3,,1), IF(AE65<MIN('2) หลักการคำนวน Table'!$C$3:$K$3), MIN('2) หลักการคำนวน Table'!$C$3:$K$3), MAX('2) หลักการคำนวน Table'!$C$3:$K$3) ) ) -> 0.9 | AR65: =IFERROR( _xlfn.XLOOKUP(AF65,'2) หลักการคำนวน Table'!$C$3:$K$3,'2) หลักการคำนวน Table'!$C$3:$K$3,,1), IF(AF65<MIN('2) หลักการคำนวน Table'!$C$3:$K$3), MIN('2) หลักการคำนวน Table'!$C$3:$K$3), MAX('2) หลักการคำนวน Table'!$C$3:$K$3) ) ) -> 0.9 | AS65: =IFERROR( _xlfn.XLOOKUP(AG65,'2) หลักการคำนวน Table'!$C$3:$K$3,'2) หลักการคำนวน Table'!$C$3:$K$3,,1), IF(AG65<MIN('2) หลักการคำนวน Table'!$C$3:$K$3), MIN('2) หลักการคำนวน Table'!$C$3:$K$3), MAX('2) หลักการคำนวน Table'!$C$3:$K$3) ) ) -> 0.9 | AT65: =IFERROR( _xlfn.XLOOKUP(AH65,'2) หลักการคำนวน Table'!$C$3:$K$3,'2) หลักการคำนวน Table'!$C$3:$K$3,,1), IF(AH65<MIN('2) หลักการคำนวน Table'!$C$3:$K$3), MIN('2) หลักการคำนวน Table'!$C$3:$K$3), MAX('2) หลักการคำนวน Table'!$C$3:$K$3) ) ) -> 0.9 | AU65: =IFERROR( _xlfn.XLOOKUP(AI65,'2) หลักการคำนวน Table'!$C$3:$K$3,'2) หลักการคำนวน Table'!$C$3:$K$3,,1), IF(AI65<MIN('2) หลักการคำนวน Table'!$C$3:$K$3), MIN('2) หลักการคำนวน Table'!$C$3:$K$3), MAX('2) หลักการคำนวน Table'!$C$3:$K$3) ) ) -> 0.9 | AV65: =IFERROR( _xlfn.XLOOKUP(AJ65,'2) หลักการคำนวน Table'!$C$3:$K$3,'2) หลักการคำนวน Table'!$C$3:$K$3,,1), IF(AJ65<MIN('2) หลักการคำนวน Table'!$C$3:$K$3), MIN('2) หลักการคำนวน Table'!$C$3:$K$3), MAX('2) หลักการคำนวน Table'!$C$3:$K$3) ) ) -> 0.9 | ... AY65: =IFERROR( _xlfn.XLOOKUP(AM65,'2) หลักการคำนวน Table'!$C$3:$K$3,'2) หลักการคำนวน Table'!$C$3:$K$3,,1), IF(AM65<MIN('2) หลักการคำนวน Table'!$C$3:$K$3), MIN('2) หลักการคำนวน Table'!$C$3:$K$3), MAX('2) หลักการคำนวน Table'!$C$3:$K$3) ) ) -> 0.9 | AZ65: {=ROUND((_xlfn.XLOOKUP($C65,'2) หลักการคำนวน Table'!$A$4:$A$36, _xlfn.XLOOKUP(AN65,'2) หลักการคำนวน Table'!$C$3:$K$3,'2) หลักการคำนวน Table'!$C$4:$K$36,,-1)))*(_xlfn.XLOOKUP($C65,'2) หลักการคำนวน Table'!$A$4:$A$36, _xlfn.XLOOKUP($B65,'2) หลักการคำนวน Table'!$L$3:$Z$3,'2) หลักการคำนวน Table'!$L$4:$Z$36))),0)} -> #N/A | BA65: {=ROUND((_xlfn.XLOOKUP($C65,'2) หลักการคำนวน Table'!$A$4:$A$36, _xlfn.XLOOKUP(AO65,'2) หลักการคำนวน Table'!$C$3:$K$3,'2) หลักการคำนวน Table'!$C$4:$K$36,,-1)))*(_xlfn.XLOOKUP($C65,'2) หลักการคำนวน Table'!$A$4:$A$36, _xlfn.XLOOKUP($B65,'2) หลักการคำนวน Table'!$L$3:$Z$3,'2) หลักการคำนวน Table'!$L$4:$Z$36))),0)} -> #N/A | BB65: {=ROUND((_xlfn.XLOOKUP($C65,'2) หลักการคำนวน Table'!$A$4:$A$36, _xlfn.XLOOKUP(AP65,'2) หลักการคำนวน Table'!$C$3:$K$3,'2) หลักการคำนวน Table'!$C$4:$K$36,,-1)))*(_xlfn.XLOOKUP($C65,'2) หลักการคำนวน Table'!$A$4:$A$36, _xlfn.XLOOKUP($B65,'2) หลักการคำนวน Table'!$L$3:$Z$3,'2) หลักการคำนวน Table'!$L$4:$Z$36))),0)} -> #N/A | BC65: {=ROUND((_xlfn.XLOOKUP($C65,'2) หลักการคำนวน Table'!$A$4:$A$36, _xlfn.XLOOKUP(AQ65,'2) หลักการคำนวน Table'!$C$3:$K$3,'2) หลักการคำนวน Table'!$C$4:$K$36,,-1)))*(_xlfn.XLOOKUP($C65,'2) หลักการคำนวน Table'!$A$4:$A$36, _xlfn.XLOOKUP($B65,'2) หลักการคำนวน Table'!$L$3:$Z$3,'2) หลักการคำนวน Table'!$L$4:$Z$36))),0)} -> #N/A | BD65: {=ROUND((_xlfn.XLOOKUP($C65,'2) หลักการคำนวน Table'!$A$4:$A$36, _xlfn.XLOOKUP(AR65,'2) หลักการคำนวน Table'!$C$3:$K$3,'2) หลักการคำนวน Table'!$C$4:$K$36,,-1)))*(_xlfn.XLOOKUP($C65,'2) หลักการคำนวน Table'!$A$4:$A$36, _xlfn.XLOOKUP($B65,'2) หลักการคำนวน Table'!$L$3:$Z$3,'2) หลักการคำนวน Table'!$L$4:$Z$36))),0)} -> #N/A | BE65: {=ROUND((_xlfn.XLOOKUP($C65,'2) หลักการคำนวน Table'!$A$4:$A$36, _xlfn.XLOOKUP(AS65,'2) หลักการคำนวน Table'!$C$3:$K$3,'2) หลักการคำนวน Table'!$C$4:$K$36,,-1)))*(_xlfn.XLOOKUP($C65,'2) หลักการคำนวน Table'!$A$4:$A$36, _xlfn.XLOOKUP($B65,'2) หลักการคำนวน Table'!$L$3:$Z$3,'2) หลักการคำนวน Table'!$L$4:$Z$36))),0)} -> #N/A | BF65: {=ROUND((_xlfn.XLOOKUP($C65,'2) หลักการคำนวน Table'!$A$4:$A$36, _xlfn.XLOOKUP(AT65,'2) หลักการคำนวน Table'!$C$3:$K$3,'2) หลักการคำนวน Table'!$C$4:$K$36,,-1)))*(_xlfn.XLOOKUP($C65,'2) หลักการคำนวน Table'!$A$4:$A$36, _xlfn.XLOOKUP($B65,'2) หลักการคำนวน Table'!$L$3:$Z$3,'2) หลักการคำนวน Table'!$L$4:$Z$36))),0)} -> #N/A | BG65: {=ROUND((_xlfn.XLOOKUP($C65,'2) หลักการคำนวน Table'!$A$4:$A$36, _xlfn.XLOOKUP(AU65,'2) หลักการคำนวน Table'!$C$3:$K$3,'2) หลักการคำนวน Table'!$C$4:$K$36,,-1)))*(_xlfn.XLOOKUP($C65,'2) หลักการคำนวน Table'!$A$4:$A$36, _xlfn.XLOOKUP($B65,'2) หลักการคำนวน Table'!$L$3:$Z$3,'2) หลักการคำนวน Table'!$L$4:$Z$36))),0)} -> #N/A | ... BK65: {=ROUND((_xlfn.XLOOKUP($C65,'2) หลักการคำนวน Table'!$A$4:$A$36, _xlfn.XLOOKUP(AY65,'2) หลักการคำนวน Table'!$C$3:$K$3,'2) หลักการคำนวน Table'!$C$4:$K$36,,-1)))*(_xlfn.XLOOKUP($C65,'2) หลักการคำนวน Table'!$A$4:$A$36, _xlfn.XLOOKUP($B65,'2) หลักการคำนวน Table'!$L$3:$Z$3,'2) หลักการคำนวน Table'!$L$4:$Z$36))),0)} -> #N/A | BM65: 222218 | BN65: 600
A66: =VLOOKUP(C66,ASTBase!E:S,13,FALSE) -> #N/A | B66: PDC | C66: 5490000721 | D66: 66.6364 | E66: 98.0642 | F66: 79.5164 | G66: 67.6364 | H66: 89.9712 | I66: 102.0468 | J66: 131.148 | K66: 135.4332 | L66: 155.7234 | M66: 221 | N66: 211.7612 | O66: 103.147 | P66: 38.1084 | AB66: =IFERROR(IF(VLOOKUP($B66,Shortage!$A:$M,AB$2,FALSE)="Shortage",1,IFERROR(ROUND(P66/D66,4),0)),IFERROR(ROUND(P66/D66,4),0)) -> 0.5719 | AC66: =IFERROR(IF(VLOOKUP($B66,Shortage!$A:$M,AC$2,FALSE)="Shortage",1,IFERROR(ROUND(Q66/E66,4),0)),IFERROR(ROUND(Q66/E66,4),0)) -> 0 | AD66: =IFERROR(IF(VLOOKUP($B66,Shortage!$A:$M,AD$2,FALSE)="Shortage",1,IFERROR(ROUND(R66/F66,4),0)),IFERROR(ROUND(R66/F66,4),0)) -> 0 | AE66: =IFERROR(IF(VLOOKUP($B66,Shortage!$A:$M,AE$2,FALSE)="Shortage",1,IFERROR(ROUND(S66/G66,4),0)),IFERROR(ROUND(S66/G66,4),0)) -> 0 | AF66: =IFERROR(IF(VLOOKUP($B66,Shortage!$A:$M,AF$2,FALSE)="Shortage",1,IFERROR(ROUND(T66/H66,4),0)),IFERROR(ROUND(T66/H66,4),0)) -> 0 | AG66: =IFERROR(IF(VLOOKUP($B66,Shortage!$A:$M,AG$2,FALSE)="Shortage",1,IFERROR(ROUND(U66/I66,4),0)),IFERROR(ROUND(U66/I66,4),0)) -> 0 | AH66: =IFERROR(IF(VLOOKUP($B66,Shortage!$A:$M,AH$2,FALSE)="Shortage",1,IFERROR(ROUND(V66/J66,4),0)),IFERROR(ROUND(V66/J66,4),0)) -> 0 | AI66: =IFERROR(IF(VLOOKUP($B66,Shortage!$A:$M,AI$2,FALSE)="Shortage",1,IFERROR(ROUND(W66/K66,4),0)),IFERROR(ROUND(W66/K66,4),0)) -> 0 | ... AM66: =IFERROR(IF(VLOOKUP($B66,Shortage!$A:$M,AM$2,FALSE)="Shortage",1,IFERROR(ROUND(AA66/O66,4),0)),IFERROR(ROUND(AA66/O66,4),0)) -> 0 | AN66: =IFERROR(_xlfn.XLOOKUP(AB66,'2) หลักการคำนวน Table'!$C$3:$K$3,'2) หลักการคำนวน Table'!$C$3:$K$3,,1),INDEX('2) หลักการคำนวน Table'!$C$3:$K$3,1)) -> 0.9 | AO66: =IFERROR( _xlfn.XLOOKUP(AC66,'2) หลักการคำนวน Table'!$C$3:$K$3,'2) หลักการคำนวน Table'!$C$3:$K$3,,1), IF(AC66<MIN('2) หลักการคำนวน Table'!$C$3:$K$3), MIN('2) หลักการคำนวน Table'!$C$3:$K$3), MAX('2) หลักการคำนวน Table'!$C$3:$K$3) ) ) -> 0.9 | AP66: =IFERROR( _xlfn.XLOOKUP(AD66,'2) หลักการคำนวน Table'!$C$3:$K$3,'2) หลักการคำนวน Table'!$C$3:$K$3,,1), IF(AD66<MIN('2) หลักการคำนวน Table'!$C$3:$K$3), MIN('2) หลักการคำนวน Table'!$C$3:$K$3), MAX('2) หลักการคำนวน Table'!$C$3:$K$3) ) ) -> 0.9 | AQ66: =IFERROR( _xlfn.XLOOKUP(AE66,'2) หลักการคำนวน Table'!$C$3:$K$3,'2) หลักการคำนวน Table'!$C$3:$K$3,,1), IF(AE66<MIN('2) หลักการคำนวน Table'!$C$3:$K$3), MIN('2) หลักการคำนวน Table'!$C$3:$K$3), MAX('2) หลักการคำนวน Table'!$C$3:$K$3) ) ) -> 0.9 | AR66: =IFERROR( _xlfn.XLOOKUP(AF66,'2) หลักการคำนวน Table'!$C$3:$K$3,'2) หลักการคำนวน Table'!$C$3:$K$3,,1), IF(AF66<MIN('2) หลักการคำนวน Table'!$C$3:$K$3), MIN('2) หลักการคำนวน Table'!$C$3:$K$3), MAX('2) หลักการคำนวน Table'!$C$3:$K$3) ) ) -> 0.9 | AS66: =IFERROR( _xlfn.XLOOKUP(AG66,'2) หลักการคำนวน Table'!$C$3:$K$3,'2) หลักการคำนวน Table'!$C$3:$K$3,,1), IF(AG66<MIN('2) หลักการคำนวน Table'!$C$3:$K$3), MIN('2) หลักการคำนวน Table'!$C$3:$K$3), MAX('2) หลักการคำนวน Table'!$C$3:$K$3) ) ) -> 0.9 | AT66: =IFERROR( _xlfn.XLOOKUP(AH66,'2) หลักการคำนวน Table'!$C$3:$K$3,'2) หลักการคำนวน Table'!$C$3:$K$3,,1), IF(AH66<MIN('2) หลักการคำนวน Table'!$C$3:$K$3), MIN('2) หลักการคำนวน Table'!$C$3:$K$3), MAX('2) หลักการคำนวน Table'!$C$3:$K$3) ) ) -> 0.9 | AU66: =IFERROR( _xlfn.XLOOKUP(AI66,'2) หลักการคำนวน Table'!$C$3:$K$3,'2) หลักการคำนวน Table'!$C$3:$K$3,,1), IF(AI66<MIN('2) หลักการคำนวน Table'!$C$3:$K$3), MIN('2) หลักการคำนวน Table'!$C$3:$K$3), MAX('2) หลักการคำนวน Table'!$C$3:$K$3) ) ) -> 0.9 | AV66: =IFERROR( _xlfn.XLOOKUP(AJ66,'2) หลักการคำนวน Table'!$C$3:$K$3,'2) หลักการคำนวน Table'!$C$3:$K$3,,1), IF(AJ66<MIN('2) หลักการคำนวน Table'!$C$3:$K$3), MIN('2) หลักการคำนวน Table'!$C$3:$K$3), MAX('2) หลักการคำนวน Table'!$C$3:$K$3) ) ) -> 0.9 | ... AY66: =IFERROR( _xlfn.XLOOKUP(AM66,'2) หลักการคำนวน Table'!$C$3:$K$3,'2) หลักการคำนวน Table'!$C$3:$K$3,,1), IF(AM66<MIN('2) หลักการคำนวน Table'!$C$3:$K$3), MIN('2) หลักการคำนวน Table'!$C$3:$K$3), MAX('2) หลักการคำนวน Table'!$C$3:$K$3) ) ) -> 0.9 | AZ66: {=ROUND((_xlfn.XLOOKUP($C66,'2) หลักการคำนวน Table'!$A$4:$A$36, _xlfn.XLOOKUP(AN66,'2) หลักการคำนวน Table'!$C$3:$K$3,'2) หลักการคำนวน Table'!$C$4:$K$36,,-1)))*(_xlfn.XLOOKUP($C66,'2) หลักการคำนวน Table'!$A$4:$A$36, _xlfn.XLOOKUP($B66,'2) หลักการคำนวน Table'!$L$3:$Z$3,'2) หลักการคำนวน Table'!$L$4:$Z$36))),0)} -> #N/A | BA66: {=ROUND((_xlfn.XLOOKUP($C66,'2) หลักการคำนวน Table'!$A$4:$A$36, _xlfn.XLOOKUP(AO66,'2) หลักการคำนวน Table'!$C$3:$K$3,'2) หลักการคำนวน Table'!$C$4:$K$36,,-1)))*(_xlfn.XLOOKUP($C66,'2) หลักการคำนวน Table'!$A$4:$A$36, _xlfn.XLOOKUP($B66,'2) หลักการคำนวน Table'!$L$3:$Z$3,'2) หลักการคำนวน Table'!$L$4:$Z$36))),0)} -> #N/A | BB66: {=ROUND((_xlfn.XLOOKUP($C66,'2) หลักการคำนวน Table'!$A$4:$A$36, _xlfn.XLOOKUP(AP66,'2) หลักการคำนวน Table'!$C$3:$K$3,'2) หลักการคำนวน Table'!$C$4:$K$36,,-1)))*(_xlfn.XLOOKUP($C66,'2) หลักการคำนวน Table'!$A$4:$A$36, _xlfn.XLOOKUP($B66,'2) หลักการคำนวน Table'!$L$3:$Z$3,'2) หลักการคำนวน Table'!$L$4:$Z$36))),0)} -> #N/A | BC66: {=ROUND((_xlfn.XLOOKUP($C66,'2) หลักการคำนวน Table'!$A$4:$A$36, _xlfn.XLOOKUP(AQ66,'2) หลักการคำนวน Table'!$C$3:$K$3,'2) หลักการคำนวน Table'!$C$4:$K$36,,-1)))*(_xlfn.XLOOKUP($C66,'2) หลักการคำนวน Table'!$A$4:$A$36, _xlfn.XLOOKUP($B66,'2) หลักการคำนวน Table'!$L$3:$Z$3,'2) หลักการคำนวน Table'!$L$4:$Z$36))),0)} -> #N/A | BD66: {=ROUND((_xlfn.XLOOKUP($C66,'2) หลักการคำนวน Table'!$A$4:$A$36, _xlfn.XLOOKUP(AR66,'2) หลักการคำนวน Table'!$C$3:$K$3,'2) หลักการคำนวน Table'!$C$4:$K$36,,-1)))*(_xlfn.XLOOKUP($C66,'2) หลักการคำนวน Table'!$A$4:$A$36, _xlfn.XLOOKUP($B66,'2) หลักการคำนวน Table'!$L$3:$Z$3,'2) หลักการคำนวน Table'!$L$4:$Z$36))),0)} -> #N/A | BE66: {=ROUND((_xlfn.XLOOKUP($C66,'2) หลักการคำนวน Table'!$A$4:$A$36, _xlfn.XLOOKUP(AS66,'2) หลักการคำนวน Table'!$C$3:$K$3,'2) หลักการคำนวน Table'!$C$4:$K$36,,-1)))*(_xlfn.XLOOKUP($C66,'2) หลักการคำนวน Table'!$A$4:$A$36, _xlfn.XLOOKUP($B66,'2) หลักการคำนวน Table'!$L$3:$Z$3,'2) หลักการคำนวน Table'!$L$4:$Z$36))),0)} -> #N/A | BF66: {=ROUND((_xlfn.XLOOKUP($C66,'2) หลักการคำนวน Table'!$A$4:$A$36, _xlfn.XLOOKUP(AT66,'2) หลักการคำนวน Table'!$C$3:$K$3,'2) หลักการคำนวน Table'!$C$4:$K$36,,-1)))*(_xlfn.XLOOKUP($C66,'2) หลักการคำนวน Table'!$A$4:$A$36, _xlfn.XLOOKUP($B66,'2) หลักการคำนวน Table'!$L$3:$Z$3,'2) หลักการคำนวน Table'!$L$4:$Z$36))),0)} -> #N/A | BG66: {=ROUND((_xlfn.XLOOKUP($C66,'2) หลักการคำนวน Table'!$A$4:$A$36, _xlfn.XLOOKUP(AU66,'2) หลักการคำนวน Table'!$C$3:$K$3,'2) หลักการคำนวน Table'!$C$4:$K$36,,-1)))*(_xlfn.XLOOKUP($C66,'2) หลักการคำนวน Table'!$A$4:$A$36, _xlfn.XLOOKUP($B66,'2) หลักการคำนวน Table'!$L$3:$Z$3,'2) หลักการคำนวน Table'!$L$4:$Z$36))),0)} -> #N/A | ... BK66: {=ROUND((_xlfn.XLOOKUP($C66,'2) หลักการคำนวน Table'!$A$4:$A$36, _xlfn.XLOOKUP(AY66,'2) หลักการคำนวน Table'!$C$3:$K$3,'2) หลักการคำนวน Table'!$C$4:$K$36,,-1)))*(_xlfn.XLOOKUP($C66,'2) หลักการคำนวน Table'!$A$4:$A$36, _xlfn.XLOOKUP($B66,'2) หลักการคำนวน Table'!$L$3:$Z$3,'2) หลักการคำนวน Table'!$L$4:$Z$36))),0)} -> #N/A | BM66: 222218 | BN66: 750
